Workbook

Sheet Banks
A1: Bank Code | B1: Bank Name
B2: 2013 | C2: 2014 | D2: 2015 | E2: 2016 | F2: 2017 | G2: 2018 | H2: 2019 | I2: 2020 | J2: 2021 | K2: 2022 | L2: 2023 | M2: 2024
A3: 1 | B3: ABC Bank | C3: ABC Bank | D3: ABC Bank | E3: ABC Bank | F3: ABC Bank | G3: ABC Bank | H3: ABC Bank | I3: ABC Bank | J3: ABC Bank | L3: ABC Bank | M3: ABC Bank
A4: 2 | B4: Bank Of Africa Kenya Ltd | C4: Bank Of Africa Kenya Ltd | D4: Bank Of Africa Kenya Ltd | E4: Bank Of Africa Kenya Ltd | F4: Bank Of Africa Kenya Ltd | G4: Bank Of Africa Kenya Ltd | H4: Bank Of Africa Kenya Ltd | I4: Bank Of Africa Kenya Ltd | J4: Bank Of Africa Kenya Ltd | L4: Bank Of Africa Kenya Ltd | M4: Bank Of Africa Kenya Ltd
A5: 3 | B5: Bank of Baroda | C5: Bank of Baroda | D5: Bank of Baroda | E5: Bank of Baroda | F5: Bank of Baroda | G5: Bank of Baroda | H5: Bank of Baroda | I5: Bank of Baroda | J5: Bank of Baroda | L5: Bank of Baroda | M5: Bank of Baroda
A6: 4 | B6: Bank of India | C6: Bank of India | D6: Bank of India | E6: Bank of India | F6: Bank of India | G6: Bank of India | H6: Bank of India | I6: Bank of India | J6: Bank of India | L6: Bank of India | M6: Bank of India
A7: 5 | B7: Barclays Bank of Kenya | C7: Barclays Bank of Kenya | D7: Barclays Bank of Kenya | E7: Barclays Bank of Kenya | F7: Barclays Bank of Kenya | G7: Barclays Bank of Kenya | H7: Absa Bank Kenya | I7: Absa Bank Kenya | J7: Absa Bank Kenya | L7: Absa Bank Kenya | M7: Absa Bank Kenya
A8: 6 | B8: CFC Stanbic Bank | C8: CFC Stanbic Bank | D8: CFC Stanbic Bank | E8: Stanbic Bank | F8: Stanbic Bank | G8: Stanbic Bank | H8: Stanbic Bank | I8: Stanbic Bank | J8: Stanbic Bank | L8: Stanbic Bank | M8: Stanbic Bank
A9: 7 | B9: Chase Bank | C9: Chase Bank | D9: Chase Bank | E9: Placed under receivership in April 2016 and later take over by SBM bank in 2018 | F9: Placed under receivership in April 2016 and later take over by SBM bank in 2019 | H9: Chase Bank | I9: Chase Bank | J9: Chase Bank | L9: Chase Bank | M9: Chase Bank
A10: 8 | B10: Citibank | C10: Citibank | D10: Citibank | E10: Citibank | F10: Citibank | G10: Citibank | H10: Citibank | I10: Citibank | J10: Citibank | L10: Citibank | M10: Citibank
A11: 9 | B11: Commercial Bank of Africa | C11: Commercial Bank of Africa | D11: Commercial Bank of Africa | E11: Commercial Bank of Africa | F11: Commercial Bank of Africa | G11: Commercial Bank of Africa | H11: Merged with NIC to form NCBA
A12: 10 | B12: Consolidated Bank of Kenya | C12: Consolidated Bank of Kenya | D12: Consolidated Bank of Kenya | E12: Consolidated Bank of Kenya | F12: Consolidated Bank of Kenya | G12: Consolidated Bank of Kenya | H12: Consolidated Bank of Kenya | I12: Consolidated Bank of Kenya | J12: Consolidated Bank of Kenya | L12: Consolidated Bank of Kenya | M12: Consolidated Bank of Kenya
A13: 11 | B13: Co-operative Bank of Kenya | C13: Co-operative Bank of Kenya | D13: Co-operative Bank of Kenya | E13: Co-operative Bank of Kenya | F13: Co-operative Bank of Kenya | G13: Co-operative Bank of Kenya | H13: Co-operative Bank of Kenya | I13: Co-operative Bank of Kenya | J13: Co-operative Bank of Kenya | L13: Co-operative Bank of Kenya | M13: Co-operative Bank of Kenya
A14: 12 | B14: Credit Bank | C14: Credit Bank | D14: Credit Bank | E14: Credit Bank | F14: Credit Bank | G14: Credit Bank | H14: Credit Bank | I14: Credit Bank | J14: Credit Bank | L14: Credit Bank | M14: Credit Bank
A15: 13 | B15: Development Bank of Kenya | C15: Development Bank of Kenya | D15: Development Bank of Kenya | E15: Development Bank of Kenya | F15: Development Bank of Kenya | G15: Development Bank of Kenya | H15: Development Bank of Kenya | I15: Development Bank of Kenya | J15: Development Bank of Kenya | L15: Development Bank of Kenya | M15: Development Bank of Kenya
A16: 14 | B16: Diamond Trust Bank | C16: Diamond Trust Bank | D16: Diamond Trust Bank | E16: Diamond Trust Bank | F16: Diamond Trust Bank | G16: Diamond Trust Bank | H16: Diamond Trust Bank | I16: Diamond Trust Bank | J16: Diamond Trust Bank | L16: Diamond Trust Bank | M16: Diamond Trust Bank
A17: 15 | B17: Dubai Bank | C17: Dubai Bank | D17: Placed under liquidation in August 2015 | H17: Dubai Bank | I17: Dubai Bank | J17: Dubai Bank | L17: Dubai Bank | M17: Dubai Bank
A18: 16 | B18: EcoBank | C18: EcoBank | D18: EcoBank | E18: EcoBank | F18: EcoBank | G18: EcoBank | H18: EcoBank | I18: EcoBank | J18: EcoBank | L18: EcoBank | M18: EcoBank
A19: 17 | B19: Equatorial Commercial Bank | C19: Equatorial Commercial Bank | D19: Equatorial Commercial Bank | E19: Spire Bank | F19: Spire Bank | G19: Spire Bank | H19: Spire Bank | I19: Spire Bank | J19: Spire Bank | L19: Spire Bank | M19: Spire Bank
A20: 18 | B20: Equity Bank | C20: Equity Bank | D20: Equity Bank | E20: Equity Bank | F20: Equity Bank | G20: Equity Bank | H20: Equity Bank | I20: Equity Bank | J20: Equity Bank | L20: Equity Bank | M20: Equity Bank
A21: 19 | B21: Family Bank Limited | C21: Family Bank Limited | D21: Family Bank Limited | E21: Family Bank Limited | F21: Family Bank Limited | G21: Family Bank Limited | H21: Family Bank Limited | I21: Family Bank Limited | J21: Family Bank Limited | L21: Family Bank Limited | M21: Family Bank Limited
A22: 20 | B22: Fidelity Commercial Bank | C22: Fidelity Commercial Bank | D22: Fidelity Commercial Bank | E22: Put up for acquisition by CBK in 2016 and later acquired by SBM Bank in 2017 | F22: Put up for acquisition by CBK in 2016 and later acquired by SBM Bank in 2018 | G22: Put up for acquisition by CBK in 2016 and later acquired by SBM Bank in 2018 | H22: SBM Bank | I22: SBM Bank | J22: SBM Bank | L22: SBM Bank | M22: SBM Bank
A23: 21 | B23: Fina Bank | C23: GT Bank | D23: GT Bank | E23: GT Bank | F23: GT Bank | G23: GT Bank | H23: GT Bank | I23: GT Bank | J23: GT Bank | L23: GT Bank | M23: GT Bank
A24: 22 | B24: First Community Bank | C24: First Community Bank | D24: First Community Bank | E24: First Community Bank | F24: First Community Bank | G24: First Community Bank | H24: First Community Bank | I24: First Community Bank | J24: First Community Bank | L24: Premier Bank | M24: Premier Bank
A25: 23 | B25: Giro Commercial Bank | C25: Giro Commercial Bank | D25: Giro Commercial Bank | E25: Giro Commercial Bank | F25: Giro Commercial Bank | G25: Acquired by I&M in Feb 2017 and its operations merged with those of I&M | H25: Giro Commercial Bank | I25: Giro Commercial Bank | J25: Giro Commercial Bank | L25: Giro Commercial Bank | M25: Giro Commercial Bank
A26: 24 | B26: Guardian Bank | C26: Guardian Bank | D26: Guardian Bank | E26: Guardian Bank | F26: Guardian Bank | G26: Guardian Bank | H26: Guardian Bank | I26: Guardian Bank | J26: Guardian Bank | L26: Guardian Bank | M26: Guardian Bank
A27: 25 | B27: Gulf African Bank | C27: Gulf African Bank | D27: Gulf African Bank | E27: Gulf African Bank | F27: Gulf African Bank | G27: Gulf African Bank | H27: Gulf African Bank | I27: Gulf African Bank | J27: Gulf African Bank | L27: Gulf African Bank | M27: Gulf African Bank
A28: 26 | B28: Habib A.G.Zurich | C28: Habib A.G.Zurich | D28: Habib A.G.Zurich | E28: Habib A.G.Zurich | F28: Habib A.G.Zurich | G28: Habib A.G.Zurich | H28: Habib A.G.Zurich | I28: Habib A.G.Zurich | J28: Habib A.G.Zurich | L28: Habib A.G.Zurich | M28: Habib A.G.Zurich
A29: 27 | B29: Habib Bank Ltd | C29: Habib Bank Ltd | D29: Habib Bank Ltd | E29: Habib Bank Ltd | F29: Acquired by DTB Kenya in August 2017 | G29: Acquired by DTB Kenya in August 2017 | H29: Habib Bank Ltd | I29: Habib Bank Ltd | J29: Habib Bank Ltd | L29: Habib Bank Ltd | M29: Habib Bank Ltd
... A37: 35 | B37: National Bank of kenya | C37: National Bank of kenya | D37: National Bank of kenya | E37: National Bank of kenya | F37: National Bank of kenya | G37: National Bank of kenya | H37: National Bank of kenya | I37: National Bank of kenya | J37: National Bank of kenya | L37: National Bank of kenya | M37: National Bank of kenya
A38: 36 | B38: NIC Bank | C38: NIC Bank | D38: NIC Bank | E38: NIC Bank | F38: NIC Bank | G38: NIC Bank | H38: Merged with CBA to form NCBA
A39: 37 | B39: Oriental Commercial Bank Limited | C39: Oriental Commercial Bank Limited | D39: Oriental Commercial Bank Limited | E39: M-Oriental Bank Limited | F39: M-Oriental Bank Limited | G39: M-Oriental Bank Limited | H39: M-Oriental Bank Limited | I39: M-Oriental Bank Limited | J39: M-Oriental Bank Limited | L39: M-Oriental Bank Limited | M39: M-Oriental Bank Limited
A40: 38 | B40: Paramount Universal Bank | C40: Paramount Universal Bank | D40: Paramount Universal Bank | E40: Paramount Universal Bank | F40: Paramount Universal Bank | G40: Paramount Universal Bank | H40: Paramount Universal Bank | I40: Paramount Universal Bank | J40: Paramount Universal Bank | L40: Paramount Universal Bank | M40: Paramount Universal Bank
A41: 39 | B41: Prime Bank | C41: Prime Bank | D41: Prime Bank | E41: Prime Bank | F41: Prime Bank | G41: Prime Bank | H41: Prime Bank | I41: Prime Bank | J41: Prime Bank | L41: Prime Bank | M41: Prime Bank
A42: 40 | B42: Standard Chartered Bank | C42: Standard Chartered Bank | D42: Standard Chartered Bank | E42: Standard Chartered Bank | F42: Standard Chartered Bank | G42: Standard Chartered Bank | H42: Standard Chartered Bank | I42: Standard Chartered Bank | J42: Standard Chartered Bank | L42: Standard Chartered Bank | M42: Standard Chartered Bank
A43: 41 | B43: Trans-National Bank | C43: Trans-National Bank | D43: Trans-National Bank | E43: Trans-National Bank | F43: Trans-National Bank | G43: Trans-National Bank | H43: Trans-National Bank | I43: Access Bank | J43: Access Bank | L43: Access Bank | M43: Access Bank
A44: 42 | B44: United Bank for Africa | C44: United Bank for Africa | D44: United Bank for Africa | E44: United Bank for Africa | F44: United Bank for Africa | G44: United Bank for Africa | H44: United Bank for Africa | I44: United Bank for Africa | J44: United Bank for Africa | L44: United Bank for Africa | M44: United Bank for Africa
A45: 43 | B45: Victoria Commercial Bank | C45: Victoria Commercial Bank | D45: Victoria Commercial Bank | E45: Victoria Commercial Bank | F45: Victoria Commercial Bank | G45: Victoria Commercial Bank | H45: Victoria Commercial Bank | I45: Victoria Commercial Bank | J45: Victoria Commercial Bank | L45: Victoria Commercial Bank | M45: Victoria Commercial Bank
A46: 44 | G46: Mayfair Bank | H46: Mayfair Bank | I46: Mayfair Bank | J46: Mayfair Bank | L46: Mayfair Bank - CIB | M46: Mayfair Bank - CIB
A47: 45 | G47: Dubai Islamic Bank | H47: Dubai Islamic Bank | I47: Dubai Islamic Bank | J47: Dubai Islamic Bank | L47: Dubai Islamic Bank | M47: Dubai Islamic Bank
H48: NCBA | I48: NCBA | J48: NCBA | L48: NCBA | M48: NCBA

Sheet Data for analysis
B1: #
C2: 2014 | U2: 2015 | AS2: 2016 | BQ2: 2017 | CO2: 2018 | DM2: 2019 | EK2: 2020 | FI2: 2021 | GG2: 2022 | HE2: 2023 | IC2: 2024 | JA2: 2025
B3: Bank Name | C3: 41699 | I3: 41791 | O3: 41974 | U3: 42064 | AA3: 42156 | AG3: 42248 | AM3: 42339 | AS3: 42430 | AY3: 42522 | BE3: 42614 | BK3: 42705 | BQ3: 42795 | BW3: 42887 | CC3: 42979 | CI3: 43070 | CO3: 43160 | CU3: 43252 | DA3: 43344 | DG3: 43435 | DM3: 43525 | DS3: 43617 | DY3: 43709 | EE3: 43800 | EK3: 43891 | EQ3: 43983 | EW3: 44075 | FC3: 44166 | FI3: 44256 | FO3: 44348 | FU3: 44440 | GA3: 44531 | GG3: 44621 | GM3: 44713 | GS3: 44805 | GY3: 44896 | HE3: 44986 | HK3: 45078 | HQ3: 45170 | HW3: 45261 | IC3: 45352 | II3: 45444 | IO3: 45536 | IU3: 45627 | JA3: 45717 | JG3: 45809 | JM3: 45901 | JS3: 45992
C4: GDP | D4: Interest rate | E4: Inflation rate | F4: Asset Quality | G4: Mgt Efficiency | H4: ROA | I4: GDP | J4: Interest rate | K4: Inflation rate | L4: Asset Quality | M4: Mgt Efficiency | N4: ROA | O4: GDP | P4: Interest rate | Q4: Inflation rate | R4: Asset Quality | S4: Mgt Efficiency | T4: ROA | U4: GDP | V4: Interest rate | W4: Inflation rate | X4: Asset Quality | Y4: Mgt Efficiency | Z4: ROA | AA4: GDP | AB4: Interest rate | AC4: Inflation rate | AD4: Asset Quality | AE4: Mgt Efficiency | AF4: ROA | AG4: GDP | AH4: Interest rate | AI4: Inflation rate | AJ4: Asset Quality | AK4: Mgt Efficiency | AL4: ROA | AM4: GDP | AN4: Interest rate | AO4: Inflation rate | AP4: Asset Quality | AQ4: Mgt Efficiency | AR4: ROA | AS4: GDP | AT4: Interest rate | AU4: Inflation rate | AV4: Asset Quality | AW4: Mgt Efficiency | AX4: ROA | AY4: GDP | AZ4: Interest rate | BA4: Inflation rate | BB4: Asset Quality | BC4: Mgt Efficiency | BD4: ROA | BE4: GDP | BF4: Interest rate | BG4: Inflation rate | BH4: Asset Quality | BI4: Mgt Efficiency | BJ4: ROA | BK4: GDP | BL4: Interest rate | BM4: Inflation rate | BN4: Asset Quality | BO4: Mgt Efficiency | BP4: ROA | BQ4: GDP | BR4: Interest rate | BS4: Inflation rate | BT4: Asset Quality | BU4: Mgt Efficiency | BV4: ROA | BW4: GDP | BX4: Interest rate | BY4: Inflation rate | BZ4: Asset Quality | CA4: Mgt Efficiency | CB4: ROA | CC4: GDP | CD4: Interest rate | CE4: Inflation rate | CF4: Asset Quality | CG4: Mgt Efficiency | CH4: ROA | CI4: GDP | CJ4: Interest rate | CK4: Inflation rate | CL4: Asset Quality | CM4: Mgt Efficiency | CN4: ROA | CO4: GDP | CP4: Interest rate | CQ4: Inflation rate | CR4: Asset Quality | CS4: Mgt Efficiency | CT4: ROA | CU4: GDP | CV4: Interest rate | CW4: Inflation rate | CX4: Asset Quality | CY4: Mgt Efficiency | CZ4: ROA | DA4: GDP | DB4: Interest rate | DC4: Inflation rate | DD4: Asset Quality | DE4: Mgt Efficiency | DF4: ROA | DG4: GDP | DH4: Interest rate | DI4: Inflation rate | DJ4: Asset Quality | DK4: Mgt Efficiency | DL4: ROA | DM4: GDP | DN4: Interest rate | DO4: Inflation rate | DP4: Asset Quality | DQ4: Mgt Efficiency | DR4: ROA | DS4: GDP | DT4: Interest rate | DU4: Inflation rate | DV4: Asset Quality | DW4: Mgt Efficiency | DX4: ROA | DY4: GDP | DZ4: Interest rate | EA4: Inflation rate | EB4: Asset Quality | EC4: Mgt Efficiency | ED4: ROA | EE4: GDP | EF4: Interest rate | EG4: Inflation rate | EH4: Asset Quality | EI4: Mgt Efficiency | EJ4: ROA | EK4: GDP | EL4: Interest rate | EM4: Inflation rate | EN4: Asset Quality | EO4: Mgt Efficiency | EP4: ROA | EQ4: GDP | ER4: Interest rate | ES4: Inflation rate | ET4: Asset Quality | EU4: Mgt Efficiency | EV4: ROA | EW4: GDP | EX4: Interest rate | EY4: Inflation rate | EZ4: Asset Quality | FA4: Mgt Efficiency | FB4: ROA | FC4: GDP | FD4: Interest rate | FE4: Inflation rate | FF4: Asset Quality | FG4: Mgt Efficiency | FH4: ROA | FI4: GDP | FJ4: Interest rate | FK4: Inflation rate | FL4: Asset Quality | FM4: Mgt Efficiency | FN4: ROA | FO4: GDP | FP4: Interest rate | FQ4: Inflation rate | FR4: Asset Quality | FS4: Mgt Efficiency | FT4: ROA | FU4: GDP | FV4: Interest rate | FW4: Inflation rate | FX4: Asset Quality | FY4: Mgt Efficiency | FZ4: ROA | GA4: GDP | GB4: Interest rate | GC4: Inflation rate | GD4: Asset Quality | GE4: Mgt Efficiency | GF4: ROA | GG4: GDP | GH4: Interest rate | GI4: Inflation rate | GJ4: Asset Quality | GK4: Mgt Efficiency | GL4: ROA | GM4: GDP | GN4: Interest rate | GO4: Inflation rate | GP4: Asset Quality | GQ4: Mgt Efficiency | GR4: ROA | GS4: GDP | GT4: Interest rate | GU4: Inflation rate | GV4: Asset Quality | GW4: Mgt Efficiency | GX4: ROA | GY4: GDP | GZ4: Interest rate | HA4: Inflation rate | HB4: Asset Quality | HC4: Mgt Efficiency | HD4: ROA | HE4: GDP | HF4: Interest rate | HG4: Inflation rate | HH4: Asset Quality | HI4: Mgt Efficiency | HJ4: ROA | HK4: GDP | HL4: Interest rate | HM4: Inflation rate | HN4: Asset Quality | HO4: Mgt Efficiency | HP4: ROA | HQ4: GDP | HR4: Interest rate | HS4: Inflation rate | HT4: Asset Quality | HU4: Mgt Efficiency | HV4: ROA | HW4: GDP | HX4: Interest rate | HY4: Inflation rate | HZ4: Asset Quality | IA4: Mgt Efficiency | IB4: ROA | IC4: GDP | ID4: Interest rate | IE4: Inflation rate | IF4: Asset Quality | IG4: Mgt Efficiency | IH4: ROA | II4: GDP | IJ4: Interest rate | IK4: Inflation rate | IL4: Asset Quality | IM4: Mgt Efficiency | IN4: ROA | IO4: GDP | IP4: Interest rate | IQ4: Inflation rate | IR4: Asset Quality | IS4: Mgt Efficiency | IT4: ROA | IU4: GDP | IV4: Interest rate | IW4: Inflation rate | IX4: Asset Quality | IY4: Mgt Efficiency | IZ4: ROA | JA4: GDP | JB4: Interest rate | JC4: Inflation rate | JD4: Asset Quality | JE4: Mgt Efficiency | JF4: ROA | JG4: GDP | JH4: Interest rate | JI4: Inflation rate | JJ4: Asset Quality | JK4: Mgt Efficiency | JL4: ROA | JM4: GDP | JN4: Interest rate | JO4: Inflation rate | JP4: Asset Quality | JQ4: Mgt Efficiency | JR4: ROA | JS4: GDP | JT4: Interest rate | JU4: Inflation rate | JV4: Asset Quality | JW4: Mgt Efficiency | JX4: ROA
A5: 1 | B5: ABC Bank | C5: 0.052 | D5: 16.91 | E5: 0.0627 | F5: 0.045405928 | G5: 0.69514707 | H5: 0.014665198 | I5: 0.06 | J5: 0.1636 | K5: 0.0739 | L5: 0.067301025 | M5: 0.75249518 | N5: 0.011876546 | O5: 0.05 | P5: 0.1599 | Q5: 0.0602 | R5: 0.049227827 | S5: 0.92101622 | T5: 0.012568498 | U5: 0.057 | V5: 0.1546 | W5: 0.0631 | X5: 0.072964761 | Y5: 0.70283835 | Z5: 0.014215563 | AA5: 0.056 | AB5: 0.1606 | AC5: 0.0703 | AD5: 0.066403973 | AE5: 0.71869931 | AF5: 0.011677502 | AG5: 0.061 | AH5: 0.1682 | AI5: 0.0597 | AJ5: 0.1375945 | AK5: 0.68181462 | AL5: 0.011898201 | AM5: 0.05 | AN5: 0.183 | AO5: 0.0801 | AP5: 0.12730314 | AQ5: 0.95118861 | AR5: 0.012263735 | AS5: 0.038 | AT5: 0.1787 | AU5: 0.0645 | AV5: 0.13915209 | AW5: 0.6836856 | AX5: 0.014290063 | AY5: 0.038 | AZ5: 0.1818 | BA5: 0.058 | BB5: 0.13851823 | BC5: 0.68857683 | BD5: 0.013231178 | BE5: 0.044 | BF5: 0.1386 | BG5: 0.0634 | BH5: 0.14267298 | BI5: 0.72469925 | BJ5: 0.0086487484 | BK5: 0.042 | BL5: 0.1366 | BM5: 0.0635 | BN5: 0.13826028 | BO5: 0.78618419 | BP5: 0.0070709851 | BQ5: 0.054 | BR5: 0.1361 | BS5: 0.1028 | BT5: 0.145888 | BU5: 0.50107294 | BV5: 0.0076268125 | BW5: 0.033 | BX5: 0.1366 | BY5: 0.0921 | BZ5: 0.1630576 | CA5: 0.74811677 | CB5: 0.0024653854 | CC5: 0.032 | CD5: 0.1369 | CE5: 0.0706 | CF5: 0.17252498 | CG5: 0.77380868 | CH5: 0.0060845457 | CI5: 0.038 | CJ5: 0.1364 | CK5: 0.045 | CL5: 0.15874312 | CM5: 0.81737303 | CN5: 0.0058056071 | CO5: 0.052 | CP5: 0.1349 | CQ5: 0.0418 | CR5: 0.17174388 | CS5: 0.81234593 | CT5: 0.0057922888 | CU5: 0.061 | CV5: 0.1322 | CW5: 0.0428 | CX5: 0.17930718 | CY5: 0.76857214 | CZ5: 0.0043080763 | DA5: 0.053 | DB5: 0.1266 | DC5: 0.057 | DD5: 0.17867807 | DE5: 0.81665917 | DF5: 0.0049546095 | DG5: 0.056 | DH5: 0.1251 | DI5: 0.0571 | DJ5: 0.16954524 | DK5: 0.79893866 | DL5: 0.0024144746 | DM5: 0.048 | DN5: 0.1251 | DO5: 0.0435 | DP5: 0.18773631 | DQ5: 0.8674733 | DR5: 0.0032608944 | DS5: 0.06 | DT5: 0.1247 | DU5: 0.057 | DV5: 0.18647538 | DW5: 0.88082873 | DX5: 0.0026124132 | DY5: 0.05 | DZ5: 0.1247 | EA5: 0.0383 | EB5: 0.19126766 | EC5: 0.87180774 | ED5: 0.0023845334 | EE5: 0.051 | EF5: 0.1224 | EG5: 0.0582 | EH5: 0.13085691 | EI5: 0.860361 | EJ5: 0.0042758337 | EK5: 0.046 | EL5: 0.1209 | EM5: 0.0584 | EN5: 0.13139371 | EO5: 0.87497033 | EP5: 0.0034968931 | EQ5: -0.041 | ER5: 0.1189 | ES5: 0.0459 | ET5: 0.12748493 | EU5: 0.87998479 | EV5: 0.0028031363 | EW5: -0.036 | EX5: 0.1175 | EY5: 0.042 | EZ5: 0.12663912 | FA5: 0.87012384 | FB5: 0.0020668948 | FC5: -0.003 | FD5: 0.1202 | FE5: 0.0562 | FF5: 0.11320991 | FG5: 0.82082289 | FH5: 0.0044284159 | FI5: 0.024 | FJ5: 0.1205 | FK5: 0.059 | FL5: 0.11484447 | FM5: 0.87491188 | FN5: 0.0027421819 | FO5: 0.103 | FP5: 0.1202 | FQ5: 0.0632 | FR5: 0.10906695 | FS5: 0.87395909 | FT5: 0.0023150966 | FU5: 0.094 | FV5: 0.121 | FW5: 0.0691 | FX5: 0.10920678 | FY5: 0.88060412 | FZ5: 0.0019425933 | GA5: 0.076 | GB5: 0.1216 | GC5: 0.0573 | GD5: 0.14880928 | GE5: 0.80734621 | GF5: 0.0031455572 | GG5: 0.059 | GH5: 0.1215 | GI5: 0.0556 | GJ5: 0.15040826 | GK5: 0.87302602 | GL5: 0.002561733 | GM5: 0.049 | GN5: 0.1227 | GO5: 0.0791 | GP5: 0.15300356 | GQ5: 0.85590731 | GR5: 0.0021991338 | GS5: 0.046 | GT5: 0.1241 | GU5: 0.0918 | GV5: 0.15578729 | GW5: 0.84648683 | GX5: 0.0021366627 | GY5: 0.049 | GZ5: 0.1267 | HA5: 0.0906 | HB5: 0.15478643 | HC5: 0.79403862 | HD5: 0.0064317379 | HE5: 0.054 | HF5: 0.1309 | HG5: 0.0919 | HH5: 0.15518994 | HI5: 0.85069674 | HJ5: 0.0033349274 | HK5: 0.055 | HL5: 0.1331 | HM5: 0.0788 | HN5: 0.15153975 | HO5: 0.87171191 | HP5: 0.0023473094 | HQ5: 0.06 | HR5: 0.1398 | HS5: 0.0678 | HT5: 0.15020369 | HU5: 0.86683426 | HV5: 0.0021632741 | HW5: 0.056 | HX5: 0.1463 | HY5: 0.0663 | HZ5: 0.12344076 | IA5: 0.7998862 | IB5: 0.0063156477 | IC5: 0.049 | ID5: 0.1628 | IE5: 0.057 | IF5: 0.15069574 | IG5: 0.85384624 | IH5: 0.0030124574 | II5: 0.046 | IJ5: 0.1685 | IK5: 0.0622 | IL5: 0.15425203 | IM5: 0.86312553 | IN5: 0.002124592 | IO5: 0.04 | IP5: 0.1691 | IQ5: 0.0356 | IR5: 0.15524075 | IS5: 0.8682173 | IT5: 0.0019380295 | IU5: 0.047 | IV5: 0.1689 | IW5: 0.0299 | IX5: 0.22867369 | IY5: 0.83869548 | IZ5: -0.0068997193 | JA5: 0.049 | JB5: 0.1577 | JC5: 0.0362 | JD5: 0.2288022 | JE5: 0.8776199 | JF5: 0.0026050696 | JG5: 0.05 | JH5: 0.1528 | JI5: 0.0382 | JJ5: 0.23309382 | JK5: 0.76668245 | JL5: 0.0020553192 | JM5: 0.049 | JN5: 0.1507 | JO5: 0.0458 | JP5: 0.23764501 | JQ5: 0.71645881 | JR5: 0.0017758457 | JS5: 0.05 | JT5: 0.1481 | JU5: 0.0449 | JV5: 0.39309023 | JW5: 0.72501588 | JX5: -0.015733347
A6: 2 | B6: Bank Of Africa Kenya Ltd | C6: 0.052 | D6: 0.1691 | E6: 0.0627 | F6: 0.032327879 | G6: 0.67287873 | H6: 0.01288096 | I6: 0.06 | J6: 0.1636 | K6: 0.0739 | L6: 0.030167236 | M6: 0.69752021 | N6: 0.011153877 | O6: 0.05 | P6: 0.1599 | Q6: 0.0602 | R6: 0.026947056 | S6: 0.81050196 | T6: 0.00250857 | U6: 0.057 | V6: 0.1546 | W6: 0.0631 | X6: 0.027403626 | Y6: 0.8056459 | Z6: 0.0067034203 | AA6: 0.056 | AB6: 0.1606 | AC6: 0.0703 | AD6: 0.058406729 | AE6: 0.79532916 | AF6: 0.001757349 | AG6: 0.061 | AH6: 0.1682 | AI6: 0.0597 | AJ6: 0.059383148 | AK6: 0.75397028 | AL6: 0.0028677766 | AM6: 0.05 | AN6: 0.183 | AO6: 0.0801 | AP6: 0.18863187 | AQ6: 0.80425478 | AR6: -0.015565384 | AS6: 0.038 | AT6: 0.1787 | AU6: 0.0645 | AV6: 0.19032766 | AW6: 0.53845109 | AX6: -0.0051579854 | AY6: 0.038 | AZ6: 0.1818 | BA6: 0.058 | BB6: 0.18647322 | BC6: 0.84566727 | BD6: 0.00049540885 | BE6: 0.044 | BF6: 0.1386 | BG6: 0.0634 | BH6: 0.19306604 | BI6: 0.86493421 | BJ6: -8.1330017e-05 | BK6: 0.042 | BL6: 0.1366 | BM6: 0.0635 | BN6: 0.20670632 | BO6: 0.77138878 | BP6: 0.00016715101 | BQ6: 0.054 | BR6: 0.1361 | BS6: 0.1028 | BT6: 0.19970199 | BU6: 0.69008776 | BV6: 0.00060415343 | BW6: 0.033 | BX6: 0.1366 | BY6: 0.0921 | BZ6: 0.19143232 | CA6: 0.67538568 | CB6: 0.0010957039 | CC6: 0.032 | CD6: 0.1369 | CE6: 0.0706 | CF6: 0.20965511 | CG6: 1.0599959 | CH6: 0.00018122868 | CI6: 0.038 | CJ6: 0.1364 | CK6: 0.045 | CL6: 0.21972985 | CM6: 0.76644888 | CN6: 0.0012273321 | CO6: 0.052 | CP6: 0.1349 | CQ6: 0.0418 | CR6: 0.23679287 | CS6: 0.69758628 | CT6: 0.0013115377 | CU6: 0.061 | CV6: 0.1322 | CW6: 0.0428 | CX6: 0.25175574 | CY6: 0.74675751 | CZ6: 0.002212048 | DA6: 0.053 | DB6: 0.1266 | DC6: 0.057 | DD6: 0.24671314 | DE6: 0.78924885 | DF6: 0.0013391842 | DG6: 0.056 | DH6: 0.1251 | DI6: 0.0571 | DJ6: 0.25280432 | DK6: 0.78837838 | DL6: 0.0033517846 | DM6: 0.048 | DN6: 0.1251 | DO6: 0.0435 | DP6: 0.25031875 | DQ6: 0.79668123 | DR6: 0.002511444 | DS6: 0.06 | DT6: 0.1247 | DU6: 0.057 | DV6: 0.24815695 | DW6: 0.76942149 | DX6: 0.0048012365 | DY6: 0.05 | DZ6: 0.1247 | EA6: 0.0383 | EB6: 0.2387427 | EC6: 0.85364873 | ED6: 0.0028891699 | EE6: 0.051 | EF6: 0.1224 | EG6: 0.0582 | EH6: 0.29273458 | EI6: 1.0827048 | EJ6: -0.043831204 | EK6: 0.046 | EL6: 0.1209 | EM6: 0.0584 | EN6: 0.28133853 | EO6: 1.3772643 | EP6: -0.024944673 | EQ6: -0.041 | ER6: 0.1189 | ES6: 0.0459 | ET6: 0.26775902 | EU6: 0.94072015 | EV6: -0.0075461757 | EW6: -0.036 | EX6: 0.1175 | EY6: 0.042 | EZ6: 0.26340546 | FA6: 0.94924052 | FB6: -0.0064882858 | FC6: -0.003 | FD6: 0.1202 | FE6: 0.0562 | FF6: 0.28508963 | FG6: 1.00056 | FH6: -0.0087881995 | FI6: 0.024 | FJ6: 0.1205 | FK6: 0.059 | FL6: 0.27458928 | FM6: 0.89558897 | FN6: -0.0015253904 | FO6: 0.103 | FP6: 0.1202 | FQ6: 0.0632 | FR6: 0.28520716 | FS6: 0.8960996 | FT6: -0.002690454 | FU6: 0.094 | FV6: 0.121 | FW6: 0.0691 | FX6: 0.28245981 | FY6: 0.84526987 | FZ6: 0.0001440046 | GA6: 0.076 | GB6: 0.1216 | GC6: 0.0573 | GD6: 0.25848905 | GE6: 0.6834473 | GF6: 0.004908419 | GG6: 0.059 | GH6: 0.1215 | GI6: 0.0556 | GJ6: 0.24504571 | GK6: 0.77183874 | GL6: 0.0051673904 | GM6: 0.049 | GN6: 0.1227 | GO6: 0.0791 | GP6: 0.24207486 | GQ6: 0.72783466 | GR6: 0.0058326096 | GS6: 0.046 | GT6: 0.1241 | GU6: 0.0918 | GV6: 0.16872856 | GW6: 0.70948811 | GX6: 0.0047625794 | GY6: 0.049 | GZ6: 0.1267 | HA6: 0.0906 | HB6: 0.16771408 | HC6: 0.70047216 | HD6: 0.0042315346 | HE6: 0.054 | HF6: 0.1309 | HG6: 0.0919 | HH6: 0.1785937 | HI6: 0.60244762 | HJ6: 0.0094465559 | HK6: 0.055 | HL6: 0.1331 | HM6: 0.0788 | HN6: 0.15318046 | HO6: 0.61812362 | HP6: 0.0083125811 | HQ6: 0.06 | HR6: 0.1398 | HS6: 0.0678 | HT6: 0.15372062 | HU6: 0.64081987 | HV6: 0.0061894302 | HW6: 0.056 | HX6: 0.1463 | HY6: 0.0663 | HZ6: 0.15731285 | IA6: 0.65259977 | IB6: 0.005587334 | IC6: 0.049 | ID6: 0.1628 | IE6: 0.057 | IF6: 0.14830829 | IG6: 0.76441373 | IH6: 0.0057358042 | II6: 0.046 | IJ6: 0.1685 | IK6: 0.0622 | IL6: 0.11793666 | IM6: 0.75220846 | IN6: 0.00504826 | IO6: 0.04 | IP6: 0.1691 | IQ6: 0.0356 | IR6: 0.11966432 | IS6: 0.76087805 | IT6: 0.0035882813 | IU6: 0.047 | IV6: 0.1689 | IW6: 0.0299 | IX6: 0.15122875 | IY6: 0.78113087 | IZ6: 0.0021846946 | JA6: 0.049 | JB6: 0.1577 | JC6: 0.0362 | JD6: 0.14411239 | JE6: 0.87505092 | JF6: 0.0016121182 | JG6: 0.05 | JH6: 0.1528 | JI6: 0.0382 | JJ6: 0.13977219 | JK6: 0.84047531 | JL6: 0.0024273585 | JM6: 0.049 | JN6: 0.1507 | JO6: 0.0458 | JP6: 0.12550751 | JQ6: 0.7962092 | JR6: 0.0046963938 | JS6: 0.05 | JT6: 0.1481 | JU6: 0.0449 | JV6: 0.13071812 | JW6: 0.7498566 | JX6: 0.0059916911
A7: 3 | B7: Bank of Baroda | C7: 0.052 | D7: 0.1691 | E7: 0.0627 | F7: 0.021058722 | G7: 0.25646167 | H7: 0.034447597 | I7: 0.06 | J7: 0.1636 | K7: 0.0739 | L7: 0.024344327 | M7: 0.22149916 | N7: 0.035118625 | O7: 0.05 | P7: 0.1599 | Q7: 0.0602 | R7: 0.032244372 | S7: 0.23456884 | T7: 0.038904719 | U7: 0.057 | V7: 0.1546 | W7: 0.0631 | X7: 0.034698387 | Y7: 0.23893924 | Z7: 0.033288373 | AA7: 0.056 | AB7: 0.1606 | AC7: 0.0703 | AD7: 0.033980781 | AE7: 0.21146717 | AF7: 0.034205155 | AG7: 0.061 | AH7: 0.1682 | AI7: 0.0597 | AJ7: 0.059620179 | AK7: 0.23803781 | AL7: 0.027525927 | AM7: 0.05 | AN7: 0.183 | AO7: 0.0801 | AP7: 0.064566793 | AQ7: 0.23726095 | AR7: 0.031141758 | AS7: 0.038 | AT7: 0.1787 | AU7: 0.0645 | AV7: 0.06221127 | AW7: 0.20017036 | AX7: 0.032707596 | AY7: 0.038 | AZ7: 0.1818 | BA7: 0.058 | BB7: 0.088309465 | BC7: 0.20425135 | BD7: 0.036029753 | BE7: 0.044 | BF7: 0.1386 | BG7: 0.0634 | BH7: 0.081388104 | BI7: 0.19986269 | BJ7: 0.035050851 | BK7: 0.042 | BL7: 0.1366 | BM7: 0.0635 | BN7: 0.077964133 | BO7: 0.19608727 | BP7: 0.039007956 | BQ7: 0.054 | BR7: 0.1361 | BS7: 0.1028 | BT7: 0.081637039 | BU7: 0.22313787 | BV7: 0.033322153 | BW7: 0.033 | BX7: 0.1366 | BY7: 0.0921 | BZ7: 0.067305216 | CA7: 0.72574189 | CB7: 0.042473332 | CC7: 0.032 | CD7: 0.1369 | CE7: 0.0706 | CF7: 0.060282907 | CG7: 0.17004285 | CH7: 0.041336309 | CI7: 0.038 | CJ7: 0.1364 | CK7: 0.045 | CL7: 0.055391551 | CM7: 0.17366457 | CN7: 0.043822669 | CO7: 0.052 | CP7: 0.1349 | CQ7: 0.0418 | CR7: 0.07639071 | CS7: 0.21485633 | CT7: 0.033894131 | CU7: 0.061 | CV7: 0.1322 | CW7: 0.0428 | CX7: 0.076227022 | CY7: 0.21447674 | CZ7: 0.031622889 | DA7: 0.053 | DB7: 0.1266 | DC7: 0.057 | DD7: 0.07771036 | DE7: 0.17214961 | DF7: 0.048573557 | DG7: 0.056 | DH7: 0.1251 | DI7: 0.0571 | DJ7: 0.081086687 | DK7: 0.18798401 | DL7: 0.035862585 | DM7: 0.048 | DN7: 0.1251 | DO7: 0.0435 | DP7: 0.08287942 | DQ7: 0.22158971 | DR7: 0.028789412 | DS7: 0.06 | DT7: 0.1247 | DU7: 0.057 | DV7: 0.084065664 | DW7: 0.18291901 | DX7: 0.029141014 | DY7: 0.05 | DZ7: 0.1247 | EA7: 0.0383 | EB7: 0.0804182 | EC7: 0.17956607 | ED7: 0.030887078 | EE7: 0.051 | EF7: 0.1224 | EG7: 0.0582 | EH7: 0.076483247 | EI7: 0.19486251 | EJ7: 0.030735054 | EK7: 0.046 | EL7: 0.1209 | EM7: 0.0584 | EN7: 0.077503868 | EO7: 0.2482057 | EP7: 0.028099564 | EQ7: -0.041 | ER7: 0.1189 | ES7: 0.0459 | ET7: 0.10772167 | EU7: 0.18703355 | EV7: 0.026258817 | EW7: -0.036 | EX7: 0.1175 | EY7: 0.042 | EZ7: 0.1060427 | FA7: 0.16942235 | FB7: 0.027115647 | FC7: -0.003 | FD7: 0.1202 | FE7: 0.0562 | FF7: 0.11193958 | FG7: 0.18666945 | FH7: 0.029648828 | FI7: 0.024 | FJ7: 0.1205 | FK7: 0.059 | FL7: 0.106632 | FM7: 0.20733173 | FN7: 0.0240462 | FO7: 0.103 | FP7: 0.1202 | FQ7: 0.0632 | FR7: 0.117694 | FS7: 0.21569625 | FT7: 0.025220106 | FU7: 0.094 | FV7: 0.121 | FW7: 0.0691 | FX7: 0.10694165 | FY7: 0.19206356 | FZ7: 0.027083967 | GA7: 0.076 | GB7: 0.1216 | GC7: 0.0573 | GD7: 0.095115951 | GE7: 0.19477562 | GF7: 0.030393997 | GG7: 0.059 | GH7: 0.1215 | GI7: 0.0556 | GJ7: 0.096935843 | GK7: 0.21931992 | GL7: 0.0258583 | GM7: 0.049 | GN7: 0.1227 | GO7: 0.0791 | GP7: 0.092520483 | GQ7: 0.18052065 | GR7: 0.026863262 | GS7: 0.046 | GT7: 0.1241 | GU7: 0.0918 | GV7: 0.089668955 | GW7: 0.18491652 | GX7: 0.026756501 | GY7: 0.049 | GZ7: 0.1267 | HA7: 0.0906 | HB7: 0.085880264 | HC7: 0.18512829 | HD7: 0.027831529 | HE7: 0.054 | HF7: 0.1309 | HG7: 0.0919 | HH7: 0.0900765 | HI7: 0.21305322 | HJ7: 0.021716975 | HK7: 0.055 | HL7: 0.1331 | HM7: 0.0788 | HN7: 0.089856569 | HO7: 0.19048199 | HP7: 0.026498352 | HQ7: 0.06 | HR7: 0.1398 | HS7: 0.0678 | HT7: 0.082252807 | HU7: 0.19835116 | HV7: 0.026595827 | HW7: 0.056 | HX7: 0.1463 | HY7: 0.0663 | HZ7: 0.073452687 | IA7: 0.19873036 | IB7: 0.028835824 | IC7: 0.049 | ID7: 0.1628 | IE7: 0.057 | IF7: 0.12617333 | IG7: 0.28255742 | IH7: 0.021978074 | II7: 0.046 | IJ7: 0.1685 | IK7: 0.0622 | IL7: 0.12686083 | IM7: 0.24703613 | IN7: 0.020507023 | IO7: 0.04 | IP7: 0.1691 | IQ7: 0.0356 | IR7: 0.1213054 | IS7: 0.27382971 | IT7: 0.018883269 | IU7: 0.047 | IV7: 0.1689 | IW7: 0.0299 | IX7: 0.10995614 | IY7: 0.29726281 | IZ7: 0.020184042 | JA7: 0.049 | JB7: 0.1577 | JC7: 0.0362 | JD7: 0.11492406 | JE7: 0.25891748 | JF7: 0.022791603 | JG7: 0.05 | JH7: 0.1528 | JI7: 0.0382 | JJ7: 0.11303348 | JK7: 0.22636836 | JL7: 0.024862512 | JM7: 0.049 | JN7: 0.1507 | JO7: 0.0458 | JP7: 0.11262567 | JQ7: 0.2203359 | JR7: 0.026741275 | JS7: 0.05 | JT7: 0.1481 | JU7: 0.0449 | JV7: 0.10923001 | JW7: 0.23115092 | JX7: 0.03155936
A8: 4 | B8: Bank of India | C8: 0.052 | D8: 0.1691 | E8: 0.0627 | F8: 0.0085097743 | G8: 0.39044081 | H8: 0.020452215 | I8: 0.06 | J8: 0.1636 | K8: 0.0739 | L8: 0.0081603867 | M8: 0.29130486 | N8: 0.026117232 | O8: 0.05 | P8: 0.1599 | Q8: 0.0602 | R8: 0.0055611898 | S8: 0.25508891 | T8: 0.031380052 | U8: 0.057 | V8: 0.1546 | W8: 0.0631 | X8: 0.0051136259 | Y8: 0.29889093 | Z8: 0.026957164 | AA8: 0.056 | AB8: 0.1606 | AC8: 0.0703 | AD8: 0.0051341698 | AE8: 0.26075067 | AF8: 0.028360671 | AG8: 0.061 | AH8: 0.1682 | AI8: 0.0597 | AJ8: 0.0050168691 | AK8: 0.25215775 | AL8: 0.029903764 | AM8: 0.05 | AN8: 0.183 | AO8: 0.0801 | AP8: 0.019845835 | AQ8: 0.25245545 | AR8: 0.028953044 | AS8: 0.038 | AT8: 0.1787 | AU8: 0.0645 | AV8: 0.0092053947 | AW8: 0.23481547 | AX8: 0.039694705 | AY8: 0.038 | AZ8: 0.1818 | BA8: 0.058 | BB8: 0.021687728 | BC8: 0.20821251 | BD8: 0.035328383 | BE8: 0.044 | BF8: 0.1386 | BG8: 0.0634 | BH8: 0.014598752 | BI8: 0.20087433 | BJ8: 0.035825875 | BK8: 0.042 | BL8: 0.1366 | BM8: 0.0635 | BN8: 0.013750301 | BO8: 0.18951919 | BP8: 0.036473462 | BQ8: 0.054 | BR8: 0.1361 | BS8: 0.1028 | BT8: 0.011434085 | BU8: 0.18771859 | BV8: 0.037171135 | BW8: 0.033 | BX8: 0.1366 | BY8: 0.0921 | BZ8: 0.023662302 | CA8: 0.178425 | CB8: 0.033858732 | CC8: 0.032 | CD8: 0.1369 | CE8: 0.0706 | CF8: 0.029373642 | CG8: 0.17478793 | CH8: 0.035382189 | CI8: 0.038 | CJ8: 0.1364 | CK8: 0.045 | CL8: 0.020298168 | CM8: 0.17078772 | CN8: 0.039995335 | CO8: 0.052 | CP8: 0.1349 | CQ8: 0.0418 | CR8: 0.023144418 | CS8: 0.19744698 | CT8: 0.034135148 | CU8: 0.061 | CV8: 0.1322 | CW8: 0.0428 | CX8: 0.037821235 | CY8: 0.18087041 | CZ8: 0.030803882 | DA8: 0.053 | DB8: 0.1266 | DC8: 0.057 | DD8: 0.037390917 | DE8: 0.20373459 | DF8: 0.042444594 | DG8: 0.056 | DH8: 0.1251 | DI8: 0.0571 | DJ8: 0.06659609 | DK8: 0.19399564 | DL8: 0.032435743 | DM8: 0.048 | DN8: 0.1251 | DO8: 0.0435 | DP8: 0.094023853 | DQ8: 0.17308476 | DR8: 0.035685812 | DS8: 0.06 | DT8: 0.1247 | DU8: 0.057 | DV8: 0.093354898 | DW8: 0.15601191 | DX8: 0.035641848 | DY8: 0.05 | DZ8: 0.1247 | EA8: 0.0383 | EB8: 0.090684186 | EC8: 0.15890146 | ED8: 0.033479495 | EE8: 0.051 | EF8: 0.1224 | EG8: 0.0582 | EH8: 0.085554944 | EI8: 0.16014163 | EJ8: 0.037387951 | EK8: 0.046 | EL8: 0.1209 | EM8: 0.0584 | EN8: 0.070102598 | EO8: 0.15854953 | EP8: 0.038812628 | EQ8: -0.041 | ER8: 0.1189 | ES8: 0.0459 | ET8: 0.070392861 | EU8: 0.16584227 | EV8: 0.034503103 | EW8: -0.036 | EX8: 0.1175 | EY8: 0.042 | EZ8: 0.06524467 | FA8: 0.16503957 | FB8: 0.03306708 | FC8: -0.003 | FD8: 0.1202 | FE8: 0.0562 | FF8: 0.064938122 | FG8: 0.16209224 | FH8: 0.034697625 | FI8: 0.024 | FJ8: 0.1205 | FK8: 0.059 | FL8: 0.067221619 | FM8: 0.1718153 | FN8: 0.032820995 | FO8: 0.103 | FP8: 0.1202 | FQ8: 0.0632 | FR8: 0.048919222 | FS8: 0.14381526 | FT8: 0.03613568 | FU8: 0.094 | FV8: 0.121 | FW8: 0.0691 | FX8: 0.046996673 | FY8: 0.16553527 | FZ8: 0.036180577 | GA8: 0.076 | GB8: 0.1216 | GC8: 0.0573 | GD8: 0.038601894 | GE8: 0.14663052 | GF8: 0.036109844 | GG8: 0.059 | GH8: 0.1215 | GI8: 0.0556 | GJ8: 0.029025729 | GK8: 0.15708413 | GL8: 0.03376416 | GM8: 0.049 | GN8: 0.1227 | GO8: 0.0791 | GP8: 0.052518491 | GQ8: 0.14937276 | GR8: 0.029296107 | GS8: 0.046 | GT8: 0.1241 | GU8: 0.0918 | GV8: 0.042240872 | GW8: 0.143508 | GX8: 0.03219609 | GY8: 0.049 | GZ8: 0.1267 | HA8: 0.0906 | HB8: 0.039390872 | HC8: 0.14771189 | HD8: 0.031471051 | HE8: 0.054 | HF8: 0.1309 | HG8: 0.0919 | HH8: 0.040923153 | HI8: 0.15428771 | HJ8: 0.025666807 | HK8: 0.055 | HL8: 0.1331 | HM8: 0.0788 | HN8: 0.046201258 | HO8: 0.13488828 | HP8: 0.02770808 | HQ8: 0.06 | HR8: 0.1398 | HS8: 0.0678 | HT8: 0.098691491 | HU8: 0.13565627 | HV8: 0.029241739 | HW8: 0.056 | HX8: 0.1463 | HY8: 0.0663 | HZ8: 0.067311488 | IA8: 0.1331656 | IB8: 0.031509782 | IC8: 0.049 | ID8: 0.1628 | IE8: 0.057 | IF8: 0.078825671 | IG8: 0.17343088 | IH8: 0.037880643 | II8: 0.046 | IJ8: 0.1685 | IK8: 0.0622 | IL8: 0.090061011 | IM8: 0.13189568 | IN8: 0.038040221 | IO8: 0.04 | IP8: 0.1691 | IQ8: 0.0356 | IR8: 0.095002862 | IS8: 0.1415614 | IT8: 0.038540623 | IU8: 0.047 | IV8: 0.1689 | IW8: 0.0299 | IX8: 0.10035976 | IY8: 0.17190224 | IZ8: 0.034405716 | JA8: 0.049 | JB8: 0.1577 | JC8: 0.0362 | JD8: 0.18768521 | JE8: 0.13024372 | JF8: 0.053187505 | JG8: 0.05 | JH8: 0.1528 | JI8: 0.0382 | JJ8: 0.11109098 | JK8: 0.1179198 | JL8: 0.040090858 | JM8: 0.049 | JN8: 0.1507 | JO8: 0.0458 | JP8: 0.10891076 | JQ8: 0.1172414 | JR8: 0.045792873 | JS8: 0.05 | JT8: 0.1481 | JU8: 0.0449 | JV8: 0.10966313 | JW8: 0.11891256 | JX8: 0.055791948
A9: 5 | B9: Absa Bank Kenya | C9: 0.052 | D9: 0.1691 | E9: 0.0627 | F9: 0.038103839 | G9: 0.52865679 | H9: 0.038067107 | I9: 0.06 | J9: 0.1636 | K9: 0.0739 | L9: 0.032196493 | M9: 0.51027995 | N9: 0.040274003 | O9: 0.05 | P9: 0.1599 | Q9: 0.0602 | R9: 0.035040031 | S9: 0.51575768 | T9: 0.038729202 | U9: 0.057 | V9: 0.1546 | W9: 0.0631 | X9: 0.033980753 | Y9: 0.52896178 | Z9: 0.038041927 | AA9: 0.056 | AB9: 0.1606 | AC9: 0.0703 | AD9: 0.033901174 | AE9: 0.52629811 | AF9: 0.039514012 | AG9: 0.061 | AH9: 0.1682 | AI9: 0.0597 | AJ9: 0.03932776 | AK9: 0.53488734 | AL9: 0.03819356 | AM9: 0.05 | AN9: 0.183 | AO9: 0.0801 | AP9: 0.030376412 | AQ9: 0.53026031 | AR9: 0.035955945 | AS9: 0.038 | AT9: 0.1787 | AU9: 0.0645 | AV9: 0.040269707 | AW9: 0.51930096 | AX9: 0.038523037 | AY9: 0.038 | AZ9: 0.1818 | BA9: 0.058 | BB9: 0.040995473 | BC9: 0.51755107 | BD9: 0.032871328 | BE9: 0.044 | BF9: 0.1386 | BG9: 0.0634 | BH9: 0.046683675 | BI9: 0.51484825 | BJ9: 0.046031156 | BK9: 0.042 | BL9: 0.1366 | BM9: 0.0635 | BN9: 0.049538249 | BO9: 0.53939573 | BP9: 0.028408401 | BQ9: 0.054 | BR9: 0.1361 | BS9: 0.1028 | BT9: 0.049381487 | BU9: 0.56442424 | BV9: 0.025359819 | BW9: 0.033 | BX9: 0.1366 | BY9: 0.0921 | BZ9: 0.050802085 | CA9: 0.57132269 | CB9: 0.025682545 | CC9: 0.032 | CD9: 0.1369 | CE9: 0.0706 | CF9: 0.050569477 | CG9: 0.56207039 | CH9: 0.025325797 | CI9: 0.038 | CJ9: 0.1364 | CK9: 0.045 | CL9: 0.052648873 | CM9: 0.55943392 | CN9: 0.025149938 | CO9: 0.052 | CP9: 0.1349 | CQ9: 0.0418 | CR9: 0.053173856 | CS9: 0.58220979 | CT9: 0.025367168 | CU9: 0.061 | CV9: 0.1322 | CW9: 0.0428 | CX9: 0.05844344 | CY9: 0.55886479 | CZ9: 0.024513786 | DA9: 0.053 | DB9: 0.1266 | DC9: 0.057 | DD9: 0.060632845 | DE9: 0.56378617 | DF9: 0.033155691 | DG9: 0.056 | DH9: 0.1251 | DI9: 0.0571 | DJ9: 0.057517939 | DK9: 0.54656329 | DL9: 0.023931614 | DM9: 0.048 | DN9: 0.1251 | DO9: 0.0435 | DP9: 0.064382445 | DQ9: 0.54629153 | DR9: 0.02146836 | DS9: 0.06 | DT9: 0.1247 | DU9: 0.057 | DV9: 0.063596535 | DW9: 0.51797998 | DX9: 0.022131739 | DY9: 0.05 | DZ9: 0.1247 | EA9: 0.0383 | EB9: 0.053392293 | EC9: 0.51232535 | ED9: 0.0208122 | EE9: 0.051 | EF9: 0.1224 | EG9: 0.0582 | EH9: 0.05304483 | EI9: 0.5155539 | EJ9: 0 | EK9: 0.046 | EL9: 0.1209 | EM9: 0.0584 | EN9: 0.068632606 | EO9: 0.47567404 | EP9: 0.019408116 | EQ9: -0.041 | ER9: 0.1189 | ES9: 0.0459 | ET9: 0.067303992 | EU9: 0.48875468 | EV9: 0.0020230382 | EW9: -0.036 | EX9: 0.1175 | EY9: 0.042 | EZ9: 0.063946093 | FA9: 0.4927631 | FB9: 0.0056968154 | FC9: -0.003 | FD9: 0.1202 | FE9: 0.0562 | FF9: 0.065614331 | FG9: 0.48411089 | FH9: 0.0098232123 | FI9: 0.024 | FJ9: 0.1205 | FK9: 0.059 | FL9: 0.063699793 | FM9: 0.46016314 | FN9: 0.023643296 | FO9: 0.103 | FP9: 0.1202 | FQ9: 0.0632 | FR9: 0.067876038 | FS9: 0.44950093 | FT9: 0.027040217 | FU9: 0.094 | FV9: 0.121 | FW9: 0.0691 | FX9: 0.069875001 | FY9: 0.44501379 | FZ9: 0.026117109 | GA9: 0.076 | GB9: 0.1216 | GC9: 0.0573 | GD9: 0.068857847 | GE9: 0.45611909 | GF9: 0.025213555 | GG9: 0.059 | GH9: 0.1215 | GI9: 0.0556 | GJ9: 0.065949752 | GK9: 0.45558452 | GL9: 0.025412043 | GM9: 0.049 | GN9: 0.1227 | GO9: 0.0791 | GP9: 0.062243391 | GQ9: 0.42890334 | GR9: 0.027165922 | GS9: 0.046 | GT9: 0.1241 | GU9: 0.0918 | GV9: 0.056884269 | GW9: 0.40216577 | GX9: 0.02975333 | GY9: 0.049 | GZ9: 0.1267 | HA9: 0.0906 | HB9: 0.058827993 | HC9: 0.41120598 | HD9: 0.030612193 | HE9: 0.054 | HF9: 0.1309 | HG9: 0.0919 | HH9: 0.07908864 | HI9: 0.372397 | HJ9: 0.033286073 | HK9: 0.055 | HL9: 0.1331 | HM9: 0.0788 | HN9: 0.079690281 | HO9: 0.37782725 | HP9: 0.031527449 | HQ9: 0.06 | HR9: 0.1398 | HS9: 0.0678 | HT9: 0.080934381 | HU9: 0.39487968 | HV9: 0.031159682 | HW9: 0.056 | HX9: 0.1463 | HY9: 0.0663 | HZ9: 0.080580895 | IA9: 0.40335248 | IB9: 0.030827195 | IC9: 0.049 | ID9: 0.1628 | IE9: 0.057 | IF9: 0.09093433 | IG9: 0.34603637 | IH9: 0.043918776 | II9: 0.046 | IJ9: 0.1685 | IK9: 0.0622 | IL9: 0.093688589 | IM9: 0.36422822 | IN9: 0.040251511 | IO9: 0.04 | IP9: 0.1691 | IQ9: 0.0356 | IR9: 0.10242028 | IS9: 0.38560151 | IT9: 0.036641111 | IU9: 0.047 | IV9: 0.1689 | IW9: 0.0299 | IX9: 0.10238959 | IY9: 0.38411414 | IZ9: 0.038265147 | JA9: 0.049 | JB9: 0.1577 | JC9: 0.0362 | JD9: 0.10526973 | JE9: 0.36310462 | JF9: 0.044132875 | JG9: 0.05 | JH9: 0.1528 | JI9: 0.0382 | JJ9: 0.10559877 | JK9: 0.37658668 | JL9: 0.041252564 | JM9: 0.049 | JN9: 0.1507 | JO9: 0.0458 | JP9: 0.10451268 | JQ9: 0.39032334 | JR9: 0.038731484 | JS9: 0.05 | JT9: 0.1481 | JU9: 0.0449 | JV9: 0.090584839 | JW9: 0.37882609 | JX9: 0.04017011
A10: 6 | B10: Stanbic Bank | C10: 0.052 | D10: 0.1691 | E10: 0.0627 | F10: 0.021255656 | G10: 0.51904229 | H10: 0.038951559 | I10: 0.06 | J10: 0.1636 | K10: 0.0739 | L10: 0.012267936 | M10: 0.50160014 | N10: 0.039711495 | O10: 0.05 | P10: 0.1599 | Q10: 0.0602 | R10: 0.033092824 | S10: 0.49847088 | T10: 0.032032263 | U10: 0.057 | V10: 0.1546 | W10: 0.0631 | X10: 0.034378891 | Y10: 0.56022453 | Z10: 0.027267188 | AA10: 0.056 | AB10: 0.1606 | AC10: 0.0703 | AD10: 0.032924261 | AE10: 0.59958418 | AF10: 0.019397298 | AG10: 0.061 | AH10: 0.1682 | AI10: 0.0597 | AJ10: 0.032046141 | AK10: 0.59030261 | AL10: 0.01934098 | AM10: 0.05 | AN10: 0.183 | AO10: 0.0801 | AP10: 0.03943801 | AQ10: 0.50591733 | AR10: 0.02539452 | AS10: 0.038 | AT10: 0.1787 | AU10: 0.0645 | AV10: 0.04115104 | AW10: 0.48772163 | AX10: 0.023355536 | AY10: 0.038 | AZ10: 0.1818 | BA10: 0.058 | BB10: 0.04378028 | BC10: 0.51485647 | BD10: 0.023554407 | BE10: 0.044 | BF10: 0.1386 | BG10: 0.0634 | BH10: 0.046162351 | BI10: 0.57674939 | BJ10: 0.021265017 | BK10: 0.042 | BL10: 0.1366 | BM10: 0.0635 | BN10: 0.048052143 | BO10: 0.50261322 | BP10: 0.021936537 | BQ10: 0.054 | BR10: 0.1361 | BS10: 0.1028 | BT10: 0.047536934 | BU10: 0.56663304 | BV10: 0.020616008 | BW10: 0.033 | BX10: 0.1366 | BY10: 0.0921 | BZ10: 0.042852431 | CA10: 0.54079311 | CB10: 0.016097209 | CC10: 0.032 | CD10: 0.1369 | CE10: 0.0706 | CF10: 0.061214872 | CG10: 0.5242787 | CH10: 0.019486055 | CI10: 0.038 | CJ10: 0.1364 | CK10: 0.045 | CL10: 0.062448864 | CM10: 0.5516432 | CN10: 0.019532327 | CO10: 0.052 | CP10: 0.1349 | CQ10: 0.0418 | CR10: 0.061931022 | CS10: 0.49388389 | CT10: 0.031551997 | CU10: 0.061 | CV10: 0.1322 | CW10: 0.0428 | CX10: 0.057773053 | CY10: 0.47808192 | CZ10: 0.027426248 | DA10: 0.053 | DB10: 0.1266 | DC10: 0.057 | DD10: 0.054421144 | DE10: 0.50099357 | DF10: 0.034014831 | DG10: 0.056 | DH10: 0.1251 | DI10: 0.0571 | DJ10: 0.086329554 | DK10: 0.50195626 | DL10: 0.023737649 | DM10: 0.048 | DN10: 0.1251 | DO10: 0.0435 | DP10: 0.085509165 | DQ10: 0.43570287 | DR10: 0.03249934 | DS10: 0.06 | DT10: 0.1247 | DU10: 0.057 | DV10: 0.080363254 | DW10: 0.47960913 | DX10: 0.027089815 | DY10: 0.05 | DZ10: 0.1247 | EA10: 0.0383 | EB10: 0.082825751 | EC10: 0.54406436 | ED10: 0.023667806 | EE10: 0.051 | EF10: 0.1224 | EG10: 0.0582 | EH10: 0.090731362 | EI10: 0.53903147 | EJ10: 0.021692864 | EK10: 0.046 | EL10: 0.1209 | EM10: 0.0584 | EN10: 0.091679775 | EO10: 0.48862189 | EP10: 0.020313194 | EQ10: -0.041 | ER10: 0.1189 | ES10: 0.0459 | ET10: 0.090617807 | EU10: 0.46456849 | EV10: 0.015502641 | EW10: -0.036 | EX10: 0.1175 | EY10: 0.042 | EZ10: 0.091773839 | FA10: 0.48086172 | FB10: 0.015593645 | FC10: -0.003 | FD10: 0.1202 | FE10: 0.0562 | FF10: 0.11076257 | FG10: 0.52014163 | FH10: 0.017114583 | FI10: 0.024 | FJ10: 0.1205 | FK10: 0.059 | FL10: 0.11483654 | FM10: 0.46650774 | FN10: 0.023736752 | FO10: 0.103 | FP10: 0.1202 | FQ10: 0.0632 | FR10: 0.095153411 | FS10: 0.50422162 | FT10: 0.021202069 | FU10: 0.094 | FV10: 0.121 | FW10: 0.0691 | FX10: 0.092260273 | FY10: 0.51122854 | FZ10: 0.022248847 | GA10: 0.076 | GB10: 0.1216 | GC10: 0.0573 | GD10: 0.089619218 | GE10: 0.51898274 | GF10: 0.022187933 | GG10: 0.059 | GH10: 0.1215 | GI10: 0.0556 | GJ10: 0.08744815 | GK10: 0.49564875 | GL10: 0.025962226 | GM10: 0.049 | GN10: 0.1227 | GO10: 0.0791 | GP10: 0.082338254 | GQ10: 0.48308284 | GR10: 0.029297209 | GS10: 0.046 | GT10: 0.1241 | GU10: 0.0918 | GV10: 0.079479968 | GW10: 0.4541808 | GX10: 0.02700536 | GY10: 0.049 | GZ10: 0.1267 | HA10: 0.0906 | HB10: 0.087940029 | HC10: 0.46583438 | HD10: 0.025619363 | HE10: 0.054 | HF10: 0.1309 | HG10: 0.0919 | HH10: 0.090800207 | HI10: 0.40478907 | HJ10: 0.056219969 | HK10: 0.055 | HL10: 0.1331 | HM10: 0.0788 | HN10: 0.072127166 | HO10: 0.4286554 | HP10: 0.035296539 | HQ10: 0.06 | HR10: 0.1398 | HS10: 0.0678 | HT10: 0.070236812 | HU10: 0.34636509 | HV10: 0.030764962 | HW10: 0.056 | HX10: 0.1463 | HY10: 0.0663 | HZ10: 0.073113642 | IA10: 0.42374787 | IB10: 0.028384116 | IC10: 0.049 | ID10: 0.1628 | IE10: 0.057 | IF10: 0.067894536 | IG10: 0.35667466 | IH10: 0.033978647 | II10: 0.046 | IJ10: 0.1685 | IK10: 0.0622 | IL10: 0.072461436 | IM10: 0.40373905 | IN10: 0.030312483 | IO10: 0.04 | IP10: 0.1691 | IQ10: 0.0356 | IR10: 0.079132732 | IS10: 0.42941958 | IT10: 0.029649805 | IU10: 0.047 | IV10: 0.1689 | IW10: 0.0299 | IX10: 0.06790174 | IY10: 0.43352391 | IZ10: 0.030506717 | JA10: 0.049 | JB10: 0.1577 | JC10: 0.0362 | JD10: 0.063596227 | JE10: 0.48205155 | JF10: 0.036488459 | JG10: 0.05 | JH10: 0.1528 | JI10: 0.0382 | JJ10: 0.06895431 | JK10: 0.47466601 | JL10: 0.036943962 | JM10: 0.049 | JN10: 0.1507 | JO10: 0.0458 | JP10: 0.060125185 | JQ10: 0.45635151 | JR10: 0.027157396 | JS10: 0.05 | JT10: 0.1481 | JU10: 0.0449 | JV10: 0.056981394 | JW10: 0.45907583 | JX10: 0.027649597
A11: 7 | B11: Chase Bank | C11: 0.052 | D11: 0.1691 | E11: 0.0627 | F11: 0.025240983 | G11: 0.50051175 | H11: 0.021067733 | I11: 0.06 | J11: 0.1636 | K11: 0.0739 | L11: 0.02620056 | M11: 0.4900459 | N11: 0.025511105 | O11: 0.05 | P11: 0.1599 | Q11: 0.0602 | R11: 0.040687918 | S11: 0.5529911 | T11: 0.025224122 | U11: 0.057 | V11: 0.1546 | W11: 0.0631 | X11: 0.042175276 | Y11: 0.52540315 | Z11: 0.025283942 | AA11: 0.056 | AB11: 0.1606 | AC11: 0.0703 | AD11: 0.044058319 | AE11: 0.51178692 | AF11: 0.02468733 | AG11: 0.061 | AH11: 0.1682 | AI11: 0.0597 | AJ11: 0.039361257 | AK11: 0.5452865 | AL11: 0.023661921 | AM11: 0.05 | AN11: 0.183 | AO11: 0.0801 | AP11: 0.092405475 | AQ11: 0.86812519 | AR11: -0.0059528436 | AS11: 0.038 | AT11: 0.1787 | AU11: 0.0645 | AV11: NA | AW11: NA | AX11: NA | AY11: 0.038 | AZ11: 0.1818 | BA11: 0.058 | BB11: NA | BC11: NA | BD11: NA | BE11: 0.044 | BF11: 0.1386 | BG11: 0.0634 | BH11: NA | BI11: NA | BJ11: NA | BK11: 0.042 | BL11: 0.1366 | BM11: 0.0635 | BN11: NA | BO11: NA | BP11: NA | BQ11: 0.054 | BR11: 0.1361 | BS11: 0.1028 | BT11: NA | BU11: NA | BV11: NA | BW11: 0.033 | BX11: 0.1366 | BY11: 0.0921 | BZ11: NA | CA11: NA | CB11: NA | CC11: 0.032 | CD11: 0.1369 | CE11: 0.0706 | CF11: NA | CG11: NA | CH11: NA | CI11: 0.038 | CJ11: 0.1364 | CK11: 0.045 | CL11: NA | CM11: NA | CN11: NA | CO11: 0.052 | CP11: 0.1349 | CQ11: 0.0418 | CR11: NA | CS11: NA | CT11: NA | CU11: 0.061 | CV11: 0.1322 | CW11: 0.0428 | CX11: NA | CY11: NA | CZ11: NA | DA11: 0.053 | DB11: 0.1266 | DC11: 0.057 | DD11: NA | DE11: NA | DF11: NA | DG11: 0.056 | DH11: 0.1251 | DI11: 0.0571 | DJ11: NA | DK11: NA | DL11: NA | DM11: 0.048 | DN11: 0.1251 | DO11: 0.0435 | DP11: NA | DQ11: NA | DR11: NA | DS11: 0.06 | DT11: 0.1247 | DU11: 0.057 | DV11: NA | DW11: NA | DX11: NA | DY11: 0.05 | DZ11: 0.1247 | EA11: 0.0383 | EB11: NA | EC11: NA | ED11: NA | EE11: 0.051 | EF11: 0.1224 | EG11: 0.0582 | EH11: NA | EI11: NA | EJ11: NA | EK11: 0.046 | EL11: 0.1209 | EM11: 0.0584 | EN11: NA | EO11: NA | EP11: NA | EQ11: -0.041 | ER11: 0.1189 | ES11: 0.0459 | ET11: NA | EU11: NA | EV11: NA | EW11: -0.036 | EX11: 0.1175 | EY11: 0.042 | EZ11: NA | FA11: NA | FB11: NA | FC11: -0.003 | FD11: 0.1202 | FE11: 0.0562 | FF11: NA | FG11: NA | FH11: NA | FI11: 0.024 | FJ11: 0.1205 | FK11: 0.059 | FL11: NA | FM11: NA | FN11: NA | FO11: 0.103 | FP11: 0.1202 | FQ11: 0.0632 | FR11: NA | FS11: NA | FT11: NA | FU11: 0.094 | FV11: 0.121 | FW11: 0.0691 | FX11: NA | FY11: NA | FZ11: NA | GA11: 0.076 | GB11: 0.1216 | GC11: 0.0573 | GD11: NA | GE11: NA | GF11: NA | GG11: 0.059 | GH11: 0.1215 | GI11: 0.0556 | GJ11: NA | GK11: NA | GL11: NA | GM11: 0.049 | GN11: 0.1227 | GO11: 0.0791 | GP11: NA | GQ11: NA | GR11: NA | GS11: 0.046 | GT11: 0.1241 | GU11: 0.0918 | GV11: NA | GW11: NA | GX11: NA | GY11: 0.049 | GZ11: 0.1267 | HA11: 0.0906 | HB11: NA | HC11: NA | HD11: NA | HE11: 0.054 | HF11: 0.1309 | HG11: 0.0919 | HH11: NA | HI11: NA | HJ11: NA | HK11: 0.055 | HL11: 0.1331 | HM11: 0.0788 | HN11: NA | HO11: NA | HP11: NA | HQ11: 0.06 | HR11: 0.1398 | HS11: 0.0678 | HT11: NA | HU11: NA | HV11: NA | HW11: 0.056 | HX11: 0.1463 | HY11: 0.0663 | HZ11: NA | IA11: NA | IB11: NA | IC11: 0.049 | ID11: 0.1628 | IE11: 0.057 | IF11: NA | IG11: NA | IH11: NA | II11: 0.046 | IJ11: 0.1685 | IK11: 0.0622 | IL11: NA | IM11: NA | IN11: NA | IO11: 0.04 | IP11: 0.1691 | IQ11: 0.0356 | IR11: NA | IS11: NA | IT11: NA | IU11: 0.047 | IV11: 0.1689 | IW11: 0.0299 | IX11: NA | IY11: NA | IZ11: NA | JA11: 0.049 | JB11: 0.1577 | JC11: 0.0362 | JD11: NA | JE11: NA | JF11: NA | JG11: 0.05 | JH11: 0.1528 | JI11: 0.0382 | JJ11: NA | JK11: NA | JL11: NA | JM11: 0.049 | JN11: 0.1507 | JO11: 0.0458 | JP11: NA | JQ11: NA | JR11: NA | JS11: 0.05 | JT11: 0.1481 | JU11: 0.0449 | JV11: NA | JW11: NA | JX11: NA
A12: 8 | B12: Citibank | C12: 0.052 | D12: 0.1691 | E12: 0.0627 | F12: 0.0060500984 | G12: 0.35193766 | H12: 0.039438919 | I12: 0.06 | J12: 0.1636 | K12: 0.0739 | L12: 0.0045586433 | M12: 0.40238331 | N12: 0.032869648 | O12: 0.05 | P12: 0.1599 | Q12: 0.0602 | R12: 0.036996585 | S12: 0.42933701 | T12: 0.03243568 | U12: 0.057 | V12: 0.1546 | W12: 0.0631 | X12: 0.051009874 | Y12: 0.30643599 | Z12: 0.042666905 | AA12: 0.056 | AB12: 0.1606 | AC12: 0.0703 | AD12: 0.033123348 | AE12: 0.3490164 | AF12: 0.032547667 | AG12: 0.061 | AH12: 0.1682 | AI12: 0.0597 | AJ12: 0.031013004 | AK12: 0.34585148 | AL12: 0.035100484 | AM12: 0.05 | AN12: 0.183 | AO12: 0.0801 | AP12: 0.054840166 | AQ12: 0.32029579 | AR12: 0.040597548 | AS12: 0.038 | AT12: 0.1787 | AU12: 0.0645 | AV12: 0.048539079 | AW12: 0.46338928 | AX12: 0.030484526 | AY12: 0.038 | AZ12: 0.1818 | BA12: 0.058 | BB12: 0.038900672 | BC12: 0.35070412 | BD12: 0.033040598 | BE12: 0.044 | BF12: 0.1386 | BG12: 0.0634 | BH12: 0.034128611 | BI12: 0.39106697 | BJ12: 0.02862068 | BK12: 0.042 | BL12: 0.1366 | BM12: 0.0635 | BN12: 0.018842164 | BO12: 0.33895317 | BP12: 0.035850777 | BQ12: 0.054 | BR12: 0.1361 | BS12: 0.1028 | BT12: 0.048479409 | BU12: 0.43109224 | BV12: 0.028404925 | BW12: 0.033 | BX12: 0.1366 | BY12: 0.0921 | BZ12: 0.046123527 | CA12: 0.33587879 | CB12: 0.042951928 | CC12: 0.032 | CD12: 0.1369 | CE12: 0.0706 | CF12: 0.044319377 | CG12: 0.32766685 | CH12: 0.039707028 | CI12: 0.038 | CJ12: 0.1364 | CK12: 0.045 | CL12: 0.035499899 | CM12: 0.32669581 | CN12: 0.038802384 | CO12: 0.052 | CP12: 0.1349 | CQ12: 0.0418 | CR12: 0.015949684 | CS12: 0.31645605 | CT12: 0.026882866 | CU12: 0.061 | CV12: 0.1322 | CW12: 0.0428 | CX12: 0.014017693 | CY12: 0.33671588 | CZ12: 0.034479276 | DA12: 0.053 | DB12: 0.1266 | DC12: 0.057 | DD12: 0.014250816 | DE12: 0.33508204 | DF12: 0.058281667 | DG12: 0.056 | DH12: 0.1251 | DI12: 0.0571 | DJ12: 0.01595735 | DK12: 0.3661205 | DL12: 0.034391273 | DM12: 0.048 | DN12: 0.1251 | DO12: 0.0435 | DP12: 0.016237889 | DQ12: 0.37014591 | DR12: 0.044987731 | DS12: 0.06 | DT12: 0.1247 | DU12: 0.057 | DV12: 0.01620172 | DW12: 0.38499266 | DX12: 0.035427577 | DY12: 0.05 | DZ12: 0.1247 | EA12: 0.0383 | EB12: 0.018776861 | EC12: 0.38498059 | ED12: 0.035943844 | EE12: 0.051 | EF12: 0.1224 | EG12: 0.0582 | EH12: 0.025031368 | EI12: 0.38476123 | EJ12: 0.03219033 | EK12: 0.046 | EL12: 0.1209 | EM12: 0.0584 | EN12: 0.021749031 | EO12: 0.35745588 | EP12: 0.038948661 | EQ12: -0.041 | ER12: 0.1189 | ES12: 0.0459 | ET12: 0.02425567 | EU12: 0.37007058 | EV12: 0.034591976 | EW12: -0.036 | EX12: 0.1175 | EY12: 0.042 | EZ12: 0.02226798 | FA12: 0.38087383 | FB12: 0 | FC12: -0.003 | FD12: 0.1202 | FE12: 0.0562 | FF12: 0.022199034 | FG12: 0.33614421 | FH12: 0.031168657 | FI12: 0.024 | FJ12: 0.1205 | FK12: 0.059 | FL12: 0.016869609 | FM12: 0.37660801 | FN12: 0.033270352 | FO12: 0.103 | FP12: 0.1202 | FQ12: 0.0632 | FR12: 0.017828566 | FS12: 0.38977698 | FT12: 0.031210087 | FU12: 0.094 | FV12: 0.121 | FW12: 0.0691 | FX12: 0.017115981 | FY12: 0.38052962 | FZ12: 0.031271851 | GA12: 0.076 | GB12: 0.1216 | GC12: 0.0573 | GD12: 0.01372247 | GE12: 0.34807052 | GF12: 0.03001605 | GG12: 0.059 | GH12: 0.1215 | GI12: 0.0556 | GJ12: 0.013762914 | GK12: 0.35052142 | GL12: 0.035908465 | GM12: 0.049 | GN12: 0.1227 | GO12: 0.0791 | GP12: 0.016774356 | GQ12: 0.30388712 | GR12: 0.039473693 | GS12: 0.046 | GT12: 0.1241 | GU12: 0.0918 | GV12: 0.019718307 | GW12: 0.28562364 | GX12: 0.043723501 | GY12: 0.049 | GZ12: 0.1267 | HA12: 0.0906 | HB12: 0.024586672 | HC12: 0.28936363 | HD12: 0.043534494 | HE12: 0.054 | HF12: 0.1309 | HG12: 0.0919 | HH12: 0.031139226 | HI12: 0.30505036 | HJ12: 0.052115045 | HK12: 0.055 | HL12: 0.1331 | HM12: 0.0788 | HN12: 0.027288505 | HO12: 0.275385 | HP12: 0.063583606 | HQ12: 0.06 | HR12: 0.1398 | HS12: 0.0678 | HT12: 0.027097875 | HU12: 0.28174677 | HV12: 0.060239587 | HW12: 0.056 | HX12: 0.1463 | HY12: 0.0663 | HZ12: 0.036712597 | IA12: 0.28205235 | IB12: 0.057282257 | IC12: 0.049 | ID12: 0.1628 | IE12: 0.057 | IF12: 0.031075083 | IG12: 0.25044579 | IH12: 0.080336488 | II12: 0.046 | IJ12: 0.1685 | IK12: 0.0622 | IL12: 0.031629359 | IM12: 0.27257648 | IN12: 0.067829953 | IO12: 0.04 | IP12: 0.1691 | IQ12: 0.0356 | IR12: 0.031984725 | IS12: 0.27958169 | IT12: 0.069182113 | IU12: 0.047 | IV12: 0.1689 | IW12: 0.0299 | IX12: 0.032497449 | IY12: 0.29247902 | IZ12: 0.064774631 | JA12: 0.049 | JB12: 0.1577 | JC12: 0.0362 | JD12: 0.034799886 | JE12: 0.30481861 | JF12: 0.073166882 | JG12: 0.05 | JH12: 0.1528 | JI12: 0.0382 | JJ12: 0.040896731 | JK12: 0.30756849 | JL12: 0.04649152 | JM12: 0.049 | JN12: 0.1507 | JO12: 0.0458 | JP12: 0.037001893 | JQ12: 0.33155584 | JR12: 0.043491942 | JS12: 0.05 | JT12: 0.1481 | JU12: 0.0449 | JV12: 0.035167096 | JW12: 0.36945303 | JX12: 0.039215627
A13: 9 | B13: Commercial Bank of Africa | C13: 0.052 | D13: 0.1691 | E13: 0.0627 | F13: 0.033730079 | G13: 0.49028313 | H13: 0.024343904 | I13: 0.06 | J13: 0.1636 | K13: 0.0739 | L13: 0.030680544 | M13: 0.47154327 | N13: 0.024083989 | O13: 0.05 | P13: 0.1599 | Q13: 0.0602 | R13: 0.03312438 | S13: 0.48156422 | T13: 0.02510589 | U13: 0.057 | V13: 0.1546 | W13: 0.0631 | X13: 0.044465976 | Y13: 0.44478976 | Z13: 0.019171989 | AA13: 0.056 | AB13: 0.1606 | AC13: 0.0703 | AD13: 0.046290784 | AE13: 0.43476316 | AF13: 0.021501009 | AG13: 0.061 | AH13: 0.1682 | AI13: 0.0597 | AJ13: 0.039017427 | AK13: 0.42869251 | AL13: 0.023930074 | AM13: 0.05 | AN13: 0.183 | AO13: 0.0801 | AP13: 0.036887527 | AQ13: 0.42422482 | AR13: 0.024661213 | AS13: 0.038 | AT13: 0.1787 | AU13: 0.0645 | AV13: 0.069980232 | AW13: 0.37373911 | AX13: 0.022128211 | AY13: 0.038 | AZ13: 0.1818 | BA13: 0.058 | BB13: 0.076698648 | BC13: 0.36697353 | BD13: 0.02339494 | BE13: 0.044 | BF13: 0.1386 | BG13: 0.0634 | BH13: 0.082942435 | BI13: 0.37158207 | BJ13: 0.024822051 | BK13: 0.042 | BL13: 0.1366 | BM13: 0.0635 | BN13: 0.038021398 | BO13: 0.37002554 | BP13: 0.03220974 | BQ13: 0.054 | BR13: 0.1361 | BS13: 0.1028 | BT13: 0.064403048 | BU13: 0.40379313 | BV13: 0.028259096 | BW13: 0.033 | BX13: 0.1366 | BY13: 0.0921 | BZ13: 0.063436596 | CA13: 0.42468993 | CB13: 0.02514716 | CC13: 0.032 | CD13: 0.1369 | CE13: 0.0706 | CF13: 0.068965185 | CG13: 0.43621625 | CH13: 0.024528444 | CI13: 0.038 | CJ13: 0.1364 | CK13: 0.045 | CL13: 0.056792742 | CM13: 0.46506056 | CN13: 0.025824493 | CO13: 0.052 | CP13: 0.1349 | CQ13: 0.0418 | CR13: 0.067244965 | CS13: 0.53250578 | CT13: 0.018933462 | CU13: 0.061 | CV13: 0.1322 | CW13: 0.0428 | CX13: 0.064925769 | CY13: 0.45223296 | CZ13: 0.024118094 | DA13: 0.053 | DB13: 0.1266 | DC13: 0.057 | DD13: 0.071260583 | DE13: 0.4677188 | DF13: 0.034848524 | DG13: 0.056 | DH13: 0.1251 | DI13: 0.0571 | DJ13: 0.060640957 | DK13: 0.46766325 | DL13: 0.02625214 | DM13: 0.048 | DN13: 0.1251 | DO13: 0.0435 | DP13: 0.062143521 | DQ13: 0.54494218 | DR13: 0.021319183 | DS13: 0.06 | DT13: 0.1247 | DU13: 0.057 | DV13: 0.065774757 | DW13: 0.49378314 | DX13: 0.023459501 | DY13: 0.05 | DZ13: 0.1247 | EA13: 0.0383 | EB13: 0.077252227 | EC13: 0.54553796 | ED13: 0.025799714 | EE13: 0.051 | EF13: 0.1224 | EG13: 0.0582 | EH13: NA | EI13: NA | EJ13: NA | EK13: 0.046 | EL13: 0.1209 | EM13: 0.0584 | EN13: NA | EO13: NA | EP13: NA | EQ13: -0.041 | ER13: 0.1189 | ES13: 0.0459 | ET13: NA | EU13: NA | EV13: NA | EW13: -0.036 | EX13: 0.1175 | EY13: 0.042 | EZ13: NA | FA13: NA | FB13: NA | FC13: -0.003 | FD13: 0.1202 | FE13: 0.0562 | FF13: NA | FG13: NA | FH13: NA | FI13: 0.024 | FJ13: 0.1205 | FK13: 0.059 | FL13: NA | FM13: NA | FN13: NA | FO13: 0.103 | FP13: 0.1202 | FQ13: 0.0632 | FR13: NA | FS13: NA | FT13: NA | FU13: 0.094 | FV13: 0.121 | FW13: 0.0691 | FX13: NA | FY13: NA | FZ13: NA | GA13: 0.076 | GB13: 0.1216 | GC13: 0.0573 | GD13: NA | GE13: NA | GF13: NA | GG13: 0.059 | GH13: 0.1215 | GI13: 0.0556 | GJ13: NA | GK13: NA | GL13: NA | GM13: 0.049 | GN13: 0.1227 | GO13: 0.0791 | GP13: NA | GQ13: NA | GR13: NA | GS13: 0.046 | GT13: 0.1241 | GU13: 0.0918 | GV13: NA | GW13: NA | GX13: NA | GY13: 0.049 | GZ13: 0.1267 | HA13: 0.0906 | HB13: NA | HC13: NA | HD13: NA | HE13: 0.054 | HF13: 0.1309 | HG13: 0.0919 | HH13: NA | HI13: NA | HJ13: NA | HK13: 0.055 | HL13: 0.1331 | HM13: 0.0788 | HN13: NA | HO13: NA | HP13: NA | HQ13: 0.06 | HR13: 0.1398 | HS13: 0.0678 | HT13: NA | HU13: NA | HV13: NA | HW13: 0.056 | HX13: 0.1463 | HY13: 0.0663 | HZ13: NA | IA13: NA | IB13: NA | IC13: 0.049 | ID13: 0.1628 | IE13: 0.057 | IF13: NA | IG13: NA | IH13: NA | II13: 0.046 | IJ13: 0.1685 | IK13: 0.0622 | IL13: NA | IM13: NA | IN13: NA | IO13: 0.04 | IP13: 0.1691 | IQ13: 0.0356 | IR13: NA | IS13: NA | IT13: NA | IU13: 0.047 | IV13: 0.1689 | IW13: 0.0299 | IX13: NA | IY13: NA | IZ13: NA | JA13: 0.049 | JB13: 0.1577 | JC13: 0.0362 | JD13: NA | JE13: NA | JF13: NA | JG13: 0.05 | JH13: 0.1528 | JI13: 0.0382 | JJ13: NA | JK13: NA | JL13: NA | JM13: 0.049 | JN13: 0.1507 | JO13: 0.0458 | JP13: NA | JQ13: NA | JR13: NA | JS13: 0.05 | JT13: 0.1481 | JU13: 0.0449 | JV13: NA | JW13: NA | JX13: NA
A14: 10 | B14: Consolidated Bank of Kenya | C14: 0.052 | D14: 0.1691 | E14: 0.0627 | F14: 0.12333568 | G14: 0.83745635 | H14: 0.0038362975 | I14: 0.06 | J14: 0.1636 | K14: 0.0739 | L14: 0.16194141 | M14: 0.89563965 | N14: -0.0013585055 | O14: 0.05 | P14: 0.1599 | Q14: 0.0602 | R14: 0.20192937 | S14: 0.87431804 | T14: -0.017681744 | U14: 0.057 | V14: 0.1546 | W14: 0.0631 | X14: 0.21134761 | Y14: 1.0438779 | Z14: -0.0049044543 | AA14: 0.056 | AB14: 0.1606 | AC14: 0.0703 | AD14: 0.21825051 | AE14: 0.65713092 | AF14: 0.0048068657 | AG14: 0.061 | AH14: 0.1682 | AI14: 0.0597 | AJ14: 0.21282992 | AK14: 0.68206396 | AL14: 0.0014520754 | AM14: 0.05 | AN14: 0.183 | AO14: 0.0801 | AP14: 0.14462599 | AQ14: 0.68364172 | AR14: 0.0030417034 | AS14: 0.038 | AT14: 0.1787 | AU14: 0.0645 | AV14: 0.14284299 | AW14: 0.86313881 | AX14: -0.0079948547 | AY14: 0.038 | AZ14: 0.1818 | BA14: 0.058 | BB14: 0.12375276 | BC14: 0.901096 | BD14: -0.01008104 | BE14: 0.044 | BF14: 0.1386 | BG14: 0.0634 | BH14: 0.12749842 | BI14: 0.9514631 | BJ14: -0.019359589 | BK14: 0.042 | BL14: 0.1366 | BM14: 0.0635 | BN14: 0.13892517 | BO14: 0.97757704 | BP14: -0.015068393 | BQ14: 0.054 | BR14: 0.1361 | BS14: 0.1028 | BT14: 0.14274185 | BU14: 0.91934473 | BV14: -0.0059668861 | BW14: 0.033 | BX14: 0.1366 | BY14: 0.0921 | BZ14: 0.14978662 | CA14: 1.0257732 | CB14: -0.023076531 | CC14: 0.032 | CD14: 0.1369 | CE14: 0.0706 | CF14: 0.1611644 | CG14: 1.0632377 | CH14: -0.029407348 | CI14: 0.038 | CJ14: 0.1364 | CK14: 0.045 | CL14: 0.16962124 | CM14: 1.0341177 | CN14: -0.024525859 | CO14: 0.052 | CP14: 0.1349 | CQ14: 0.0418 | CR14: 0.18889815 | CS14: 1.7285245 | CT14: -0.043021077 | CU14: 0.061 | CV14: 0.1322 | CW14: 0.0428 | CX14: 0.2119186 | CY14: 1.1204514 | CZ14: -0.036103725 | DA14: 0.053 | DB14: 0.1266 | DC14: 0.057 | DD14: 0.20699529 | DE14: 1.1848217 | DF14: -0.040252373 | DG14: 0.056 | DH14: 0.1251 | DI14: 0.0571 | DJ14: 0.17839261 | DK14: 0.98818249 | DL14: -0.041000072 | DM14: 0.048 | DN14: 0.1251 | DO14: 0.0435 | DP14: 0.17993812 | DQ14: 0.94019845 | DR14: -0.016917092 | DS14: 0.06 | DT14: 0.1247 | DU14: 0.057 | DV14: 0.2083109 | DW14: 1.0764265 | DX14: -0.029540575 | DY14: 0.05 | DZ14: 0.1247 | EA14: 0.0383 | EB14: 0.20372073 | EC14: 1.1139315 | ED14: -0.039806473 | EE14: 0.051 | EF14: 0.1224 | EG14: 0.0582 | EH14: 0 | EI14: 1.0826377 | EJ14: -0.042839273 | EK14: 0.046 | EL14: 0.1209 | EM14: 0.0584 | EN14: 0 | EO14: 1.0470725 | EP14: -0.025529386 | EQ14: -0.041 | ER14: 0.1189 | ES14: 0.0459 | ET14: 0 | EU14: 1.0748264 | EV14: -0.02992999 | EW14: -0.036 | EX14: 0.1175 | EY14: 0.042 | EZ14: 0 | FA14: 0.92418386 | FB14: -0.027932098 | FC14: -0.003 | FD14: 0.1202 | FE14: 0.0562 | FF14: 0 | FG14: 1.0276309 | FH14: -0.023094091 | FI14: 0.024 | FJ14: 0.1205 | FK14: 0.059 | FL14: 0.15916382 | FM14: 1.0246294 | FN14: -0.019843566 | FO14: 0.103 | FP14: 0.1202 | FQ14: 0.0632 | FR14: 0.16452187 | FS14: 1.0584171 | FT14: -0.022909556 | FU14: 0.094 | FV14: 0.121 | FW14: 0.0691 | FX14: 0.17374205 | FY14: 1.0194147 | FZ14: -0.036539902 | GA14: 0.076 | GB14: 0.1216 | GC14: 0.0573 | GD14: 0.17441378 | GE14: 0.99365047 | GF14: 0.02308781 | GG14: 0.059 | GH14: 0.1215 | GI14: 0.0556 | GJ14: 0.16624955 | GK14: 0.91246912 | GL14: -0.02519696 | GM14: 0.049 | GN14: 0.1227 | GO14: 0.0791 | GP14: 0.16025766 | GQ14: 0.61207782 | GR14: -0.02255928 | GS14: 0.046 | GT14: 0.1241 | GU14: 0.0918 | GV14: 0.1640693 | GW14: 0.93622012 | GX14: -0.019730464 | GY14: 0.049 | GZ14: 0.1267 | HA14: 0.0906 | HB14: 0.16708486 | HC14: 1.1013504 | HD14: -0.030789697 | HE14: 0.054 | HF14: 0.1309 | HG14: 0.0919 | HH14: 0.17763807 | HI14: 1.015054 | HJ14: -0.020825753 | HK14: 0.055 | HL14: 0.1331 | HM14: 0.0788 | HN14: 0.1829952 | HO14: 1.0322066 | HP14: -0.021257256 | HQ14: 0.06 | HR14: 0.1398 | HS14: 0.0678 | HT14: 0.19399343 | HU14: 1.0495702 | HV14: -0.021936136 | HW14: 0.056 | HX14: 0.1463 | HY14: 0.0663 | HZ14: 0.21090486 | IA14: 0.977435 | IB14: -0.029517292 | IC14: 0.049 | ID14: 0.1628 | IE14: 0.057 | IF14: 0.20542912 | IG14: 0.96598152 | IH14: -0.014025319 | II14: 0.046 | IJ14: 0.1685 | IK14: 0.0622 | IL14: 0.20446329 | IM14: 0.90591831 | IN14: -0.012074678 | IO14: 0.04 | IP14: 0.1691 | IQ14: 0.0356 | IR14: 0.21011136 | IS14: 0.93079734 | IT14: -0.012091521 | IU14: 0.047 | IV14: 0.1689 | IW14: 0.0299 | IX14: 0.21897482 | IY14: 0.94092142 | IZ14: -0.010009872 | JA14: 0.049 | JB14: 0.1577 | JC14: 0.0362 | JD14: 0.22493852 | JE14: 0.83391552 | JF14: -0.0027871278 | JG14: 0.05 | JH14: 0.1528 | JI14: 0.0382 | JJ14: 0.23075148 | JK14: 0.78239987 | JL14: 0.00084373222 | JM14: 0.049 | JN14: 0.1507 | JO14: 0.0458 | JP14: 0.22112074 | JQ14: 0.73934599 | JR14: 0.0054778797 | JS14: 0.05 | JT14: 0.1481 | JU14: 0.0449 | JV14: 0.23277791 | JW14: 0.74285752 | JX14: 0.0099656626
A15: 11 | B15: Co-operative Bank of Kenya | C15: 0.052 | D15: 0.1691 | E15: 0.0627 | F15: 0.03886555 | G15: 0.52098295 | H15: 0.038974712 | I15: 0.06 | J15: 0.1636 | K15: 0.0739 | L15: 0.037361166 | M15: 0.54110579 | N15: 0.038586025 | O15: 0.05 | P15: 0.1599 | Q15: 0.0602 | R15: 0.041092156 | S15: 0.56510554 | T15: 0.032650198 | U15: 0.057 | V15: 0.1546 | W15: 0.0631 | X15: 0.039690629 | Y15: 0.43984332 | Z15: 0.044108171 | AA15: 0.056 | AB15: 0.1606 | AC15: 0.0703 | AD15: 0.038483958 | AE15: 0.46213582 | AF15: 0.039494139 | AG15: 0.061 | AH15: 0.1682 | AI15: 0.0597 | AJ15: 0.034519312 | AK15: 0.48064746 | AL15: 0.035657622 | AM15: 0.05 | AN15: 0.183 | AO15: 0.0801 | AP15: 0.033133814 | AQ15: 0.52742839 | AR15: 0.033657802 | AS15: 0.038 | AT15: 0.1787 | AU15: 0.0645 | AV15: 0.033238421 | AW15: 0.62540458 | AX15: 0.039908982 | AY15: 0.038 | AZ15: 0.1818 | BA15: 0.058 | BB15: 0.039385213 | BC15: 0.443688 | BD15: 0.041146025 | BE15: 0.044 | BF15: 0.1386 | BG15: 0.0634 | BH15: 0.038179229 | BI15: 0.46220844 | BJ15: 0.039679182 | BK15: 0.042 | BL15: 0.1366 | BM15: 0.0635 | BN15: 0.041145495 | BO15: 0.49724305 | BP15: 0.037855442 | BQ15: 0.054 | BR15: 0.1361 | BS15: 0.1028 | BT15: 0.04025537 | BU15: 0.47238762 | BV15: 0.034820898 | BW15: 0.033 | BX15: 0.1366 | BY15: 0.0921 | BZ15: 0.042784181 | CA15: 0.47388219 | CB15: 0.0349126 | CC15: 0.032 | CD15: 0.1369 | CE15: 0.0706 | CF15: 0.058480495 | CG15: 0.47101607 | CH15: 0.033155861 | CI15: 0.038 | CJ15: 0.1364 | CK15: 0.045 | CL15: 0.065766372 | CM15: 0.49821428 | CN15: 0.031755172 | CO15: 0.052 | CP15: 0.1349 | CQ15: 0.0418 | CR15: 0.098833116 | CS15: 0.83259303 | CT15: 0.033379087 | CU15: 0.061 | CV15: 0.1322 | CW15: 0.0428 | CX15: 0.098881673 | CY15: 0.4966213 | CZ15: 0.034604678 | DA15: 0.053 | DB15: 0.1266 | DC15: 0.057 | DD15: 0.10100736 | DE15: 0.51038063 | DF15: 0.047362706 | DG15: 0.056 | DH15: 0.1251 | DI15: 0.0571 | DJ15: 0.092259835 | DK15: 0.5327546 | DL15: 0.031370379 | DM15: 0.048 | DN15: 0.1251 | DO15: 0.0435 | DP15: 0.089774897 | DQ15: 0.49660889 | DR15: 0.032510786 | DS15: 0.06 | DT15: 0.1247 | DU15: 0.057 | DV15: 0.089649479 | DW15: 0.4934993 | DX15: 0.033928091 | DY15: 0.05 | DZ15: 0.1247 | EA15: 0.0383 | EB15: 0.083249471 | EC15: 0.49944214 | ED15: 0.032574518 | EE15: 0.051 | EF15: 0.1224 | EG15: 0.0582 | EH15: 0.089627251 | EI15: 0.50815867 | EJ15: 0.033232531 | EK15: 0.046 | EL15: 0.1209 | EM15: 0.0584 | EN15: 0.086212499 | EO15: 0.5098191 | EP15: 0.030667172 | EQ15: -0.041 | ER15: 0.1189 | ES15: 0.0459 | ET15: 0.093307413 | EU15: 0.52466948 | EV15: 0.028675949 | EW15: -0.036 | EX15: 0.1175 | EY15: 0.042 | EZ15: 0.10617213 | FA15: 0.52381869 | FB15: 0.025536496 | FC15: -0.003 | FD15: 0.1202 | FE15: 0.0562 | FF15: 0.14163873 | FG15: 0.51816334 | FH15: 0.028813611 | FI15: 0.024 | FJ15: 0.1205 | FK15: 0.059 | FL15: 0.11803557 | FM15: 0.4762467 | FN15: 0.026325354 | FO15: 0.103 | FP15: 0.1202 | FQ15: 0.0632 | FR15: 0.11575786 | FS15: 0.47727607 | FT15: 0.026900109 | FU15: 0.094 | FV15: 0.121 | FW15: 0.0691 | FX15: 0.1107356 | FY15: 0.47998921 | FZ15: 0.027091231 | GA15: 0.076 | GB15: 0.1216 | GC15: 0.0573 | GD15: 0.11279854 | GE15: 0.47980262 | GF15: 0.029909031 | GG15: 0.059 | GH15: 0.1215 | GI15: 0.0556 | GJ15: 0.10718534 | GK15: 0.43595733 | GL15: 0.038626664 | GM15: 0.049 | GN15: 0.1227 | GO15: 0.0791 | GP15: 0.11095863 | GQ15: 0.44211031 | GR15: 0.037779531 | GS15: 0.046 | GT15: 0.1241 | GU15: 0.0918 | GV15: 0.11209122 | GW15: 0.44259335 | GX15: 0.036866007 | GY15: 0.049 | GZ15: 0.1267 | HA15: 0.0906 | HB15: 0.11470175 | HC15: 0.46487563 | HD15: 0.03562117 | HE15: 0.054 | HF15: 0.1309 | HG15: 0.0919 | HH15: 0.11547728 | HI15: 0.44314496 | HJ15: 0.038217348 | HK15: 0.055 | HL15: 0.1331 | HM15: 0.0788 | HN15: 0.11912247 | HO15: 0.44204415 | HP15: 0.037111178 | HQ15: 0.06 | HR15: 0.1398 | HS15: 0.0678 | HT15: 0.12459309 | HU15: 0.44842671 | HV15: 0.037341705 | HW15: 0.056 | HX15: 0.1463 | HY15: 0.0663 | HZ15: 0.13912554 | IA15: 0.45865511 | IB15: 0.036201336 | IC15: 0.049 | ID15: 0.1628 | IE15: 0.057 | IF15: 0.13660361 | IG15: 0.51843607 | IH15: 0.035823056 | II15: 0.046 | IJ15: 0.1685 | IK15: 0.0622 | IL15: 0.14379732 | IM15: 0.44433886 | IN15: 0.037239282 | IO15: 0.04 | IP15: 0.1691 | IQ15: 0.0356 | IR15: 0.14322889 | IS15: 0.44424282 | IT15: 0.035398773 | IU15: 0.047 | IV15: 0.1689 | IW15: 0.0299 | IX15: 0.14903862 | IY15: 0.45987295 | IZ15: 0.035040741 | JA15: 0.049 | JB15: 0.1577 | JC15: 0.0362 | JD15: 0.15147767 | JE15: 0.44207176 | JF15: 0.0354635 | JG15: 0.05 | JH15: 0.1528 | JI15: 0.0382 | JJ15: 0.1542194 | JK15: 0.43704297 | JL15: 0.035503109 | JM15: 0.049 | JN15: 0.1507 | JO15: 0.0458 | JP15: 0.15541533 | JQ15: 0.43872762 | JR15: 0.035919201 | JS15: 0.05 | JT15: 0.1481 | JU15: 0.0449 | JV15: 0.14189619 | JW15: 0.45363293 | JX15: 0.036557602
A16: 12 | B16: Credit Bank | C16: 0.052 | D16: 0.1691 | E16: 0.0627 | F16: 0.063488316 | G16: 0.86184581 | H16: 0.010883752 | I16: 0.06 | J16: 0.1636 | K16: 0.0739 | L16: 0.052899126 | M16: 0.86191408 | N16: 0.0099047212 | O16: 0.05 | P16: 0.1599 | Q16: 0.0602 | R16: 0.076138469 | S16: 0.96014263 | T16: -0.011341468 | U16: 0.057 | V16: 0.1546 | W16: 0.0631 | X16: 0.088460616 | Y16: 0.97607653 | Z16: 0.0019105684 | AA16: 0.056 | AB16: 0.1606 | AC16: 0.0703 | AD16: 0.083650261 | AE16: 0.97636691 | AF16: 0.0019410651 | AG16: 0.061 | AH16: 0.1682 | AI16: 0.0597 | AJ16: 0.051063782 | AK16: 0.92474064 | AL16: 0.0033828487 | AM16: 0.05 | AN16: 0.183 | AO16: 0.0801 | AP16: 0.060001599 | AQ16: 0.94541043 | AR16: -0.0062443797 | AS16: 0.038 | AT16: 0.1787 | AU16: 0.0645 | AV16: 0.053396372 | AW16: 0.83155484 | AX16: 0.011272149 | AY16: 0.038 | AZ16: 0.1818 | BA16: 0.058 | BB16: 0.048836853 | BC16: 0.76125203 | BD16: 0.015503897 | BE16: 0.044 | BF16: 0.1386 | BG16: 0.0634 | BH16: 0.070199191 | BI16: 0.73228648 | BJ16: 0.014956773 | BK16: 0.042 | BL16: 0.1366 | BM16: 0.0635 | BN16: 0.06732362 | BO16: 0.75018764 | BP16: 0.0094124906 | BQ16: 0.054 | BR16: 0.1361 | BS16: 0.1028 | BT16: 0.062799554 | BU16: 0.76561738 | BV16: 0.012372745 | BW16: 0.033 | BX16: 0.1366 | BY16: 0.0921 | BZ16: 0.085416917 | CA16: 0.74247343 | CB16: 0.013769488 | CC16: 0.032 | CD16: 0.1369 | CE16: 0.0706 | CF16: 0.069158025 | CG16: 0.74714774 | CH16: 0.013493878 | CI16: 0.038 | CJ16: 0.1364 | CK16: 0.045 | CL16: 0.07007659 | CM16: 0.77050039 | CN16: 0.0097383129 | CO16: 0.052 | CP16: 0.1349 | CQ16: 0.0418 | CR16: 0.10134984 | CS16: 0.77470186 | CT16: 0.014500452 | CU16: 0.061 | CV16: 0.1322 | CW16: 0.0428 | CX16: 0.087009709 | CY16: 0.70490737 | CZ16: 0.020731739 | DA16: 0.053 | DB16: 0.1266 | DC16: 0.057 | DD16: 0.075908488 | DE16: 0.70392248 | DF16: 0.024677197 | DG16: 0.056 | DH16: 0.1251 | DI16: 0.0571 | DJ16: 0.067530438 | DK16: 0.73395569 | DL16: 0.01493835 | DM16: 0.048 | DN16: 0.1251 | DO16: 0.0435 | DP16: 0.063815618 | DQ16: 0.72922601 | DR16: 0.018782339 | DS16: 0.06 | DT16: 0.1247 | DU16: 0.057 | DV16: 0.058061316 | DW16: 0.76689029 | DX16: 0.015902768 | DY16: 0.05 | DZ16: 0.1247 | EA16: 0.0383 | EB16: 0.06267443 | EC16: 0.80261446 | ED16: 0.016034633 | EE16: 0.051 | EF16: 0.1224 | EG16: 0.0582 | EH16: 0.08005684 | EI16: 0.75426572 | EJ16: 0.010686226 | EK16: 0.046 | EL16: 0.1209 | EM16: 0.0584 | EN16: 0.079080509 | EO16: 0.75565796 | EP16: 0.010688407 | EQ16: -0.041 | ER16: 0.1189 | ES16: 0.0459 | ET16: 0.076806155 | EU16: 0.81057565 | EV16: 0.0066039321 | EW16: -0.036 | EX16: 0.1175 | EY16: 0.042 | EZ16: 0.073056618 | FA16: 0.85064366 | FB16: 0.0051858372 | FC16: -0.003 | FD16: 0.1202 | FE16: 0.0562 | FF16: 0.087310035 | FG16: 0.8291849 | FH16: -0.0028443621 | FI16: 0.024 | FJ16: 0.1205 | FK16: 0.059 | FL16: 0.072676393 | FM16: 0.77307433 | FN16: 0.0111202 | FO16: 0.103 | FP16: 0.1202 | FQ16: 0.0632 | FR16: 0.071138805 | FS16: 0.78696187 | FT16: 0.0078240773 | FU16: 0.094 | FV16: 0.121 | FW16: 0.0691 | FX16: 0.16000343 | FY16: 0.84356373 | FZ16: 0.0031783658 | GA16: 0.076 | GB16: 0.1216 | GC16: 0.0573 | GD16: 0.21476552 | GE16: 0.84285991 | GF16: 0.005333486 | GG16: 0.059 | GH16: 0.1215 | GI16: 0.0556 | GJ16: 0.20283774 | GK16: 0.91082777 | GL16: 0.003884619 | GM16: 0.049 | GN16: 0.1227 | GO16: 0.0791 | GP16: 0.19839985 | GQ16: 0.91456355 | GR16: 0.0024298457 | GS16: 0.046 | GT16: 0.1241 | GU16: 0.0918 | GV16: 0.19727875 | GW16: 0.9379891 | GX16: 0.0018477683 | GY16: 0.049 | GZ16: 0.1267 | HA16: 0.0906 | HB16: 0.20986775 | HC16: 0.93577001 | HD16: -0.00037605245 | HE16: 0.054 | HF16: 0.1309 | HG16: 0.0919 | HH16: 0.20683605 | HI16: 0.96462586 | HJ16: 0.00060345536 | HK16: 0.055 | HL16: 0.1331 | HM16: 0.0788 | HN16: 0.21310925 | HO16: 0.91255173 | HP16: 0.0029878416 | HQ16: 0.06 | HR16: 0.1398 | HS16: 0.0678 | HT16: 0.22131519 | HU16: 0.87397633 | HV16: 0.001797898 | HW16: 0.056 | HX16: 0.1463 | HY16: 0.0663 | HZ16: 0.30878878 | IA16: 0.91174302 | IB16: 0.00093580678 | IC16: 0.049 | ID16: 0.1628 | IE16: 0.057 | IF16: 0.29677879 | IG16: 0.86208152 | IH16: 0.0016475934 | II16: 0.046 | IJ16: 0.1685 | IK16: 0.0622 | IL16: 0.29173708 | IM16: 1.0633898 | IN16: -0.0061484492 | IO16: 0.04 | IP16: 0.1691 | IQ16: 0.0356 | IR16: 0.60825741 | IS16: 1.0965156 | IT16: -0.0070283977 | IU16: 0.047 | IV16: 0.1689 | IW16: 0.0299 | IX16: 0.60825741 | IY16: 1.0965156 | IZ16: -0.0052712982 | JA16: 0.049 | JB16: 0.1577 | JC16: 0.0362 | JD16: 0.3951443 | JE16: 0.58177858 | JF16: 0.0086628552 | JG16: 0.05 | JH16: 0.1528 | JI16: 0.0382 | JJ16: 0.4011523 | JK16: 1.1258235 | JL16: -0.0070426799 | JM16: 0.049 | JN16: 0.1507 | JO16: 0.0458 | JP16: 0.39445455 | JQ16: 1.1961593 | JR16: -0.0098996783 | JS16: 0.05 | JT16: 0.1481 | JU16: 0.0449 | JV16: NA | JW16: NA | JX16: 0
A17: 13 | B17: Development Bank of Kenya | C17: 0.052 | D17: 0.1691 | E17: 0.0627 | F17: 0.12791569 | G17: 0.43291435 | H17: 0.013192524 | I17: 0.06 | J17: 0.1636 | K17: 0.0739 | L17: 0.11292884 | M17: 0.4193758 | N17: 0.013104055 | O17: 0.05 | P17: 0.1599 | Q17: 0.0602 | R17: 0.11792391 | S17: 0.42493865 | T17: 0.01352076 | U17: 0.057 | V17: 0.1546 | W17: 0.0631 | X17: 0.11972599 | Y17: 0.48057718 | Z17: 0.010433313 | AA17: 0.056 | AB17: 0.1606 | AC17: 0.0703 | AD17: 0.11480865 | AE17: 0.48908312 | AF17: 0.0097284673 | AG17: 0.061 | AH17: 0.1682 | AI17: 0.0597 | AJ17: 0.11631506 | AK17: 0.52295947 | AL17: 0.010084315 | AM17: 0.05 | AN17: 0.183 | AO17: 0.0801 | AP17: 0.16860077 | AQ17: 0.97263864 | AR17: 0.007081406 | AS17: 0.038 | AT17: 0.1787 | AU17: 0.0645 | AV17: 0.16870201 | AW17: 0.68607448 | AX17: 0.007630388 | AY17: 0.038 | AZ17: 0.1818 | BA17: 0.058 | BB17: 0.16815849 | BC17: 0.55891327 | BD17: 0.0081207792 | BE17: 0.044 | BF17: 0.1386 | BG17: 0.0634 | BH17: 0.1653989 | BI17: 0.52976873 | BJ17: 0.0082359568 | BK17: 0.042 | BL17: 0.1366 | BM17: 0.0635 | BN17: 0.20642059 | BO17: 0.63551177 | BP17: 0.0035804579 | BQ17: 0.054 | BR17: 0.1361 | BS17: 0.1028 | BT17: 0.20941329 | BU17: 0.68712168 | BV17: 0.003975924 | BW17: 0.033 | BX17: 0.1366 | BY17: 0.0921 | BZ17: 0.20729025 | CA17: 0.74112492 | CB17: 0.00078504367 | CC17: 0.032 | CD17: 0.1369 | CE17: 0.0706 | CF17: 0.18134409 | CG17: 0.7285719 | CH17: 0.0045043419 | CI17: 0.038 | CJ17: 0.1364 | CK17: 0.045 | CL17: 0.1734371 | CM17: 0.7621706 | CN17: 0.0016129117 | CO17: 0.052 | CP17: 0.1349 | CQ17: 0.0418 | CR17: 0.17097788 | CS17: 0.62756151 | CT17: 0.0063960354 | CU17: 0.061 | CV17: 0.1322 | CW17: 0.0428 | CX17: 0.17268366 | CY17: 0.59678098 | CZ17: 0.0079976078 | DA17: 0.053 | DB17: 0.1266 | DC17: 0.057 | DD17: 0.17727153 | DE17: 0.59494142 | DF17: 0.011968071 | DG17: 0.056 | DH17: 0.1251 | DI17: 0.0571 | DJ17: 0.22962738 | DK17: 0.66203516 | DL17: 0.0072335031 | DM17: 0.048 | DN17: 0.1251 | DO17: 0.0435 | DP17: 0.22903972 | DQ17: 0.081603435 | DR17: 0.2605035 | DS17: 0.06 | DT17: 0.1247 | DU17: 0.057 | DV17: 0.23364744 | DW17: 0.1459584 | DX17: 0.13201857 | DY17: 0.05 | DZ17: 0.1247 | EA17: 0.0383 | EB17: 0.23630671 | EC17: 0.20597294 | ED17: 0.088599159 | EE17: 0.051 | EF17: 0.1224 | EG17: 0.0582 | EH17: 0.26978476 | EI17: 0.2603318 | EJ17: 0.070343774 | EK17: 0.046 | EL17: 0.1209 | EM17: 0.0584 | EN17: 0.27107773 | EO17: 0.64356121 | EP17: 0.0062347495 | EQ17: -0.041 | ER17: 0.1189 | ES17: 0.0459 | ET17: 0.27468555 | EU17: 0.82582628 | EV17: 0.0020008245 | EW17: -0.036 | EX17: 0.1175 | EY17: 0.042 | EZ17: 0.27130592 | FA17: 0.82064346 | FB17: 0.0025148057 | FC17: -0.003 | FD17: 0.1202 | FE17: 0.0562 | FF17: 0.25606294 | FG17: 0.89350418 | FH17: 0.0012672763 | FI17: 0.024 | FJ17: 0.1205 | FK17: 0.059 | FL17: 0.25402849 | FM17: 1.036803 | FN17: 0.0018981366 | FO17: 0.103 | FP17: 0.1202 | FQ17: 0.0632 | FR17: 0.23299606 | FS17: 1.0193355 | FT17: 0.0021534457 | FU17: 0.094 | FV17: 0.121 | FW17: 0.0691 | FX17: 0.22752256 | FY17: 1.0714557 | FZ17: 0.0026080051 | GA17: 0.076 | GB17: 0.1216 | GC17: 0.0573 | GD17: 0.2243086 | GE17: 1.068654 | GF17: 0.003058532 | GG17: 0.059 | GH17: 0.1215 | GI17: 0.0556 | GJ17: 0.22109899 | GK17: 1.1386129 | GL17: 0.0012144158 | GM17: 0.049 | GN17: 0.1227 | GO17: 0.0791 | GP17: 0.22404452 | GQ17: 1.0808216 | GR17: 0.0032314665 | GS17: 0.046 | GT17: 0.1241 | GU17: 0.0918 | GV17: 0.2319285 | GW17: 0.62497846 | GX17: 0.002442809 | GY17: 0.049 | GZ17: 0.1267 | HA17: 0.0906 | HB17: 0.21701343 | HC17: 1.0721888 | HD17: 0.0037645846 | HE17: 0.054 | HF17: 0.1309 | HG17: 0.0919 | HH17: 0.19282457 | HI17: 1.6551316 | HJ17: 0.003236093 | HK17: 0.055 | HL17: 0.1331 | HM17: 0.0788 | HN17: 0.18942162 | HO17: 0.83023979 | HP17: 0.0054785772 | HQ17: 0.06 | HR17: 0.1398 | HS17: 0.0678 | HT17: 0.18535198 | HU17: 0.94426113 | HV17: 0.0030180801 | HW17: 0.056 | HX17: 0.1463 | HY17: 0.0663 | HZ17: 0.17834738 | IA17: 1.2328668 | IB17: 0.0025698316 | IC17: 0.049 | ID17: 0.1628 | IE17: 0.057 | IF17: 0.17267886 | IG17: 2.4610066 | IH17: 0.0034762754 | II17: 0.046 | IJ17: 0.1685 | IK17: 0.0622 | IL17: 0.17444851 | IM17: 3.8740997 | IN17: 0.002674166 | IO17: 0.04 | IP17: 0.1691 | IQ17: 0.0356 | IR17: 0.16943921 | IS17: 1.77537 | IT17: 0.0036997006 | IU17: 0.047 | IV17: 0.1689 | IW17: 0.0299 | IX17: 0.17213012 | IY17: 1.7562908 | IZ17: 0.0040760694 | JA17: 0.049 | JB17: 0.1577 | JC17: 0.0362 | JD17: 0.16837389 | JE17: 1.347027 | JF17: 0.0035044095 | JG17: 0.05 | JH17: 0.1528 | JI17: 0.0382 | JJ17: 0.16782781 | JK17: 1.0445856 | JL17: 0.002776304 | JM17: 0.049 | JN17: 0.1507 | JO17: 0.0458 | JP17: 0.16848145 | JQ17: 0.89402486 | JR17: 0.0046109944 | JS17: 0.05 | JT17: 0.1481 | JU17: 0.0449 | JV17: 0.1619574 | JW17: 0.26200285 | JX17: 0.0051039106
A18: 14 | B18: Diamond Trust Bank | C18: 0.052 | D18: 0.1691 | E18: 0.0627 | F18: 0.011502142 | G18: 0.40839966 | H18: 0.032910684 | I18: 0.06 | J18: 0.1636 | K18: 0.0739 | L18: 0.012307032 | M18: 0.39347294 | N18: 0.037114645 | O18: 0.05 | P18: 0.1599 | Q18: 0.0602 | R18: 0.011231348 | S18: 0.37892774 | T18: 0.032528313 | U18: 0.057 | V18: 0.1546 | W18: 0.0631 | X18: 0.011984379 | Y18: 0.3875291 | Z18: 0.032832471 | AA18: 0.056 | AB18: 0.1606 | AC18: 0.0703 | AD18: 0.011394451 | AE18: 0.37357435 | AF18: 0.031192165 | AG18: 0.061 | AH18: 0.1682 | AI18: 0.0597 | AJ18: 0.012670708 | AK18: 0.36973048 | AL18: 0.029631763 | AM18: 0.05 | AN18: 0.183 | AO18: 0.0801 | AP18: 0.025328338 | AQ18: 0.35137316 | AR18: 0.028861843 | AS18: 0.038 | AT18: 0.1787 | AU18: 0.0645 | AV18: 0.026710867 | AW18: 0.35391108 | AX18: 0.024629001 | AY18: 0.038 | AZ18: 0.1818 | BA18: 0.058 | BB18: 0.034502815 | BC18: 0.30960543 | BD18: 0.028741085 | BE18: 0.044 | BF18: 0.1386 | BG18: 0.0634 | BH18: 0.033757615 | BI18: 0.30553009 | BJ18: 0.026544265 | BK18: 0.042 | BL18: 0.1366 | BM18: 0.0635 | BN18: 0.031782117 | BO18: 0.30673079 | BP18: 0.028279949 | BQ18: 0.054 | BR18: 0.1361 | BS18: 0.1028 | BT18: 0.03390222 | BU18: 0.39145824 | BV18: 0.020225439 | BW18: 0.033 | BX18: 0.1366 | BY18: 0.0921 | BZ18: 0.039518554 | CA18: 0.37401613 | CB18: 0.022398056 | CC18: 0.032 | CD18: 0.1369 | CE18: 0.0706 | CF18: 0.054560639 | CG18: 0.35846967 | CH18: 0.020862634 | CI18: 0.038 | CJ18: 0.1364 | CK18: 0.045 | CL18: 0.066604941 | CM18: 0.3546966 | CN18: 0.021390952 | CO18: 0.052 | CP18: 0.1349 | CQ18: 0.0418 | CR18: 0.067488242 | CS18: 0.38831051 | CT18: 0.020642385 | CU18: 0.061 | CV18: 0.1322 | CW18: 0.0428 | CX18: 0.066401913 | CY18: 0.37358905 | CZ18: 0.021525082 | DA18: 0.053 | DB18: 0.1266 | DC18: 0.057 | DD18: 0.06981752 | DE18: 0.37461232 | DF18: 0.030698849 | DG18: 0.056 | DH18: 0.1251 | DI18: 0.0571 | DJ18: 0.062051893 | DK18: 0.37310588 | DL18: 0.020982396 | DM18: 0.048 | DN18: 0.1251 | DO18: 0.0435 | DP18: 0.061842995 | DQ18: 0.39531846 | DR18: 0.021824767 | DS18: 0.06 | DT18: 0.1247 | DU18: 0.057 | DV18: 0.060398507 | DW18: 0.3951628 | DX18: 0.023956187 | DY18: 0.05 | DZ18: 0.1247 | EA18: 0.0383 | EB18: 0.069689937 | EC18: 0.39352031 | ED18: 0.022840978 | EE18: 0.051 | EF18: 0.1224 | EG18: 0.0582 | EH18: 0.067094987 | EI18: 0.41952427 | EJ18: 0.020096096 | EK18: 0.046 | EL18: 0.1209 | EM18: 0.0584 | EN18: 0.067318204 | EO18: 0.37419143 | EP18: 0.022379127 | EQ18: -0.041 | ER18: 0.1189 | ES18: 0.0459 | ET18: 0.069327288 | EU18: 0.39212979 | EV18: 0.016649904 | EW18: -0.036 | EX18: 0.1175 | EY18: 0.042 | EZ18: 0.069057099 | FA18: 0.41180367 | FB18: 0.0178454 | FC18: -0.003 | FD18: 0.1202 | FE18: 0.0562 | FF18: 0.11064147 | FG18: 0.4216569 | FH18: 0.010631125 | FI18: 0.024 | FJ18: 0.1205 | FK18: 0.059 | FL18: 0.11080422 | FM18: 0.35269358 | FN18: 0.022824386 | FO18: 0.103 | FP18: 0.1202 | FQ18: 0.0632 | FR18: 0.11158592 | FS18: 0.36907847 | FT18: 0.016938626 | FU18: 0.094 | FV18: 0.121 | FW18: 0.0691 | FX18: 0.12658388 | FY18: 0.38657845 | FZ18: 0.018085225 | GA18: 0.076 | GB18: 0.1216 | GC18: 0.0573 | GD18: 0.14067184 | GE18: 0.39475221 | GF18: 0.0096811262 | GG18: 0.059 | GH18: 0.1215 | GI18: 0.0556 | GJ18: 0.13793318 | GK18: 0.387428 | GL18: 0.020738843 | GM18: 0.049 | GN18: 0.1227 | GO18: 0.0791 | GP18: 0.1402697 | GQ18: 0.39875943 | GR18: 0.016315563 | GS18: 0.046 | GT18: 0.1241 | GU18: 0.0918 | GV18: 0.13915296 | GW18: 0.38647058 | GX18: 0.017596819 | GY18: 0.049 | GZ18: 0.1267 | HA18: 0.0906 | HB18: 0.13226374 | HC18: 0.40952105 | HD18: 0.013182283 | HE18: 0.054 | HF18: 0.1309 | HG18: 0.0919 | HH18: 0.12858991 | HI18: 0.38792976 | HJ18: 0.02085801 | HK18: 0.055 | HL18: 0.1331 | HM18: 0.0788 | HN18: 0.12852153 | HO18: 0.43106687 | HP18: 0.017073121 | HQ18: 0.06 | HR18: 0.1398 | HS18: 0.0678 | HT18: 0.13426222 | HU18: 0.43737676 | HV18: 0.016442913 | HW18: 0.056 | HX18: 0.1463 | HY18: 0.0663 | HZ18: 0.15289019 | IA18: 0.44799268 | IB18: 0.01313595 | IC18: 0.049 | ID18: 0.1628 | IE18: 0.057 | IF18: 0.16583531 | IG18: 0.42876987 | IH18: 0.020072928 | II18: 0.046 | IJ18: 0.1685 | IK18: 0.0622 | IL18: 0.14832507 | IM18: 0.46032152 | IN18: 0.016377952 | IO18: 0.04 | IP18: 0.1691 | IQ18: 0.0356 | IR18: 0.14342202 | IS18: 0.46942462 | IT18: 0.015088196 | IU18: 0.047 | IV18: 0.1689 | IW18: 0.0299 | IX18: 0.14581261 | IY18: 0.48195983 | IZ18: 0.01360351 | JA18: 0.049 | JB18: 0.1577 | JC18: 0.0362 | JD18: 0.14740606 | JE18: 0.50677134 | JF18: 0.021467845 | JG18: 0.05 | JH18: 0.1528 | JI18: 0.0382 | JJ18: 0.14938908 | JK18: 0.4793946 | JL18: 0.018059764 | JM18: 0.049 | JN18: 0.1507 | JO18: 0.0458 | JP18: 0.14829967 | JQ18: 0.45831476 | JR18: 0.018637928 | JS18: 0.05 | JT18: 0.1481 | JU18: 0.0449 | JV18: 0.13481168 | JW18: 0.44338732 | JX18: 0.01892465
A19: 15 | B19: Dubai Bank | C19: 0.052 | D19: 0.1691 | E19: 0.0627 | F19: 0.3697142 | G19: 0.6502051 | H19: 0.011186195 | I19: 0.06 | J19: 0.1636 | K19: 0.0739 | L19: 0.37209625 | M19: 0.63122638 | N19: 0.0072389681 | O19: 0.05 | P19: 0.1599 | Q19: 0.0602 | R19: 0.32959663 | S19: 0.53063167 | T19: 0.0013672154 | U19: 0.057 | V19: 0.1546 | W19: 0.0631 | X19: 0.33534221 | Y19: 0.27221752 | Z19: 0.038940826 | AA19: 0.056 | AB19: 0.1606 | AC19: 0.0703 | AD19: NA | AE19: NA | AF19: NA | AG19: 0.061 | AH19: 0.1682 | AI19: 0.0597 | AJ19: NA | AK19: NA | AL19: NA | AM19: 0.05 | AN19: 0.183 | AO19: 0.0801 | AP19: NA | AQ19: NA | AR19: NA | AS19: 0.038 | AT19: 0.1787 | AU19: 0.0645 | AV19: NA | AW19: NA | AX19: NA | AY19: 0.038 | AZ19: 0.1818 | BA19: 0.058 | BB19: NA | BC19: NA | BD19: NA | BE19: 0.044 | BF19: 0.1386 | BG19: 0.0634 | BH19: NA | BI19: NA | BJ19: NA | BK19: 0.042 | BL19: 0.1366 | BM19: 0.0635 | BN19: NA | BO19: NA | BP19: NA | BQ19: 0.054 | BR19: 0.1361 | BS19: 0.1028 | BT19: NA | BU19: NA | BV19: NA | BW19: 0.033 | BX19: 0.1366 | BY19: 0.0921 | BZ19: NA | CA19: NA | CB19: NA | CC19: 0.032 | CD19: 0.1369 | CE19: 0.0706 | CF19: NA | CG19: NA | CH19: NA | CI19: 0.038 | CJ19: 0.1364 | CK19: 0.045 | CL19: NA | CM19: NA | CN19: NA | CO19: 0.052 | CP19: 0.1349 | CQ19: 0.0418 | CR19: NA | CS19: NA | CT19: NA | CU19: 0.061 | CV19: 0.1322 | CW19: 0.0428 | CX19: NA | CY19: NA | CZ19: NA | DA19: 0.053 | DB19: 0.1266 | DC19: 0.057 | DD19: NA | DE19: NA | DF19: NA | DG19: 0.056 | DH19: 0.1251 | DI19: 0.0571 | DJ19: NA | DK19: NA | DL19: NA | DM19: 0.048 | DN19: 0.1251 | DO19: 0.0435 | DP19: NA | DQ19: NA | DR19: NA | DS19: 0.06 | DT19: 0.1247 | DU19: 0.057 | DV19: NA | DW19: NA | DX19: NA | DY19: 0.05 | DZ19: 0.1247 | EA19: 0.0383 | EB19: NA | EC19: NA | ED19: NA | EE19: 0.051 | EF19: 0.1224 | EG19: 0.0582 | EH19: NA | EI19: NA | EJ19: NA | EK19: 0.046 | EL19: 0.1209 | EM19: 0.0584 | EN19: NA | EO19: NA | EP19: NA | EQ19: -0.041 | ER19: 0.1189 | ES19: 0.0459 | ET19: NA | EU19: NA | EV19: NA | EW19: -0.036 | EX19: 0.1175 | EY19: 0.042 | EZ19: NA | FA19: NA | FB19: NA | FC19: -0.003 | FD19: 0.1202 | FE19: 0.0562 | FF19: NA | FG19: NA | FH19: NA | FI19: 0.024 | FJ19: 0.1205 | FK19: 0.059 | FL19: NA | FM19: NA | FN19: NA | FO19: 0.103 | FP19: 0.1202 | FQ19: 0.0632 | FR19: NA | FS19: NA | FT19: NA | FU19: 0.094 | FV19: 0.121 | FW19: 0.0691 | FX19: NA | FY19: NA | FZ19: NA | GA19: 0.076 | GB19: 0.1216 | GC19: 0.0573 | GD19: NA | GE19: NA | GF19: NA | GG19: 0.059 | GH19: 0.1215 | GI19: 0.0556 | GJ19: NA | GK19: NA | GL19: NA | GM19: 0.049 | GN19: 0.1227 | GO19: 0.0791 | GP19: NA | GQ19: NA | GR19: NA | GS19: 0.046 | GT19: 0.1241 | GU19: 0.0918 | GV19: NA | GW19: NA | GX19: NA | GY19: 0.049 | GZ19: 0.1267 | HA19: 0.0906 | HB19: NA | HC19: NA | HD19: NA | HE19: 0.054 | HF19: 0.1309 | HG19: 0.0919 | HH19: NA | HI19: NA | HJ19: NA | HK19: 0.055 | HL19: 0.1331 | HM19: 0.0788 | HN19: NA | HO19: NA | HP19: NA | HQ19: 0.06 | HR19: 0.1398 | HS19: 0.0678 | HT19: NA | HU19: NA | HV19: NA | HW19: 0.056 | HX19: 0.1463 | HY19: 0.0663 | HZ19: NA | IA19: NA | IB19: NA | IC19: 0.049 | ID19: 0.1628 | IE19: 0.057 | IF19: NA | IG19: NA | IH19: NA | II19: 0.046 | IJ19: 0.1685 | IK19: 0.0622 | IL19: NA | IM19: NA | IN19: NA | IO19: 0.04 | IP19: 0.1691 | IQ19: 0.0356 | IR19: NA | IS19: NA | IT19: NA | IU19: 0.047 | IV19: 0.1689 | IW19: 0.0299 | IX19: NA | IY19: NA | IZ19: NA | JA19: 0.049 | JB19: 0.1577 | JC19: 0.0362 | JD19: NA | JE19: NA | JF19: NA | JG19: 0.05 | JH19: 0.1528 | JI19: 0.0382 | JJ19: NA | JK19: NA | JL19: NA | JM19: 0.049 | JN19: 0.1507 | JO19: 0.0458 | JP19: NA | JQ19: NA | JR19: NA | JS19: 0.05 | JT19: 0.1481 | JU19: 0.0449 | JV19: NA | JW19: NA | JX19: NA
A20: 16 | B20: EcoBank | C20: 0.052 | D20: 0.1691 | E20: 0.0627 | F20: 0.05335281 | G20: 1.2079043 | H20: 0.0030383339 | I20: 0.06 | J20: 0.1636 | K20: 0.0739 | L20: 0.098125245 | M20: 0.85476667 | N20: -0.0026847699 | O20: 0.05 | P20: 0.1599 | Q20: 0.0602 | R20: 0.080133265 | S20: 1.2558991 | T20: -0.0077307059 | U20: 0.057 | V20: 0.1546 | W20: 0.0631 | X20: 0.086698639 | Y20: 0.93681575 | Z20: 0.001213488 | AA20: 0.056 | AB20: 0.1606 | AC20: 0.0703 | AD20: 0.072102012 | AE20: 0.95526072 | AF20: 0 | AG20: 0.061 | AH20: 0.1682 | AI20: 0.0597 | AJ20: 0.05222615 | AK20: 0.98586107 | AL20: 0.0010816264 | AM20: 0.05 | AN20: 0.183 | AO20: 0.0801 | AP20: 0.058532739 | AQ20: 0.95331788 | AR20: 0.0018375784 | AS20: 0.038 | AT20: 0.1787 | AU20: 0.0645 | AV20: 0.058973539 | AW20: 0.85131649 | AX20: 0.0038300545 | AY20: 0.038 | AZ20: 0.1818 | BA20: 0.058 | BB20: 0.095025528 | BC20: 0.88836786 | BD20: 0.0022098719 | BE20: 0.044 | BF20: 0.1386 | BG20: 0.0634 | BH20: 0.11702093 | BI20: 0.92919646 | BJ20: 0.0010937391 | BK20: 0.042 | BL20: 0.1366 | BM20: 0.0635 | BN20: 0.14002236 | BO20: 2.3052279 | BP20: -0.040660489 | BQ20: 0.054 | BR20: 0.1361 | BS20: 0.1028 | BT20: 0.2376915 | BU20: 0.85800681 | BV20: -0.0041756917 | BW20: 0.033 | BX20: 0.1366 | BY20: 0.0921 | BZ20: 0.25553456 | CA20: 0.81865818 | CB20: 0.00032929512 | CC20: 0.032 | CD20: 0.1369 | CE20: 0.0706 | CF20: 0.24449896 | CG20: 0.81735081 | CH20: 0.0019537147 | CI20: 0.038 | CJ20: 0.1364 | CK20: 0.045 | CL20: 0.27376305 | CM20: 0.88352981 | CN20: -0.022178096 | CO20: 0.052 | CP20: 0.1349 | CQ20: 0.0418 | CR20: 0.2939599 | CS20: 0.80899232 | CT20: 0.0039755719 | CU20: 0.061 | CV20: 0.1322 | CW20: 0.0428 | CX20: 0.29029209 | CY20: 0.85824466 | CZ20: 0.0025299938 | DA20: 0.053 | DB20: 0.1266 | DC20: 0.057 | DD20: 0.27673632 | DE20: 0.88276438 | DF20: 0.0033250662 | DG20: 0.056 | DH20: 0.1251 | DI20: 0.0571 | DJ20: 0.14786253 | DK20: 0.90605467 | DL20: 0.0013062312 | DM20: 0.048 | DN20: 0.1251 | DO20: 0.0435 | DP20: 0.084345751 | DQ20: 0.80820383 | DR20: 0.005598894 | DS20: 0.06 | DT20: 0.1247 | DU20: 0.057 | DV20: 0.086970301 | DW20: 0.82011066 | DX20: 0.0049382355 | DY20: 0.05 | DZ20: 0.1247 | EA20: 0.0383 | EB20: 0.086925329 | EC20: 0.83612303 | ED20: 0.0033152713 | EE20: 0.051 | EF20: 0.1224 | EG20: 0.0582 | EH20: 0.12646903 | EI20: 0.89574508 | EJ20: 0.0037484251 | EK20: 0.046 | EL20: 0.1209 | EM20: 0.0584 | EN20: 0.12388437 | EO20: 0.87690748 | EP20: 0.0019593241 | EQ20: -0.041 | ER20: 0.1189 | ES20: 0.0459 | ET20: 0.11815825 | EU20: 0.86482118 | EV20: 0.0014427031 | EW20: -0.036 | EX20: 0.1175 | EY20: 0.042 | EZ20: 0.10625234 | FA20: 0.88273061 | FB20: -0.0020834251 | FC20: -0.003 | FD20: 0.1202 | FE20: 0.0562 | FF20: 0.10601984 | FG20: 0.87196513 | FH20: 7.6162249e-05 | FI20: 0.024 | FJ20: 0.1205 | FK20: 0.059 | FL20: 0.10421665 | FM20: 0.54828604 | FN20: 0.012866989 | FO20: 0.103 | FP20: 0.1202 | FQ20: 0.0632 | FR20: 0.10817175 | FS20: 0.67656439 | FT20: 0.0067789745 | FU20: 0.094 | FV20: 0.121 | FW20: 0.0691 | FX20: 0.11283136 | FY20: 0.74707358 | FZ20: 0.0082835181 | GA20: 0.076 | GB20: 0.1216 | GC20: 0.0573 | GD20: 0.10447396 | GE20: 0.75904984 | GF20: 0.007105858 | GG20: 0.059 | GH20: 0.1215 | GI20: 0.0556 | GJ20: 0.097309608 | GK20: 0.76160173 | GL20: 0.004193216 | GM20: 0.049 | GN20: 0.1227 | GO20: 0.0791 | GP20: 0.09970806 | GQ20: 0.65594527 | GR20: 0.012014937 | GS20: 0.046 | GT20: 0.1241 | GU20: 0.0918 | GV20: 0.089401133 | GW20: 0.6789842 | GX20: 0.012474302 | GY20: 0.049 | GZ20: 0.1267 | HA20: 0.0906 | HB20: 0.13302869 | HC20: 0.83128755 | HD20: 0.0066177424 | HE20: 0.054 | HF20: 0.1309 | HG20: 0.0919 | HH20: 0.12824497 | HI20: 0.89956063 | HJ20: 0.0030744078 | HK20: 0.055 | HL20: 0.1331 | HM20: 0.0788 | HN20: 0.12129632 | HO20: 0.88699809 | HP20: 0.0035623958 | HQ20: 0.06 | HR20: 0.1398 | HS20: 0.0678 | HT20: 0.12840461 | HU20: 0.86423726 | HV20: 0.0034077608 | HW20: 0.056 | HX20: 0.1463 | HY20: 0.0663 | HZ20: 0.13769168 | IA20: 0.81994701 | IB20: 0.0043098201 | IC20: 0.049 | ID20: 0.1628 | IE20: 0.057 | IF20: 0.14199887 | IG20: 0.96409046 | IH20: 0.003133067 | II20: 0.046 | IJ20: 0.1685 | IK20: 0.0622 | IL20: 0.15275102 | IM20: 0.97711493 | IN20: 0.0022070881 | IO20: 0.04 | IP20: 0.1691 | IQ20: 0.0356 | IR20: 0.10275919 | IS20: 1.0421331 | IT20: -0.00048606835 | IU20: 0.047 | IV20: 0.1689 | IW20: 0.0299 | IX20: 0.079150206 | IY20: 0.83549635 | IZ20: -0.030803237 | JA20: 0.049 | JB20: 0.1577 | JC20: 0.0362 | JD20: 0.075415965 | JE20: 0.83061271 | JF20: 0.0035738448 | JG20: 0.05 | JH20: 0.1528 | JI20: 0.0382 | JJ20: 0.081102817 | JK20: 0.67899443 | JL20: 0.0077793102 | JM20: 0.049 | JN20: 0.1507 | JO20: 0.0458 | JP20: 0.084604416 | JQ20: 0.70077666 | JR20: 0.007324769 | JS20: 0.05 | JT20: 0.1481 | JU20: 0.0449 | JV20: 0.097489902 | JW20: 0.72855601 | JX20: 0.0052639943
A21: 17 | B21: Spire bank | C21: 0.052 | D21: 0.1691 | E21: 0.0627 | F21: 0.095378708 | G21: 0.77460568 | H21: 0.0076870085 | I21: 0.06 | J21: 0.1636 | K21: 0.0739 | L21: 0.086476692 | M21: 0.81696156 | N21: 0.004124598 | O21: 0.05 | P21: 0.1599 | Q21: 0.0602 | R21: 0.19199448 | S21: 0.69869875 | T21: -0.020305591 | U21: 0.057 | V21: 0.1546 | W21: 0.0631 | X21: 0.24666379 | Y21: 0.78502989 | Z21: 0.00061006925 | AA21: 0.056 | AB21: 0.1606 | AC21: 0.0703 | AD21: 0.26671994 | AE21: 0.90331964 | AF21: 0.0042756655 | AG21: 0.061 | AH21: 0.1682 | AI21: 0.0597 | AJ21: 0.27316288 | AK21: 1.1010626 | AL21: -0.0050904311 | AM21: 0.05 | AN21: 0.183 | AO21: 0.0801 | AP21: 0.2499029 | AQ21: 1.3721682 | AR21: -0.031352538 | AS21: 0.038 | AT21: 0.1787 | AU21: 0.0645 | AV21: 0.23230649 | AW21: 1.194584 | AX21: -0.036579695 | AY21: 0.038 | AZ21: 0.1818 | BA21: 0.058 | BB21: 0.22964629 | BC21: 1.1415563 | BD21: -0.053565999 | BE21: 0.044 | BF21: 0.1386 | BG21: 0.0634 | BH21: 0.23100563 | BI21: 1.2695849 | BJ21: -0.049423452 | BK21: 0.042 | BL21: 0.1366 | BM21: 0.0635 | BN21: 0.14359685 | BO21: 1.3570798 | BP21: -0.053170728 | BQ21: 0.054 | BR21: 0.1361 | BS21: 0.1028 | BT21: 0.15310849 | BU21: 1.9955264 | BV21: -0.02961689 | BW21: 0.033 | BX21: 0.1366 | BY21: 0.0921 | BZ21: 0.16955717 | CA21: 1.8611566 | CB21: -0.028033899 | CC21: 0.032 | CD21: 0.1369 | CE21: 0.0706 | CF21: 0.20456178 | CG21: 1.8626376 | CH21: -0.041082864 | CI21: 0.038 | CJ21: 0.1364 | CK21: 0.045 | CL21: 0.29925375 | CM21: 2.4803869 | CN21: -0.090262752 | CO21: 0.052 | CP21: 0.1349 | CQ21: 0.0418 | CR21: 0.31445649 | CS21: 3.0064098 | CT21: -0.069970305 | CU21: 0.061 | CV21: 0.1322 | CW21: 0.0428 | CX21: 0.33031577 | CY21: 1.9239017 | CZ21: -0.075896207 | DA21: 0.053 | DB21: 0.1266 | DC21: 0.057 | DD21: 0.34483144 | DE21: 2.6261051 | DF21: -0.047146758 | DG21: 0.056 | DH21: 0.1251 | DI21: 0.0571 | DJ21: 0.35888771 | DK21: 3.9194582 | DL21: -0.22138491 | DM21: 0.048 | DN21: 0.1251 | DO21: 0.0435 | DP21: 0.37084932 | DQ21: 0.94275863 | DR21: 0.047957051 | DS21: 0.06 | DT21: 0.1247 | DU21: 0.057 | DV21: 0.39893893 | DW21: 1.1787025 | DX21: 0.019633953 | DY21: 0.05 | DZ21: 0.1247 | EA21: 0.0383 | EB21: 0.40830231 | EC21: 1.8760505 | ED21: 0.035592782 | EE21: 0.051 | EF21: 0.1224 | EG21: 0.0582 | EH21: 0.41558904 | EI21: 2.3033594 | EJ21: -0.058698735 | EK21: 0.046 | EL21: 0.1209 | EM21: 0.0584 | EN21: 0.42627479 | EO21: 83.118455 | EP21: -0.15209503 | EQ21: -0.041 | ER21: 0.1189 | ES21: 0.0459 | ET21: 0.44785439 | EU21: -22.649049 | EV21: -0.17121656 | EW21: -0.036 | EX21: 0.1175 | EY21: 0.042 | EZ21: 0.45133919 | FA21: -15.117849 | FB21: -0.16004838 | FC21: -0.003 | FD21: 0.1202 | FE21: 0.0562 | FF21: 0.48545568 | FG21: -17.156119 | FH21: -0.19423829 | FI21: 0.024 | FJ21: 0.1205 | FK21: 0.059 | FL21: 0.49240315 | FM21: -12.880891 | FN21: -0.19767236 | FO21: 0.103 | FP21: 0.1202 | FQ21: 0.0632 | FR21: 0.50018612 | FS21: -88.120952 | FT21: -0.19155145 | FU21: 0.094 | FV21: 0.121 | FW21: 0.0691 | FX21: 0.52221525 | FY21: -11.249794 | FZ21: -0.15833686 | GA21: 0.076 | GB21: 0.1216 | GC21: 0.0573 | GD21: NA | GE21: NA | GF21: 0 | GG21: 0.059 | GH21: 0.1215 | GI21: 0.0556 | GJ21: 0.55634357 | GK21: 5.4108847 | GL21: -0.40521207 | GM21: 0.049 | GN21: 0.1227 | GO21: 0.0791 | GP21: 0.57081216 | GQ21: 6.00464 | GR21: -0.45461972 | GS21: 0.046 | GT21: 0.1241 | GU21: 0.0918 | GV21: 0.58846129 | GW21: 6.5095253 | GX21: -0.4955139 | GY21: 0.049 | GZ21: 0.1267 | HA21: 0.0906 | HB21: NA | HC21: NA | HD21: NA | HE21: 0.054 | HF21: 0.1309 | HG21: 0.0919 | HH21: NA | HI21: NA | HJ21: NA | HK21: 0.055 | HL21: 0.1331 | HM21: 0.0788 | HN21: NA | HO21: NA | HP21: NA | HQ21: 0.06 | HR21: 0.1398 | HS21: 0.0678 | HT21: NA | HU21: NA | HV21: NA | HW21: 0.056 | HX21: 0.1463 | HY21: 0.0663 | HZ21: NA | IA21: NA | IB21: NA | IC21: 0.049 | ID21: 0.1628 | IE21: 0.057 | IF21: NA | IG21: NA | IH21: NA | II21: 0.046 | IJ21: 0.1685 | IK21: 0.0622 | IL21: NA | IM21: NA | IN21: NA | IO21: 0.04 | IP21: 0.1691 | IQ21: 0.0356 | IR21: NA | IS21: NA | IT21: NA | IU21: 0.047 | IV21: 0.1689 | IW21: 0.0299 | IX21: NA | IY21: NA | IZ21: NA | JA21: 0.049 | JB21: 0.1577 | JC21: 0.0362 | JD21: NA | JE21: NA | JF21: NA | JG21: 0.05 | JH21: 0.1528 | JI21: 0.0382 | JJ21: NA | JK21: NA | JL21: NA | JM21: 0.049 | JN21: 0.1507 | JO21: 0.0458 | JP21: NA | JQ21: NA | JR21: NA | JS21: 0.05 | JT21: 0.1481 | JU21: 0.0449 | JV21: NA | JW21: NA | JX21: NA
A22: 18 | B22: Equity Bank | C22: 0.052 | D22: 0.1691 | E22: 0.0627 | F22: 0.029562675 | G22: 0.45358042 | H22: 0.05396959 | I22: 0.06 | J22: 0.1636 | K22: 0.0739 | L22: 0.030742642 | M22: 0.65971313 | N22: 0.055263706 | O22: 0.05 | P22: 0.1599 | Q22: 0.0602 | R22: 0.029315864 | S22: 0.48330097 | T22: 0.065470192 | U22: 0.057 | V22: 0.1546 | W22: 0.0631 | X22: 0.030052458 | Y22: 0.47767114 | Z22: 0.05375642 | AA22: 0.056 | AB22: 0.1606 | AC22: 0.0703 | AD22: 0.030442419 | AE22: 0.47454901 | AF22: 0.051437388 | AG22: 0.061 | AH22: 0.1682 | AI22: 0.0597 | AJ22: 0.030721263 | AK22: 0.47381974 | AL22: 0.049614365 | AM22: 0.05 | AN22: 0.183 | AO22: 0.0801 | AP22: 0.022759977 | AQ22: 0.47086006 | AR22: 0.05239447 | AS22: 0.038 | AT22: 0.1787 | AU22: 0.0645 | AV22: 0.027851822 | AW22: 0.43292604 | AX22: 0.054087105 | AY22: 0.038 | AZ22: 0.1818 | BA22: 0.058 | BB22: 0.033952747 | BC22: 0.43584332 | BD22: 0.051984977 | BE22: 0.044 | BF22: 0.1386 | BG22: 0.0634 | BH22: 0.046545236 | BI22: 0.43136564 | BJ22: 0.050537517 | BK22: 0.042 | BL22: 0.1366 | BM22: 0.0635 | BN22: 0.05997334 | BO22: 0.44780958 | BP22: 0.042209657 | BQ22: 0.054 | BR22: 0.1361 | BS22: 0.1028 | BT22: 0.059891299 | BU22: 0.67890469 | BV22: 0.042452409 | BW22: 0.033 | BX22: 0.1366 | BY22: 0.0921 | BZ22: 0.061408191 | CA22: 0.44453239 | CB22: 0.040964724 | CC22: 0.032 | CD22: 0.1369 | CE22: 0.0706 | CF22: 0.062294687 | CG22: 0.44421074 | CH22: 0.042162451 | CI22: 0.038 | CJ22: 0.1364 | CK22: 0.045 | CL22: 0.055233946 | CM22: 0.46740362 | CN22: 0.041564682 | CO22: 0.052 | CP22: 0.1349 | CQ22: 0.0418 | CR22: 0.055913434 | CS22: 0.42454104 | CT22: 0.046371887 | CU22: 0.061 | CV22: 0.1322 | CW22: 0.0428 | CX22: 0.077908326 | CY22: 0.45572839 | CZ22: 0.0429835 | DA22: 0.053 | DB22: 0.1266 | DC22: 0.057 | DD22: 0.078989763 | DE22: 0.47044436 | DF22: 0.058644809 | DG22: 0.056 | DH22: 0.1251 | DI22: 0.0571 | DJ22: 0.061589064 | DK22: 0.47235896 | DL22: 0.03977433 | DM22: 0.048 | DN22: 0.1251 | DO22: 0.0435 | DP22: 0.073259276 | DQ22: 0.41764732 | DR22: 0.044538697 | DS22: 0.06 | DT22: 0.1247 | DU22: 0.057 | DV22: 0.073782432 | DW22: 0.44881608 | DX22: 0.04210001 | DY22: 0.05 | DZ22: 0.1247 | EA22: 0.0383 | EB22: 0.067410859 | EC22: 0.45866529 | ED22: 0.040348796 | EE22: 0.051 | EF22: 0.1224 | EG22: 0.0582 | EH22: 0.075435394 | EI22: 0.45703738 | EJ22: 0.039625941 | EK22: 0.046 | EL22: 0.1209 | EM22: 0.0584 | EN22: 0.088668217 | EO22: 0.45646709 | EP22: 0.029655923 | EQ22: -0.041 | ER22: 0.1189 | ES22: 0.0459 | ET22: 0.087233424 | EU22: 0.44238468 | EV22: 0.026828151 | EW22: -0.036 | EX22: 0.1175 | EY22: 0.042 | EZ22: 0.085646325 | FA22: 0.42032847 | FB22: 0.025617587 | FC22: -0.003 | FD22: 0.1202 | FE22: 0.0562 | FF22: 0.10484408 | FG22: 0.41118873 | FH22: 0.025313344 | FI22: 0.024 | FJ22: 0.1205 | FK22: 0.059 | FL22: 0.10358925 | FM22: 0.38478794 | FN22: 0.043405899 | FO22: 0.103 | FP22: 0.1202 | FQ22: 0.0632 | FR22: 0.099034823 | FS22: 0.38982592 | FT22: 0.041931051 | FU22: 0.094 | FV22: 0.121 | FW22: 0.0691 | FX22: 0.081873954 | FY22: 0.39835924 | FZ22: 0.040027784 | GA22: 0.076 | GB22: 0.1216 | GC22: 0.0573 | GD22: 0.070351853 | GE22: 0.3996622 | GF22: 0.043600618 | GG22: 0.059 | GH22: 0.1215 | GI22: 0.0556 | GJ22: 0.070843561 | GK22: 0.38472939 | GL22: 0.039382466 | GM22: 0.049 | GN22: 0.1227 | GO22: 0.0791 | GP22: 0.069424344 | GQ22: 0.39180047 | GR22: 0.040958979 | GS22: 0.046 | GT22: 0.1241 | GU22: 0.0918 | GV22: 0.070387073 | GW22: 0.41162104 | GX22: 0.036716902 | GY22: 0.049 | GZ22: 0.1267 | HA22: 0.0906 | HB22: 0.065450779 | HC22: 0.42014931 | HD22: 0.037702744 | HE22: 0.054 | HF22: 0.1309 | HG22: 0.0919 | HH22: 0.084402512 | HI22: 0.47056986 | HJ22: 0.032231842 | HK22: 0.055 | HL22: 0.1331 | HM22: 0.0788 | HN22: 0.10133853 | HO22: 0.46380865 | HP22: 0.033415423 | HQ22: 0.06 | HR22: 0.1398 | HS22: 0.0678 | HT22: 0.14168081 | HU22: 0.47949051 | HV22: 0.027624651 | HW22: 0.056 | HX22: 0.1463 | HY22: 0.0663 | HZ22: 0.12739601 | IA22: 0.48625224 | IB22: 0.028096051 | IC22: 0.049 | ID22: 0.1628 | IE22: 0.057 | IF22: 0.13258117 | IG22: 0.55018756 | IH22: 0.02241145 | II22: 0.046 | IJ22: 0.1685 | IK22: 0.0622 | IL22: 0.14480305 | IM22: 0.54567419 | IN22: 0.027587259 | IO22: 0.04 | IP22: 0.1691 | IQ22: 0.0356 | IR22: 0.14574817 | IS22: 0.5737385 | IT22: 0.027555171 | IU22: 0.047 | IV22: 0.1689 | IW22: 0.0299 | IX22: 0.1448106 | IY22: 0.60615634 | IZ22: 0.023693685 | JA22: 0.049 | JB22: 0.1577 | JC22: 0.0362 | JD22: 0.1516804 | JE22: 0.50794634 | JF22: 0.033772532 | JG22: 0.05 | JH22: 0.1528 | JI22: 0.0382 | JJ22: 0.16564418 | JK22: 0.48347113 | JL22: 0.038505067 | JM22: 0.049 | JN22: 0.1507 | JO22: 0.0458 | JP22: 0.14903334 | JQ22: 0.69894039 | JR22: 0.041336672 | JS22: 0.05 | JT22: 0.1481 | JU22: 0.0449 | JV22: 0.13360454 | JW22: 0.49442072 | JX22: 0.03790068
A23: 19 | B23: Family Bank Limited | C23: 0.052 | D23: 0.1691 | E23: 0.0627 | F23: 0.060646059 | G23: 0.57365388 | H23: 0.040097482 | I23: 0.06 | J23: 0.1636 | K23: 0.0739 | L23: 0.07284432 | M23: 0.596553 | N23: 0.036748234 | O23: 0.05 | P23: 0.1599 | Q23: 0.0602 | R23: 0.059274838 | S23: 0.62042758 | T23: 0.033815217 | U23: 0.057 | V23: 0.1546 | W23: 0.0631 | X23: 0.051480104 | Y23: 0.62433943 | Z23: 0.033414919 | AA23: 0.056 | AB23: 0.1606 | AC23: 0.0703 | AD23: 0.04552613 | AE23: 0.62094474 | AF23: 0.033433301 | AG23: 0.061 | AH23: 0.1682 | AI23: 0.0597 | AJ23: 0.045618994 | AK23: 0.61349128 | AL23: 0.033812885 | AM23: 0.05 | AN23: 0.183 | AO23: 0.0801 | AP23: 0.049022181 | AQ23: 0.66378705 | AR23: 0.027085581 | AS23: 0.038 | AT23: 0.1787 | AU23: 0.0645 | AV23: 0.056256749 | AW23: 0.73696513 | AX23: 0.016402687 | AY23: 0.038 | AZ23: 0.1818 | BA23: 0.058 | BB23: 0.070339182 | BC23: 0.72014329 | BD23: 0.017231461 | BE23: 0.044 | BF23: 0.1386 | BG23: 0.0634 | BH23: 0.089826234 | BI23: 0.72389236 | BJ23: 0.01569942 | BK23: 0.042 | BL23: 0.1366 | BM23: 0.0635 | BN23: 0.10687599 | BO23: 0.24453781 | BP23: 0.0043989949 | BQ23: 0.054 | BR23: 0.1361 | BS23: 0.1028 | BT23: 0.1330541 | BU23: 1.0068493 | BV23: -0.015179961 | BW23: 0.033 | BX23: 0.1366 | BY23: 0.0921 | BZ23: 0.13270977 | CA23: 1.0350733 | CB23: -0.014359997 | CC23: 0.032 | CD23: 0.1369 | CE23: 0.0706 | CF23: 0.13851548 | CG23: 1.0376522 | CH23: -0.014164722 | CI23: 0.038 | CJ23: 0.1364 | CK23: 0.045 | CL23: 0.16129253 | CM23: 0.31463167 | CN23: -0.014580486 | CO23: 0.052 | CP23: 0.1349 | CQ23: 0.0418 | CR23: 0.16650647 | CS23: 0.8454538 | CT23: 0.001649243 | CU23: 0.061 | CV23: 0.1322 | CW23: 0.0428 | CX23: 0.14272482 | CY23: 0.83832808 | CZ23: 0.0026259585 | DA23: 0.053 | DB23: 0.1266 | DC23: 0.057 | DD23: 0.13896359 | DE23: 0.82679983 | DF23: 0.0049095685 | DG23: 0.056 | DH23: 0.1251 | DI23: 0.0571 | DJ23: 0.1392301 | DK23: 0.82394294 | DL23: 0.0034546139 | DM23: 0.048 | DN23: 0.1251 | DO23: 0.0435 | DP23: 0.13518596 | DQ23: 0.76862956 | DR23: 0.0084110581 | DS23: 0.06 | DT23: 0.1247 | DU23: 0.057 | DV23: 0.13195251 | DW23: 0.76761652 | DX23: 0.0096719418 | DY23: 0.05 | DZ23: 0.1247 | EA23: 0.0383 | EB23: 0.12727989 | EC23: 0.48711434 | ED23: 0.012176487 | EE23: 0.051 | EF23: 0.1224 | EG23: 0.0582 | EH23: 0.12347566 | EI23: 0.72828501 | EJ23: 0.012292978 | EK23: 0.046 | EL23: 0.1209 | EM23: 0.0584 | EN23: 0.12870433 | EO23: 0.6773666 | EP23: 0.013738217 | EQ23: -0.041 | ER23: 0.1189 | ES23: 0.0459 | ET23: 0.1260399 | EU23: 0.69785026 | EV23: 0.014518721 | EW23: -0.036 | EX23: 0.1175 | EY23: 0.042 | EZ23: 0.12243637 | FA23: 0.64851218 | FB23: 0.01672182 | FC23: -0.003 | FD23: 0.1202 | FE23: 0.0562 | FF23: 0.12497579 | FG23: 0.67046483 | FH23: 0.012732678 | FI23: 0.024 | FJ23: 0.1205 | FK23: 0.059 | FL23: 0.12774357 | FM23: 0.57813912 | FN23: 0.020254821 | FO23: 0.103 | FP23: 0.1202 | FQ23: 0.0632 | FR23: 0.12864191 | FS23: 0.56959479 | FT23: 0.023120358 | FU23: 0.094 | FV23: 0.121 | FW23: 0.0691 | FX23: 0.1320836 | FY23: 0.57572163 | FZ23: 0.023543962 | GA23: 0.076 | GB23: 0.1216 | GC23: 0.0573 | GD23: 0.12435398 | GE23: 0.62859864 | GF23: 0.021553694 | GG23: 0.059 | GH23: 0.1215 | GI23: 0.0556 | GJ23: 0.12096755 | GK23: 0.56700806 | GL23: 0.023371012 | GM23: 0.049 | GN23: 0.1227 | GO23: 0.0791 | GP23: 0.1204724 | GQ23: 0.55853051 | GR23: 0.025933587 | GS23: 0.046 | GT23: 0.1241 | GU23: 0.0918 | GV23: 0.11960256 | GW23: 0.56751483 | GX23: 0.025986895 | GY23: 0.049 | GZ23: 0.1267 | HA23: 0.0906 | HB23: 0.11947439 | HC23: 0.64299538 | HD23: 0.018914813 | HE23: 0.054 | HF23: 0.1309 | HG23: 0.0919 | HH23: 0.1232509 | HI23: 0.61246702 | HJ23: 0.021061271 | HK23: 0.055 | HL23: 0.1331 | HM23: 0.0788 | HN23: 0.12441257 | HO23: 0.59748442 | HP23: 0.020524078 | HQ23: 0.06 | HR23: 0.1398 | HS23: 0.0678 | HT23: 0.12465393 | HU23: 0.6087649 | HV23: 0.018916228 | HW23: 0.056 | HX23: 0.1463 | HY23: 0.0663 | HZ23: 0.12374767 | IA23: 0.66194019 | IB23: 0.017799562 | IC23: 0.049 | ID23: 0.1628 | IE23: 0.057 | IF23: 0.12161928 | IG23: 0.60883545 | IH23: 0.02346877 | II23: 0.046 | IJ23: 0.1685 | IK23: 0.0622 | IL23: 0.11650586 | IM23: 0.6340397 | IN23: 0.020382993 | IO23: 0.04 | IP23: 0.1691 | IQ23: 0.0356 | IR23: 0.11364723 | IS23: 0.70753763 | IT23: 0.018726018 | IU23: 0.047 | IV23: 0.1689 | IW23: 0.0299 | IX23: 0.11433046 | IY23: 0.70105698 | IZ23: 0.020993607 | JA23: 0.049 | JB23: 0.1577 | JC23: 0.0362 | JD23: 0.11277566 | JE23: 0.59752986 | JF23: 0.030990979 | JG23: 0.05 | JH23: 0.1528 | JI23: 0.0382 | JJ23: 0.10888152 | JK23: 0.61327532 | JL23: 0.027886439 | JM23: 0.049 | JN23: 0.1507 | JO23: 0.0458 | JP23: 0.10740094 | JQ23: 0.5944787 | JR23: 0.0272289 | JS23: 0.05 | JT23: 0.1481 | JU23: 0.0449 | JV23: 0.11924031 | JW23: 0.58332141 | JX23: 0.029337164
A24: 20 | B24: SBM Bank | C24: 0.052 | D24: 0.1691 | E24: 0.0627 | F24: 0.065145628 | G24: 0.55697662 | H24: 0.01976093 | I24: 0.06 | J24: 0.1636 | K24: 0.0739 | L24: 0.074201024 | M24: 0.63848097 | N24: 0.015470082 | O24: 0.05 | P24: 0.1599 | Q24: 0.0602 | R24: 0.058153887 | S24: 0.62849938 | T24: 0.015133178 | U24: 0.057 | V24: 0.1546 | W24: 0.0631 | X24: 0.034245282 | Y24: 0.71767648 | Z24: 0.0083735654 | AA24: 0.056 | AB24: 0.1606 | AC24: 0.0703 | AD24: 0.097051116 | AE24: 0.75369338 | AF24: 0.0081305246 | AG24: 0.061 | AH24: 0.1682 | AI24: 0.0597 | AJ24: 0.060715733 | AK24: 0.71180855 | AL24: 0.0085249016 | AM24: 0.05 | AN24: 0.183 | AO24: 0.0801 | AP24: 0.12879609 | AQ24: 0.88074135 | AR24: -0.0054323975 | AS24: 0.038 | AT24: 0.1787 | AU24: 0.0645 | AV24: 0.13154239 | AW24: 0.85853761 | AX24: 0.0053897379 | AY24: 0.038 | AZ24: 0.1818 | BA24: 0.058 | BB24: NA | BC24: NA | BD24: NA | BE24: 0.044 | BF24: 0.1386 | BG24: 0.0634 | BH24: NA | BI24: NA | BJ24: NA | BK24: 0.042 | BL24: 0.1366 | BM24: 0.0635 | BN24: NA | BO24: NA | BP24: NA | BQ24: 0.054 | BR24: 0.1361 | BS24: 0.1028 | BT24: NA | BU24: NA | BV24: NA | BW24: 0.033 | BX24: 0.1366 | BY24: 0.0921 | BZ24: NA | CA24: NA | CB24: NA | CC24: 0.032 | CD24: 0.1369 | CE24: 0.0706 | CF24: NA | CG24: NA | CH24: NA | CI24: 0.038 | CJ24: 0.1364 | CK24: 0.045 | CL24: 0.42136469 | CM24: 1.8461035 | CN24: -0.05637904 | CO24: 0.052 | CP24: 0.1349 | CQ24: 0.0418 | CR24: NA | CS24: NA | CT24: 0 | CU24: 0.061 | CV24: 0.1322 | CW24: 0.0428 | CX24: NA | CY24: NA | CZ24: 0 | DA24: 0.053 | DB24: 0.1266 | DC24: 0.057 | DD24: 0.52734564 | DE24: 0.26786571 | DF24: 0.055666726 | DG24: 0.056 | DH24: 0.1251 | DI24: 0.0571 | DJ24: 0.55608699 | DK24: 0.47822351 | DL24: 0.031941642 | DM24: 0.048 | DN24: 0.1251 | DO24: 0.0435 | DP24: 0.52114842 | DQ24: 0.76488615 | DR24: 0.017688193 | DS24: 0.06 | DT24: 0.1247 | DU24: 0.057 | DV24: 0.51159453 | DW24: 0.73098501 | DX24: 0.016134348 | DY24: 0.05 | DZ24: 0.1247 | EA24: 0.0383 | EB24: 0.48578212 | EC24: 0.7170532 | ED24: 0.011968062 | EE24: 0.051 | EF24: 0.1224 | EG24: 0.0582 | EH24: 0.46006506 | EI24: 0.70589937 | EJ24: 0.0124639 | EK24: 0.046 | EL24: 0.1209 | EM24: 0.0584 | EN24: 0.39538857 | EO24: 0.75834588 | EP24: 0.003392562 | EQ24: -0.041 | ER24: 0.1189 | ES24: 0.0459 | ET24: 0.37962928 | EU24: 0.82614513 | EV24: 0.0025886579 | EW24: -0.036 | EX24: 0.1175 | EY24: 0.042 | EZ24: 0.35771997 | FA24: 0.77766127 | FB24: 0.0042385717 | FC24: -0.003 | FD24: 0.1202 | FE24: 0.0562 | FF24: 0.35376287 | FG24: 0.82865375 | FH24: 0.008581093 | FI24: 0.024 | FJ24: 0.1205 | FK24: 0.059 | FL24: 0.34823038 | FM24: 0.73790804 | FN24: 0.0012529699 | FO24: 0.103 | FP24: 0.1202 | FQ24: 0.0632 | FR24: 0.3397237 | FS24: 0.78104293 | FT24: 0.0031456818 | FU24: 0.094 | FV24: 0.121 | FW24: 0.0691 | FX24: 0.26870014 | FY24: 0.77063165 | FZ24: 0.0033971867 | GA24: 0.076 | GB24: 0.1216 | GC24: 0.0573 | GD24: 0.26335502 | GE24: 0.78043628 | GF24: 0.0042805667 | GG24: 0.059 | GH24: 0.1215 | GI24: 0.0556 | GJ24: 0.24506708 | GK24: 0.88703273 | GL24: 0.0022940446 | GM24: 0.049 | GN24: 0.1227 | GO24: 0.0791 | GP24: 0.2335114 | GQ24: 0.85775907 | GR24: 0.0044979001 | GS24: 0.046 | GT24: 0.1241 | GU24: 0.0918 | GV24: 0.21864592 | GW24: 0.87319065 | GX24: 0.0023296453 | GY24: 0.049 | GZ24: 0.1267 | HA24: 0.0906 | HB24: 0.20723386 | HC24: 0.88856987 | HD24: 0.0015937032 | HE24: 0.054 | HF24: 0.1309 | HG24: 0.0919 | HH24: 0.20607291 | HI24: 0.78404075 | HJ24: 0.001194062 | HK24: 0.055 | HL24: 0.1331 | HM24: 0.0788 | HN24: 0.19997402 | HO24: 0.78295828 | HP24: 0.0030031294 | HQ24: 0.06 | HR24: 0.1398 | HS24: 0.0678 | HT24: 0.19237031 | HU24: 0.82256333 | HV24: 0.0011864706 | HW24: 0.056 | HX24: 0.1463 | HY24: 0.0663 | HZ24: 0.19335909 | IA24: 0.83743319 | IB24: 0.0017069546 | IC24: 0.049 | ID24: 0.1628 | IE24: 0.057 | IF24: 0.19274254 | IG24: 1.4896888 | IH24: -0.015978006 | II24: 0.046 | IJ24: 0.1685 | IK24: 0.0622 | IL24: 0.19643718 | IM24: 1.4740309 | IN24: -0.020116615 | IO24: 0.04 | IP24: 0.1691 | IQ24: 0.0356 | IR24: 0.19490902 | IS24: 1.4581511 | IT24: -0.018525001 | IU24: 0.047 | IV24: 0.1689 | IW24: 0.0299 | IX24: 0.23041716 | IY24: 1.3032628 | IZ24: -0.010902123 | JA24: 0.049 | JB24: 0.1577 | JC24: 0.0362 | JD24: 0.23629116 | JE24: 0.89684198 | JF24: 0.00048519963 | JG24: 0.05 | JH24: 0.1528 | JI24: 0.0382 | JJ24: 0.23231884 | JK24: 0.86046453 | JL24: 0.0039027872 | JM24: 0.049 | JN24: 0.1507 | JO24: 0.0458 | JP24: 0.22939191 | JQ24: 0.85109146 | JR24: 0.0035815321 | JS24: 0.05 | JT24: 0.1481 | JU24: 0.0449 | JV24: 0.18888284 | JW24: 0.84668086 | JX24: 0.0041750415
A25: 21 | B25: GT Bank | C25: 0.052 | D25: 0.1691 | E25: 0.0627 | F25: 0.036962712 | G25: 0.61561985 | H25: 0.018449708 | I25: 0.06 | J25: 0.1636 | K25: 0.0739 | L25: 0.035275844 | M25: 0.58353021 | N25: 0.019032134 | O25: 0.05 | P25: 0.1599 | Q25: 0.0602 | R25: 0.021159953 | S25: 1.242833 | T25: 0.01820393 | U25: 0.057 | V25: 0.1546 | W25: 0.0631 | X25: 0.034594995 | Y25: 0.32894054 | Z25: 0.014221401 | AA25: 0.056 | AB25: 0.1606 | AC25: 0.0703 | AD25: 0.033076556 | AE25: 0.70293382 | AF25: 0.013884776 | AG25: 0.061 | AH25: 0.1682 | AI25: 0.0597 | AJ25: 0.030939662 | AK25: 1.1340571 | AL25: 0.014865585 | AM25: 0.05 | AN25: 0.183 | AO25: 0.0801 | AP25: 0.030726838 | AQ25: 0.69735269 | AR25: 0.015079052 | AS25: 0.038 | AT25: 0.1787 | AU25: 0.0645 | AV25: 0.025972124 | AW25: 0.65007642 | AX25: 0.019556108 | AY25: 0.038 | AZ25: 0.1818 | BA25: 0.058 | BB25: 0.026886518 | BC25: 0.6385984 | BD25: 0.019814734 | BE25: 0.044 | BF25: 0.1386 | BG25: 0.0634 | BH25: 0.056379681 | BI25: 0.56949654 | BJ25: 0.018304509 | BK25: 0.042 | BL25: 0.1366 | BM25: 0.0635 | BN25: 0.054521266 | BO25: 0.66819212 | BP25: 0.01514861 | BQ25: 0.054 | BR25: 0.1361 | BS25: 0.1028 | BT25: 0.058158333 | BU25: 1.0238676 | BV25: 0.0085810075 | BW25: 0.033 | BX25: 0.1366 | BY25: 0.0921 | BZ25: 0.045151263 | CA25: 0.76316058 | CB25: 0.0099057056 | CC25: 0.032 | CD25: 0.1369 | CE25: 0.0706 | CF25: 0.059522774 | CG25: 0.77078594 | CH25: 0.0094520744 | CI25: 0.038 | CJ25: 0.1364 | CK25: 0.045 | CL25: 0.079635869 | CM25: 0.71978801 | CN25: 0.006743105 | CO25: 0.052 | CP25: 0.1349 | CQ25: 0.0418 | CR25: 0.080728914 | CS25: 0.65464214 | CT25: 0.01465085 | CU25: 0.061 | CV25: 0.1322 | CW25: 0.0428 | CX25: 0.087032714 | CY25: 0.70001235 | CZ25: 0.013663015 | DA25: 0.053 | DB25: 0.1266 | DC25: 0.057 | DD25: 0.16814151 | DE25: 0.74499331 | DF25: 0.015469901 | DG25: 0.056 | DH25: 0.1251 | DI25: 0.0571 | DJ25: 0.14136541 | DK25: 0.74725526 | DL25: 0.0092891162 | DM25: 0.048 | DN25: 0.1251 | DO25: 0.0435 | DP25: 0.14604971 | DQ25: 0.7214444 | DR25: 0.013067803 | DS25: 0.06 | DT25: 0.1247 | DU25: 0.057 | DV25: 0.14909133 | DW25: 0.69414013 | DX25: 0.014192962 | DY25: 0.05 | DZ25: 0.1247 | EA25: 0.0383 | EB25: 0.14583748 | EC25: 0.67886938 | ED25: 0.01389845 | EE25: 0.051 | EF25: 0.1224 | EG25: 0.0582 | EH25: 0.13235786 | EI25: 0.67277133 | EJ25: 0.012767655 | EK25: 0.046 | EL25: 0.1209 | EM25: 0.0584 | EN25: 0.15812548 | EO25: 0.4844106 | EP25: 0.011610065 | EQ25: -0.041 | ER25: 0.1189 | ES25: 0.0459 | ET25: 0.15868656 | EU25: 0.52947277 | EV25: 0.014516673 | EW25: -0.036 | EX25: 0.1175 | EY25: 0.042 | EZ25: 0.1735743 | FA25: 0.55977684 | FB25: 0.012868645 | FC25: -0.003 | FD25: 0.1202 | FE25: 0.0562 | FF25: 0.1551513 | FG25: 0.52733065 | FH25: 0.012682783 | FI25: 0.024 | FJ25: 0.1205 | FK25: 0.059 | FL25: 0.12727489 | FM25: 0.55798988 | FN25: 0.012977155 | FO25: 0.103 | FP25: 0.1202 | FQ25: 0.0632 | FR25: 0.1080768 | FS25: 0.9106405 | FT25: 0.017365559 | FU25: 0.094 | FV25: 0.121 | FW25: 0.0691 | FX25: 0.10528344 | FY25: 0.51568162 | FZ25: 0.017858444 | GA25: 0.076 | GB25: 0.1216 | GC25: 0.0573 | GD25: 0.094512156 | GE25: 0.47446621 | GF25: 0.017603608 | GG25: 0.059 | GH25: 0.1215 | GI25: 0.0556 | GJ25: 0.094015756 | GK25: 0.40891183 | GL25: 0.023292898 | GM25: 0.049 | GN25: 0.1227 | GO25: 0.0791 | GP25: 0.10269138 | GQ25: 0.39844556 | GR25: 0.023901981 | GS25: 0.046 | GT25: 0.1241 | GU25: 0.0918 | GV25: 0.095549278 | GW25: 0.95976034 | GX25: 0.02706316 | GY25: 0.049 | GZ25: 0.1267 | HA25: 0.0906 | HB25: 0.091088927 | HC25: 0.43516516 | HD25: 0.022394401 | HE25: 0.054 | HF25: 0.1309 | HG25: 0.0919 | HH25: 0.14526471 | HI25: 0.43798035 | HJ25: 0.028650382 | HK25: 0.055 | HL25: 0.1331 | HM25: 0.0788 | HN25: 0.16264689 | HO25: 0.45185016 | HP25: 0.028249205 | HQ25: 0.06 | HR25: 0.1398 | HS25: 0.0678 | HT25: 0.20377431 | HU25: 0.42402844 | HV25: 0.03502198 | HW25: 0.056 | HX25: 0.1463 | HY25: 0.0663 | HZ25: 0.22981692 | IA25: 0.41189098 | IB25: 0.033694874 | IC25: 0.049 | ID25: 0.1628 | IE25: 0.057 | IF25: 0.26000793 | IG25: 0.64342414 | IH25: 0.028530668 | II25: 0.046 | IJ25: 0.1685 | IK25: 0.0622 | IL25: 0.28345273 | IM25: 0.44350168 | IN25: 0.028993891 | IO25: 0.04 | IP25: 0.1691 | IQ25: 0.0356 | IR25: 0.32166862 | IS25: 0.44786023 | IT25: 0.028865318 | IU25: 0.047 | IV25: 0.1689 | IW25: 0.0299 | IX25: 0.3871064 | IY25: 0.44718368 | IZ25: 0.011736239 | JA25: 0.049 | JB25: 0.1577 | JC25: 0.0362 | JD25: 0.4015076 | JE25: 0.61280618 | JF25: 0.015237973 | JG25: 0.05 | JH25: 0.1528 | JI25: 0.0382 | JJ25: 0.40144215 | JK25: 0.56573817 | JL25: 0.016265728 | JM25: 0.049 | JN25: 0.1507 | JO25: 0.0458 | JP25: 0.39705781 | JQ25: 0.57668563 | JR25: 0.016140627 | JS25: 0.05 | JT25: 0.1481 | JU25: 0.0449 | JV25: 0.17598424 | JW25: 0.58945828 | JX25: 0.011960828
A26: 22 | B26: Premier Bank | C26: 0.052 | D26: 0.1691 | E26: 0.0627 | F26: 0.14196613 | G26: 0.84871672 | H26: 0.0052433174 | I26: 0.06 | J26: 0.1636 | K26: 0.0739 | L26: 0.093544983 | M26: 0.85751419 | N26: 0.0059711529 | O26: 0.05 | P26: 0.1599 | Q26: 0.0602 | R26: 0.13091989 | S26: 0.84241542 | T26: 0.0037946203 | U26: 0.057 | V26: 0.1546 | W26: 0.0631 | X26: 0.1291631 | Y26: 0.77204523 | Z26: 0.010662067 | AA26: 0.056 | AB26: 0.1606 | AC26: 0.0703 | AD26: 0.13924947 | AE26: 0.79961821 | AF26: 0.0068706614 | AG26: 0.061 | AH26: 0.1682 | AI26: 0.0597 | AJ26: 0.15540253 | AK26: 0.79620729 | AL26: 0.0055110857 | AM26: 0.05 | AN26: 0.183 | AO26: 0.0801 | AP26: 0.18999463 | AQ26: 0.82877367 | AR26: -0.00081185801 | AS26: 0.038 | AT26: 0.1787 | AU26: 0.0645 | AV26: 0.17816775 | AW26: 0.68364892 | AX26: 0.015438289 | AY26: 0.038 | AZ26: 0.1818 | BA26: 0.058 | BB26: 0.16707176 | BC26: 0.74945481 | BD26: 0.011469347 | BE26: 0.044 | BF26: 0.1386 | BG26: 0.0634 | BH26: 0.1864746 | BI26: 0.81389247 | BJ26: 0.0068252377 | BK26: 0.042 | BL26: 0.1366 | BM26: 0.0635 | BN26: 0.24215972 | BO26: 0.83659693 | BP26: -0.0037751569 | BQ26: 0.054 | BR26: 0.1361 | BS26: 0.1028 | BT26: 0.24814848 | BU26: 0.69235456 | BV26: 0.011712056 | BW26: 0.033 | BX26: 0.1366 | BY26: 0.0921 | BZ26: 0.22459834 | CA26: 0.71316721 | CB26: 0.0065033512 | CC26: 0.032 | CD26: 0.1369 | CE26: 0.0706 | CF26: 0.24857012 | CG26: 0.69353661 | CH26: 0.005751101 | CI26: 0.038 | CJ26: 0.1364 | CK26: 0.045 | CL26: 0.28967676 | CM26: 0.68554371 | CN26: 0.0093927809 | CO26: 0.052 | CP26: 0.1349 | CQ26: 0.0418 | CR26: 0.29562519 | CS26: 0.77152131 | CT26: 0.0036671167 | CU26: 0.061 | CV26: 0.1322 | CW26: 0.0428 | CX26: 0.31535247 | CY26: 0.84963032 | CZ26: -0.0043004369 | DA26: 0.053 | DB26: 0.1266 | DC26: 0.057 | DD26: 0.33729202 | DE26: 0.90329665 | DF26: -0.011488414 | DG26: 0.056 | DH26: 0.1251 | DI26: 0.0571 | DJ26: 0.32803539 | DK26: 0.98089568 | DL26: -0.012035154 | DM26: 0.048 | DN26: 0.1251 | DO26: 0.0435 | DP26: 0.33178149 | DQ26: 1.0006221 | DR26: -0.0035846738 | DS26: 0.06 | DT26: 0.1247 | DU26: 0.057 | DV26: 0.30331019 | DW26: 0.97236673 | DX26: 0.0013674708 | DY26: 0.05 | DZ26: 0.1247 | EA26: 0.0383 | EB26: 0.30122864 | EC26: 1.0444905 | ED26: 0.0062469178 | EE26: 0.051 | EF26: 0.1224 | EG26: 0.0582 | EH26: 0.29304559 | EI26: 1.1334972 | EJ26: 0.010420839 | EK26: 0.046 | EL26: 0.1209 | EM26: 0.0584 | EN26: 0.29198305 | EO26: 0.98023837 | EP26: 0.0012713207 | EQ26: -0.041 | ER26: 0.1189 | ES26: 0.0459 | ET26: 0.29558331 | EU26: 0.95864599 | EV26: 0.002066224 | EW26: -0.036 | EX26: 0.1175 | EY26: 0.042 | EZ26: 0.28411185 | FA26: 0.86597552 | FB26: 0.0062813434 | FC26: -0.003 | FD26: 0.1202 | FE26: 0.0562 | FF26: 0.25527124 | FG26: 0.78990327 | FH26: 0.0099660677 | FI26: 0.024 | FJ26: 0.1205 | FK26: 0.059 | FL26: 0.26460271 | FM26: 0.5750598 | FN26: 0.013438855 | FO26: 0.103 | FP26: 0.1202 | FQ26: 0.0632 | FR26: 0.24325386 | FS26: 0.3382637 | FT26: 0.015545474 | FU26: 0.094 | FV26: 0.121 | FW26: 0.0691 | FX26: 0.21994513 | FY26: 0.62976933 | FZ26: 0.014705297 | GA26: 0.076 | GB26: 0.1216 | GC26: 0.0573 | GD26: 0.20620353 | GE26: 0.49117478 | GF26: 0.019286877 | GG26: 0.059 | GH26: 0.1215 | GI26: 0.0556 | GJ26: 0.20258569 | GK26: 0.70564848 | GL26: 0.013913893 | GM26: 0.049 | GN26: 0.1227 | GO26: 0.0791 | GP26: 0.19584829 | GQ26: 0.64803478 | GR26: 0.014563922 | GS26: 0.046 | GT26: 0.1241 | GU26: 0.0918 | GV26: 0.19663125 | GW26: 0.75173756 | GX26: 0.011712814 | GY26: 0.049 | GZ26: 0.1267 | HA26: 0.0906 | HB26: 0.31921595 | HC26: 0.7084387 | HD26: -0.010607409 | HE26: 0.054 | HF26: 0.1309 | HG26: 0.0919 | HH26: 0.3417631 | HI26: 1.0998998 | HJ26: 0.010077891 | HK26: 0.055 | HL26: 0.1331 | HM26: 0.0788 | HN26: 0.39739835 | HO26: 0.97580535 | HP26: -0.0022354857 | HQ26: 0.06 | HR26: 0.1398 | HS26: 0.0678 | HT26: 0.3958867 | HU26: 0.93738032 | HV26: -0.0033418162 | HW26: 0.056 | HX26: 0.1463 | HY26: 0.0663 | HZ26: 0.43819842 | IA26: 0.75220704 | IB26: -0.011052238 | IC26: 0.049 | ID26: 0.1628 | IE26: 0.057 | IF26: 0.35456985 | IG26: 1.0668065 | IH26: -0.0053178213 | II26: 0.046 | IJ26: 0.1685 | IK26: 0.0622 | IL26: 0.41175205 | IM26: 0.98662752 | IN26: -0.0013387353 | IO26: 0.04 | IP26: 0.1691 | IQ26: 0.0356 | IR26: 0.40581607 | IS26: 1.0107093 | IT26: -0.0023183438 | IU26: 0.047 | IV26: 0.1689 | IW26: 0.0299 | IX26: 0.4042439 | IY26: 0.97544374 | IZ26: -0.016638108 | JA26: 0.049 | JB26: 0.1577 | JC26: 0.0362 | JD26: 0.39883975 | JE26: 1.5180518 | JF26: -0.024796731 | JG26: 0.05 | JH26: 0.1528 | JI26: 0.0382 | JJ26: 0.50744596 | JK26: 1.1857699 | JL26: -0.011017642 | JM26: 0.049 | JN26: 0.1507 | JO26: 0.0458 | JP26: 0.39895379 | JQ26: 1.2051667 | JR26: -0.012853355 | JS26: 0.05 | JT26: 0.1481 | JU26: 0.0449 | JV26: 0.38448722 | JW26: 1.0185541 | JX26: -0.0093708051
A27: 23 | B27: Giro Commercial Bank | C27: 0.052 | D27: 0.1691 | E27: 0.0627 | F27: 0.050322149 | G27: 0.47701629 | H27: 0.036630541 | I27: 0.06 | J27: 0.1636 | K27: 0.0739 | L27: 0.047247831 | M27: 0.49286588 | N27: 0.033496402 | O27: 0.05 | P27: 0.1599 | Q27: 0.0602 | R27: 0.031062579 | S27: 0.46025798 | T27: 0.027561901 | U27: 0.057 | V27: 0.1546 | W27: 0.0631 | X27: 0.021622546 | Y27: 0.44562891 | Z27: 0.034291897 | AA27: 0.056 | AB27: 0.1606 | AC27: 0.0703 | AD27: 0.01722624 | AE27: 0.46026306 | AF27: 0.03040934 | AG27: 0.061 | AH27: 0.1682 | AI27: 0.0597 | AJ27: 0.014968805 | AK27: 0.45451261 | AL27: 0.032819613 | AM27: 0.05 | AN27: 0.183 | AO27: 0.0801 | AP27: 0.01905471 | AQ27: 0.48766437 | AR27: 0.029291415 | AS27: 0.038 | AT27: 0.1787 | AU27: 0.0645 | AV27: 0.018234766 | AW27: 0.39406881 | AX27: 0.041967071 | AY27: 0.038 | AZ27: 0.1818 | BA27: 0.058 | BB27: 0.018747812 | BC27: 0.39780601 | BD27: 0.043496497 | BE27: 0.044 | BF27: 0.1386 | BG27: 0.0634 | BH27: 0.018843252 | BI27: 0.44012338 | BJ27: 0.042835549 | BK27: 0.042 | BL27: 0.1366 | BM27: 0.0635 | BN27: 0.0205097 | BO27: 0.45750416 | BP27: 0.030660189 | BQ27: 0.054 | BR27: 0.1361 | BS27: 0.1028 | BT27: NA | BU27: NA | BV27: NA | BW27: 0.033 | BX27: 0.1366 | BY27: 0.0921 | BZ27: NA | CA27: NA | CB27: NA | CC27: 0.032 | CD27: 0.1369 | CE27: 0.0706 | CF27: NA | CG27: NA | CH27: NA | CI27: 0.038 | CJ27: 0.1364 | CK27: 0.045 | CL27: NA | CM27: NA | CN27: NA | CO27: 0.052 | CP27: 0.1349 | CQ27: 0.0418 | CR27: NA | CS27: NA | CT27: NA | CU27: 0.061 | CV27: 0.1322 | CW27: 0.0428 | CX27: NA | CY27: NA | CZ27: NA | DA27: 0.053 | DB27: 0.1266 | DC27: 0.057 | DD27: NA | DE27: NA | DF27: NA | DG27: 0.056 | DH27: 0.1251 | DI27: 0.0571 | DJ27: NA | DK27: NA | DL27: NA | DM27: 0.048 | DN27: 0.1251 | DO27: 0.0435 | DP27: NA | DQ27: NA | DR27: NA | DS27: 0.06 | DT27: 0.1247 | DU27: 0.057 | DV27: NA | DW27: NA | DX27: NA | DY27: 0.05 | DZ27: 0.1247 | EA27: 0.0383 | EB27: NA | EC27: NA | ED27: NA | EE27: 0.051 | EF27: 0.1224 | EG27: 0.0582 | EH27: NA | EI27: NA | EJ27: NA | EK27: 0.046 | EL27: 0.1209 | EM27: 0.0584 | EN27: NA | EO27: NA | EP27: NA | EQ27: -0.041 | ER27: 0.1189 | ES27: 0.0459 | ET27: NA | EU27: NA | EV27: NA | EW27: -0.036 | EX27: 0.1175 | EY27: 0.042 | EZ27: NA | FA27: NA | FB27: NA | FC27: -0.003 | FD27: 0.1202 | FE27: 0.0562 | FF27: NA | FG27: NA | FH27: NA | FI27: 0.024 | FJ27: 0.1205 | FK27: 0.059 | FL27: NA | FM27: NA | FN27: NA | FO27: 0.103 | FP27: 0.1202 | FQ27: 0.0632 | FR27: NA | FS27: NA | FT27: NA | FU27: 0.094 | FV27: 0.121 | FW27: 0.0691 | FX27: NA | FY27: NA | FZ27: NA | GA27: 0.076 | GB27: 0.1216 | GC27: 0.0573 | GD27: NA | GE27: NA | GF27: NA | GG27: 0.059 | GH27: 0.1215 | GI27: 0.0556 | GJ27: NA | GK27: NA | GL27: NA | GM27: 0.049 | GN27: 0.1227 | GO27: 0.0791 | GP27: NA | GQ27: NA | GR27: NA | GS27: 0.046 | GT27: 0.1241 | GU27: 0.0918 | GV27: NA | GW27: NA | GX27: NA | GY27: 0.049 | GZ27: 0.1267 | HA27: 0.0906 | HB27: NA | HC27: NA | HD27: NA | HE27: 0.054 | HF27: 0.1309 | HG27: 0.0919 | HH27: NA | HI27: NA | HJ27: NA | HK27: 0.055 | HL27: 0.1331 | HM27: 0.0788 | HN27: NA | HO27: NA | HP27: NA | HQ27: 0.06 | HR27: 0.1398 | HS27: 0.0678 | HT27: NA | HU27: NA | HV27: NA | HW27: 0.056 | HX27: 0.1463 | HY27: 0.0663 | HZ27: NA | IA27: NA | IB27: NA | IC27: 0.049 | ID27: 0.1628 | IE27: 0.057 | IF27: NA | IG27: NA | IH27: NA | II27: 0.046 | IJ27: 0.1685 | IK27: 0.0622 | IL27: NA | IM27: NA | IN27: NA | IO27: 0.04 | IP27: 0.1691 | IQ27: 0.0356 | IR27: NA | IS27: NA | IT27: NA | IU27: 0.047 | IV27: 0.1689 | IW27: 0.0299 | IX27: NA | IY27: NA | IZ27: NA | JA27: 0.049 | JB27: 0.1577 | JC27: 0.0362 | JD27: NA | JE27: NA | JF27: NA | JG27: 0.05 | JH27: 0.1528 | JI27: 0.0382 | JJ27: NA | JK27: NA | JL27: NA | JM27: 0.049 | JN27: 0.1507 | JO27: 0.0458 | JP27: NA | JQ27: NA | JR27: NA | JS27: 0.05 | JT27: 0.1481 | JU27: 0.0449 | JV27: NA | JW27: NA | JX27: NA
A28: 24 | B28: Guardian Bank | C28: 0.052 | D28: 0.1691 | E28: 0.0627 | F28: 0.049393847 | G28: 0.59341733 | H28: 0.018177923 | I28: 0.06 | J28: 0.1636 | K28: 0.0739 | L28: 0.049140516 | M28: 0.57643091 | N28: 0.019517673 | O28: 0.05 | P28: 0.1599 | Q28: 0.0602 | R28: 0.060970981 | S28: 0.5180145 | T28: 0.019065739 | U28: 0.057 | V28: 0.1546 | W28: 0.0631 | X28: 0.05749222 | Y28: 0.22433555 | Z28: 0.017552762 | AA28: 0.056 | AB28: 0.1606 | AC28: 0.0703 | AD28: 0.058772583 | AE28: 0.60476378 | AF28: 0.017868501 | AG28: 0.061 | AH28: 0.1682 | AI28: 0.0597 | AJ28: 0.055864569 | AK28: 0.59716668 | AL28: 0.021474533 | AM28: 0.05 | AN28: 0.183 | AO28: 0.0801 | AP28: 0.07661987 | AQ28: 0.5819567 | AR28: 0.015718183 | AS28: 0.038 | AT28: 0.1787 | AU28: 0.0645 | AV28: 0.074114438 | AW28: 0.7072441 | AX28: 0.013343184 | AY28: 0.038 | AZ28: 0.1818 | BA28: 0.058 | BB28: 0.068869462 | BC28: 0.65244853 | BD28: 0.0055077131 | BE28: 0.044 | BF28: 0.1386 | BG28: 0.0634 | BH28: 0.068210584 | BI28: 0.61235718 | BJ28: 0.005817683 | BK28: 0.042 | BL28: 0.1366 | BM28: 0.0635 | BN28: 0.055260539 | BO28: 0.54046269 | BP28: 0.015700374 | BQ28: 0.054 | BR28: 0.1361 | BS28: 0.1028 | BT28: 0.051655354 | BU28: 0.74831188 | BV28: 0.013416268 | BW28: 0.033 | BX28: 0.1366 | BY28: 0.0921 | BZ28: 0.05073387 | CA28: 0.69595405 | CB28: 0.010325031 | CC28: 0.032 | CD28: 0.1369 | CE28: 0.0706 | CF28: 0.051464008 | CG28: 0.69305251 | CH28: 0.0099181222 | CI28: 0.038 | CJ28: 0.1364 | CK28: 0.045 | CL28: 0.082206869 | CM28: 0.70215013 | CN28: 0.010490456 | CO28: 0.052 | CP28: 0.1349 | CQ28: 0.0418 | CR28: 0.082097447 | CS28: 0.72274659 | CT28: 0.0069615004 | CU28: 0.061 | CV28: 0.1322 | CW28: 0.0428 | CX28: 0.072789976 | CY28: 0.71543285 | CZ28: 0.049443348 | DA28: 0.053 | DB28: 0.1266 | DC28: 0.057 | DD28: 0.068310462 | DE28: 0.50352041 | DF28: 0.041063018 | DG28: 0.056 | DH28: 0.1251 | DI28: 0.0571 | DJ28: 0.070371762 | DK28: 0.60990789 | DL28: 0.01410297 | DM28: 0.048 | DN28: 0.1251 | DO28: 0.0435 | DP28: 0.065975882 | DQ28: 0.65778622 | DR28: 0.0093077467 | DS28: 0.06 | DT28: 0.1247 | DU28: 0.057 | DV28: 0.067974971 | DW28: 0.66045478 | DX28: 0.010634074 | DY28: 0.05 | DZ28: 0.1247 | EA28: 0.0383 | EB28: 0.064984981 | EC28: 0.90638454 | ED28: 0.011090812 | EE28: 0.051 | EF28: 0.1224 | EG28: 0.0582 | EH28: 0.064466925 | EI28: 0.70625432 | EJ28: 0.011276904 | EK28: 0.046 | EL28: 0.1209 | EM28: 0.0584 | EN28: 0.067124628 | EO28: 0.52273612 | EP28: 0.028260496 | EQ28: -0.041 | ER28: 0.1189 | ES28: 0.0459 | ET28: 0.06723609 | EU28: 0.64324647 | EV28: 0.016623374 | EW28: -0.036 | EX28: 0.1175 | EY28: 0.042 | EZ28: 0.072193332 | FA28: 0.70979997 | FB28: 0.011767358 | FC28: -0.003 | FD28: 0.1202 | FE28: 0.0562 | FF28: 0.097769343 | FG28: 0.76105795 | FH28: 0.005668843 | FI28: 0.024 | FJ28: 0.1205 | FK28: 0.059 | FL28: 0.097622383 | FM28: 0.65534881 | FN28: 0.0093376093 | FO28: 0.103 | FP28: 0.1202 | FQ28: 0.0632 | FR28: 0.096210689 | FS28: 0.70278711 | FT28: 0.0061056817 | FU28: 0.094 | FV28: 0.121 | FW28: 0.0691 | FX28: 0.098836825 | FY28: 0.72121209 | FZ28: 0.0056248332 | GA28: 0.076 | GB28: 0.1216 | GC28: 0.0573 | GD28: 0.11512173 | GE28: 0.68528843 | GF28: 0.0090572771 | GG28: 0.059 | GH28: 0.1215 | GI28: 0.0556 | GJ28: 0.10792787 | GK28: 0.67007801 | GL28: 0.016483768 | GM28: 0.049 | GN28: 0.1227 | GO28: 0.0791 | GP28: 0.095941547 | GQ28: 0.66531446 | GR28: 0.020318682 | GS28: 0.046 | GT28: 0.1241 | GU28: 0.0918 | GV28: 0.090188112 | GW28: 0.52850708 | GX28: 0.02054463 | GY28: 0.049 | GZ28: 0.1267 | HA28: 0.0906 | HB28: 0.11855826 | HC28: 0.62951858 | HD28: 0.014961075 | HE28: 0.054 | HF28: 0.1309 | HG28: 0.0919 | HH28: 0.099280449 | HI28: 0.65767841 | HJ28: 0.018838963 | HK28: 0.055 | HL28: 0.1331 | HM28: 0.0788 | HN28: 0.099099273 | HO28: 0.69437255 | HP28: 0.015404826 | HQ28: 0.06 | HR28: 0.1398 | HS28: 0.0678 | HT28: 0.099653418 | HU28: 0.65265515 | HV28: 0.017564267 | HW28: 0.056 | HX28: 0.1463 | HY28: 0.0663 | HZ28: 0.098475035 | IA28: 0.62733436 | IB28: 0.021499193 | IC28: 0.049 | ID28: 0.1628 | IE28: 0.057 | IF28: 0.088507589 | IG28: 0.4941069 | IH28: 0.034094569 | II28: 0.046 | IJ28: 0.1685 | IK28: 0.0622 | IL28: 0.079544679 | IM28: 0.50482429 | IN28: 0.028682989 | IO28: 0.04 | IP28: 0.1691 | IQ28: 0.0356 | IR28: 0.083343501 | IS28: 0.49006068 | IT28: 0.042450985 | IU28: 0.047 | IV28: 0.1689 | IW28: 0.0299 | IX28: 0.094168623 | IY28: 0.62854863 | IZ28: 0.030710034 | JA28: 0.049 | JB28: 0.1577 | JC28: 0.0362 | JD28: 0.13977078 | JE28: 0.6605672 | JF28: 0.014305251 | JG28: 0.05 | JH28: 0.1528 | JI28: 0.0382 | JJ28: 0.062560245 | JK28: 0.69313326 | JL28: 0.011461319 | JM28: 0.049 | JN28: 0.1507 | JO28: 0.0458 | JP28: 0.062187377 | JQ28: 0.69076331 | JR28: 0.011582836 | JS28: 0.05 | JT28: 0.1481 | JU28: 0.0449 | JV28: 0.082504492 | JW28: 0.7566739 | JX28: 0.010663737
A29: 25 | B29: Gulf African Bank | C29: 0.052 | D29: 0.1691 | E29: 0.0627 | F29: 0.054571883 | G29: 0.6625295 | H29: 0.020829727 | I29: 0.06 | J29: 0.1636 | K29: 0.0739 | L29: 0.055261538 | M29: 0.65943447 | N29: 0.021472243 | O29: 0.05 | P29: 0.1599 | Q29: 0.0602 | R29: 0.061028773 | S29: 0.66227924 | T29: 0.022418246 | U29: 0.057 | V29: 0.1546 | W29: 0.0631 | X29: 0.082310494 | Y29: 0.57854584 | Z29: 0.032154831 | AA29: 0.056 | AB29: 0.1606 | AC29: 0.0703 | AD29: 0.055510679 | AE29: 0.51416048 | AF29: 0.038887599 | AG29: 0.061 | AH29: 0.1682 | AI29: 0.0597 | AJ29: 0.051643583 | AK29: 0.53438559 | AL29: 0.03537275 | AM29: 0.05 | AN29: 0.183 | AO29: 0.0801 | AP29: 0.077669839 | AQ29: 0.54488755 | AR29: 0.032864639 | AS29: 0.038 | AT29: 0.1787 | AU29: 0.0645 | AV29: 0.080981726 | AW29: 0.57703656 | AX29: 0.029612715 | AY29: 0.038 | AZ29: 0.1818 | BA29: 0.058 | BB29: 0.062474915 | BC29: 0.62788693 | BD29: 0.024342091 | BE29: 0.044 | BF29: 0.1386 | BG29: 0.0634 | BH29: 0.076213588 | BI29: 0.64034908 | BJ29: 0.021833079 | BK29: 0.042 | BL29: 0.1366 | BM29: 0.0635 | BN29: 0.084472067 | BO29: 0.67063969 | BP29: 0.019214211 | BQ29: 0.054 | BR29: 0.1361 | BS29: 0.1028 | BT29: 0.070186618 | BU29: 1.5381187 | BV29: 0.017940941 | BW29: 0.033 | BX29: 0.1366 | BY29: 0.0921 | BZ29: 0.075755059 | CA29: 0.66278402 | CB29: 0.013393625 | CC29: 0.032 | CD29: 0.1369 | CE29: 0.0706 | CF29: 0.070721653 | CG29: 0.64883726 | CH29: 0.015384994 | CI29: 0.038 | CJ29: 0.1364 | CK29: 0.045 | CL29: 0.084966571 | CM29: 0.65862602 | CN29: 0.0052555653 | CO29: 0.052 | CP29: 0.1349 | CQ29: 0.0418 | CR29: 0.10907738 | CS29: 0.67666646 | CT29: 0.012620147 | CU29: 0.061 | CV29: 0.1322 | CW29: 0.0428 | CX29: 0.09656044 | CY29: 0.67247999 | CZ29: 0.013358657 | DA29: 0.053 | DB29: 0.1266 | DC29: 0.057 | DD29: 0.099636503 | DE29: 0.68813171 | DF29: 0.012221572 | DG29: 0.056 | DH29: 0.1251 | DI29: 0.0571 | DJ29: 0.096130465 | DK29: 0.65447982 | DL29: 0.0040713283 | DM29: 0.048 | DN29: 0.1251 | DO29: 0.0435 | DP29: 0.11084597 | DQ29: 0.69433639 | DR29: 0.0053009462 | DS29: 0.06 | DT29: 0.1247 | DU29: 0.057 | DV29: 0.11587039 | DW29: 0.68601411 | DX29: 0.0021676246 | DY29: 0.05 | DZ29: 0.1247 | EA29: 0.0383 | EB29: 0.120588 | EC29: 0.94089746 | ED29: 0.0023367517 | EE29: 0.051 | EF29: 0.1224 | EG29: 0.0582 | EH29: 0.13302242 | EI29: 0.67101028 | EJ29: 0.0048795769 | EK29: 0.046 | EL29: 0.1209 | EM29: 0.0584 | EN29: 0.12578826 | EO29: 0.66570603 | EP29: 0.011320084 | EQ29: -0.041 | ER29: 0.1189 | ES29: 0.0459 | ET29: 0.12789026 | EU29: 0.7138105 | EV29: 0.0085580517 | EW29: -0.036 | EX29: 0.1175 | EY29: 0.042 | EZ29: 0.14173347 | FA29: 0.68767753 | FB29: 0.0047990438 | FC29: -0.003 | FD29: 0.1202 | FE29: 0.0562 | FF29: 0.15757962 | FG29: 0.66681124 | FH29: 0.0055613533 | FI29: 0.024 | FJ29: 0.1205 | FK29: 0.059 | FL29: 0.12417011 | FM29: 0.63335785 | FN29: 0.015612948 | FO29: 0.103 | FP29: 0.1202 | FQ29: 0.0632 | FR29: 0.14607389 | FS29: 0.64514859 | FT29: 0.013780435 | FU29: 0.094 | FV29: 0.121 | FW29: 0.0691 | FX29: 0.16692379 | FY29: 0.67857514 | FZ29: 0.01245031 | GA29: 0.076 | GB29: 0.1216 | GC29: 0.0573 | GD29: 0.1575517 | GE29: 0.70327539 | GF29: 0.012300083 | GG29: 0.059 | GH29: 0.1215 | GI29: 0.0556 | GJ29: 0.13560412 | GK29: 0.6915734 | GL29: 0.01432672 | GM29: 0.049 | GN29: 0.1227 | GO29: 0.0791 | GP29: 0.17242398 | GQ29: 0.64514859 | GR29: 0.013204016 | GS29: 0.046 | GT29: 0.1241 | GU29: 0.0918 | GV29: 0.12546095 | GW29: 0.53758329 | GX29: 0.012717365 | GY29: 0.049 | GZ29: 0.1267 | HA29: 0.0906 | HB29: 0.11661714 | HC29: 0.60707187 | HD29: 0.014638632 | HE29: 0.054 | HF29: 0.1309 | HG29: 0.0919 | HH29: 0.11167829 | HI29: 0.60616973 | HJ29: 0.039931586 | HK29: 0.055 | HL29: 0.1331 | HM29: 0.0788 | HN29: 0.12202066 | HO29: 0.57862261 | HP29: 0.019756848 | HQ29: 0.06 | HR29: 0.1398 | HS29: 0.0678 | HT29: 0.11928044 | HU29: 0.53984163 | HV29: 0.023205014 | HW29: 0.056 | HX29: 0.1463 | HY29: 0.0663 | HZ29: 0.12183963 | IA29: 0.52390847 | IB29: 0.025904096 | IC29: 0.049 | ID29: 0.1628 | IE29: 0.057 | IF29: 0.12136974 | IG29: 0.48169747 | IH29: 0.032984281 | II29: 0.046 | IJ29: 0.1685 | IK29: 0.0622 | IL29: 0.12272441 | IM29: 0.49134622 | IN29: 0.026855031 | IO29: 0.04 | IP29: 0.1691 | IQ29: 0.0356 | IR29: 0.14305612 | IS29: 0.49277104 | IT29: 0.029744682 | IU29: 0.047 | IV29: 0.1689 | IW29: 0.0299 | IX29: 0.14735476 | IY29: 0.48993744 | IZ29: 0.03105488 | JA29: 0.049 | JB29: 0.1577 | JC29: 0.0362 | JD29: 0.14241088 | JE29: 0.54706162 | JF29: 0.034287724 | JG29: 0.05 | JH29: 0.1528 | JI29: 0.0382 | JJ29: 0.14348248 | JK29: 0.54920348 | JL29: 0.026181963 | JM29: 0.049 | JN29: 0.1507 | JO29: 0.0458 | JP29: 0.13740591 | JQ29: 0.54103266 | JR29: 0.026211319 | JS29: 0.05 | JT29: 0.1481 | JU29: 0.0449 | JV29: 0.12534116 | JW29: 0.53547498 | JX29: 0.027285019
A30: 26 | B30: Habib A.G.Zurich | C30: 0.052 | D30: 0.1691 | E30: 0.0627 | F30: 0.023103505 | G30: 0.44058163 | H30: 0.024753333 | I30: 0.06 | J30: 0.1636 | K30: 0.0739 | L30: 0.021924403 | M30: 0.44212329 | N30: 0.024815461 | O30: 0.05 | P30: 0.1599 | Q30: 0.0602 | R30: 0.014134244 | S30: 0.35617134 | T30: 0.034545152 | U30: 0.057 | V30: 0.1546 | W30: 0.0631 | X30: 0.010848639 | Y30: 0.48151849 | Z30: 0.022347068 | AA30: 0.056 | AB30: 0.1606 | AC30: 0.0703 | AD30: 0.010728 | AE30: 0.4813766 | AF30: 0.021257124 | AG30: 0.061 | AH30: 0.1682 | AI30: 0.0597 | AJ30: 0.013843969 | AK30: 0.48426258 | AL30: 0.020510129 | AM30: 0.05 | AN30: 0.183 | AO30: 0.0801 | AP30: 0.013687637 | AQ30: 0.45238338 | AR30: 0.024770381 | AS30: 0.038 | AT30: 0.1787 | AU30: 0.0645 | AV30: 0.014151123 | AW30: 0.44138836 | AX30: 0.024201812 | AY30: 0.038 | AZ30: 0.1818 | BA30: 0.058 | BB30: 0.014139323 | BC30: 0.42521716 | BD30: 0.025909631 | BE30: 0.044 | BF30: 0.1386 | BG30: 0.0634 | BH30: 0.020338131 | BI30: 0.40792408 | BJ30: 0.02767109 | BK30: 0.042 | BL30: 0.1366 | BM30: 0.0635 | BN30: 0.019429683 | BO30: 0.43529123 | BP30: 0.024925856 | BQ30: 0.054 | BR30: 0.1361 | BS30: 0.1028 | BT30: 0.028864029 | BU30: 0.53262783 | BV30: 0.016315735 | BW30: 0.033 | BX30: 0.1366 | BY30: 0.0921 | BZ30: 0.081204843 | CA30: 0.55070258 | CB30: 0.014509637 | CC30: 0.032 | CD30: 0.1369 | CE30: 0.0706 | CF30: 0.081244868 | CG30: 0.55505263 | CH30: 0.013973875 | CI30: 0.038 | CJ30: 0.1364 | CK30: 0.045 | CL30: 0.081257059 | CM30: 0.54067659 | CN30: 0.014279978 | CO30: 0.052 | CP30: 0.1349 | CQ30: 0.0418 | CR30: 0.074349581 | CS30: 0.65291812 | CT30: 0.0094876262 | CU30: 0.061 | CV30: 0.1322 | CW30: 0.0428 | CX30: 0.070911068 | CY30: 0.66145652 | CZ30: 0.0094021584 | DA30: 0.053 | DB30: 0.1266 | DC30: 0.057 | DD30: 0.073640584 | DE30: 0.62947692 | DF30: 0.017918921 | DG30: 0.056 | DH30: 0.1251 | DI30: 0.0571 | DJ30: 0.069333923 | DK30: 0.63604094 | DL30: 0.011235503 | DM30: 0.048 | DN30: 0.1251 | DO30: 0.0435 | DP30: 0.086757426 | DQ30: 0.61830066 | DR30: 0.0091014788 | DS30: 0.06 | DT30: 0.1247 | DU30: 0.057 | DV30: 0.087777576 | DW30: 0.63713437 | DX30: 0.0079203473 | DY30: 0.05 | DZ30: 0.1247 | EA30: 0.0383 | EB30: 0.082794914 | EC30: 0.6815844 | ED30: 0 | EE30: 0.051 | EF30: 0.1224 | EG30: 0.0582 | EH30: 0.084422085 | EI30: 0.64281307 | EJ30: 0.010355099 | EK30: 0.046 | EL30: 0.1209 | EM30: 0.0584 | EN30: 0.087650028 | EO30: 0.71956392 | EP30: 0.0065148175 | EQ30: -0.041 | ER30: 0.1189 | ES30: 0.0459 | ET30: 0.087486912 | EU30: 0.68383699 | EV30: 0.0069148449 | EW30: -0.036 | EX30: 0.1175 | EY30: 0.042 | EZ30: 0.083443012 | FA30: 0.65663528 | FB30: 0.0088388731 | FC30: -0.003 | FD30: 0.1202 | FE30: 0.0562 | FF30: 0.093285897 | FG30: 0.5884858 | FH30: 0.012108194 | FI30: 0.024 | FJ30: 0.1205 | FK30: 0.059 | FL30: 0.092386133 | FM30: 0.65413702 | FN30: 0.0089164769 | FO30: 0.103 | FP30: 0.1202 | FQ30: 0.0632 | FR30: 0.095517425 | FS30: 0.62540293 | FT30: 0.0099464298 | FU30: 0.094 | FV30: 0.121 | FW30: 0.0691 | FX30: 0.090071137 | FY30: 0.61603054 | FZ30: 0.010331593 | GA30: 0.076 | GB30: 0.1216 | GC30: 0.0573 | GD30: 0.088176941 | GE30: 0.57449947 | GF30: 0.015560833 | GG30: 0.059 | GH30: 0.1215 | GI30: 0.0556 | GJ30: 0.083945502 | GK30: 0.66614533 | GL30: 0.0078846415 | GM30: 0.049 | GN30: 0.1227 | GO30: 0.0791 | GP30: 0.08052627 | GQ30: 0.65108253 | GR30: 0.0085387643 | GS30: 0.046 | GT30: 0.1241 | GU30: 0.0918 | GV30: 0.080991669 | GW30: 0.64297829 | GX30: 0.0089187397 | GY30: 0.049 | GZ30: 0.1267 | HA30: 0.0906 | HB30: 0.075500972 | HC30: 0.58349008 | HD30: 0.0099548074 | HE30: 0.054 | HF30: 0.1309 | HG30: 0.0919 | HH30: 0.049476949 | HI30: 0.66616951 | HJ30: 0.01011721 | HK30: 0.055 | HL30: 0.1331 | HM30: 0.0788 | HN30: 0.052412442 | HO30: 0.63406709 | HP30: 0.011301886 | HQ30: 0.06 | HR30: 0.1398 | HS30: 0.0678 | HT30: 0.043350533 | HU30: 0.65437598 | HV30: 0.01150637 | HW30: 0.056 | HX30: 0.1463 | HY30: 0.0663 | HZ30: 0.043924678 | IA30: 0.68663225 | IB30: 0.00591882 | IC30: 0.049 | ID30: 0.1628 | IE30: 0.057 | IF30: 0.053148554 | IG30: 0.74587431 | IH30: 0.011495523 | II30: 0.046 | IJ30: 0.1685 | IK30: 0.0622 | IL30: 0.052810598 | IM30: 0.69867226 | IN30: 0.012048174 | IO30: 0.04 | IP30: 0.1691 | IQ30: 0.0356 | IR30: 0.054750467 | IS30: 0.68820922 | IT30: 0.011454264 | IU30: 0.047 | IV30: 0.1689 | IW30: 0.0299 | IX30: 0.055288491 | IY30: 0.44936677 | IZ30: 0.010802963 | JA30: 0.049 | JB30: 0.1577 | JC30: 0.0362 | JD30: 0.058433591 | JE30: 0.67469265 | JF30: 0.018258115 | JG30: 0.05 | JH30: 0.1528 | JI30: 0.0382 | JJ30: 0.062134093 | JK30: 0.59801284 | JL30: 0.015290797 | JM30: 0.049 | JN30: 0.1507 | JO30: 0.0458 | JP30: 0.066690397 | JQ30: 0.58019453 | JR30: 0.016384239 | JS30: 0.05 | JT30: 0.1481 | JU30: 0.0449 | JV30: 0.049155736 | JW30: 0.59467424 | JX30: 0.018288933
A31: 27 | B31: Habib Bank Ltd | C31: 0.052 | D31: 0.1691 | E31: 0.0627 | F31: 0.074393399 | G31: 0.30754334 | H31: 0.039048851 | I31: 0.06 | J31: 0.1636 | K31: 0.0739 | L31: 0.057082721 | M31: 0.31685676 | N31: 0.029826834 | O31: 0.05 | P31: 0.1599 | Q31: 0.0602 | R31: 0.061796932 | S31: 0.30779034 | T31: 0.036345883 | U31: 0.057 | V31: 0.1546 | W31: 0.0631 | X31: 0.087530453 | Y31: 0.30769568 | Z31: 0.029550437 | AA31: 0.056 | AB31: 0.1606 | AC31: 0.0703 | AD31: 0.080741788 | AE31: 0.35070351 | AF31: 0.027316708 | AG31: 0.061 | AH31: 0.1682 | AI31: 0.0597 | AJ31: 0.094525216 | AK31: 0.34308896 | AL31: 0.0212952 | AM31: 0.05 | AN31: 0.183 | AO31: 0.0801 | AP31: 0.087017722 | AQ31: 0.3541121 | AR31: 0.030344814 | AS31: 0.038 | AT31: 0.1787 | AU31: 0.0645 | AV31: 0.14132423 | AW31: 0.33795659 | AX31: 0.037498736 | AY31: 0.038 | AZ31: 0.1818 | BA31: 0.058 | BB31: 0.14368931 | BC31: 0.37056337 | BD31: 0.028307096 | BE31: 0.044 | BF31: 0.1386 | BG31: 0.0634 | BH31: 0.14351336 | BI31: 0.3852002 | BJ31: 0.028725561 | BK31: 0.042 | BL31: 0.1366 | BM31: 0.0635 | BN31: 0.16629252 | BO31: 0.40586748 | BP31: 0.026929806 | BQ31: 0.054 | BR31: 0.1361 | BS31: 0.1028 | BT31: 0.19028066 | BU31: 0.6233621 | BV31: 0.012947867 | BW31: 0.033 | BX31: 0.1366 | BY31: 0.0921 | BZ31: 0.20840515 | CA31: 0.58883412 | CB31: 0.0098182871 | CC31: 0.032 | CD31: 0.1369 | CE31: 0.0706 | CF31: NA | CG31: NA | CH31: NA | CI31: 0.038 | CJ31: 0.1364 | CK31: 0.045 | CL31: NA | CM31: NA | CN31: NA | CO31: 0.052 | CP31: 0.1349 | CQ31: 0.0418 | CR31: NA | CS31: NA | CT31: NA | CU31: 0.061 | CV31: 0.1322 | CW31: 0.0428 | CX31: NA | CY31: NA | CZ31: NA | DA31: 0.053 | DB31: 0.1266 | DC31: 0.057 | DD31: NA | DE31: NA | DF31: NA | DG31: 0.056 | DH31: 0.1251 | DI31: 0.0571 | DJ31: NA | DK31: NA | DL31: NA | DM31: 0.048 | DN31: 0.1251 | DO31: 0.0435 | DP31: NA | DQ31: NA | DR31: NA | DS31: 0.06 | DT31: 0.1247 | DU31: 0.057 | DV31: NA | DW31: NA | DX31: NA | DY31: 0.05 | DZ31: 0.1247 | EA31: 0.0383 | EB31: NA | EC31: NA | ED31: NA | EE31: 0.051 | EF31: 0.1224 | EG31: 0.0582 | EH31: NA | EI31: NA | EJ31: NA | EK31: 0.046 | EL31: 0.1209 | EM31: 0.0584 | EN31: NA | EO31: NA | EP31: NA | EQ31: -0.041 | ER31: 0.1189 | ES31: 0.0459 | ET31: NA | EU31: NA | EV31: NA | EW31: -0.036 | EX31: 0.1175 | EY31: 0.042 | EZ31: NA | FA31: NA | FB31: NA | FC31: -0.003 | FD31: 0.1202 | FE31: 0.0562 | FF31: NA | FG31: NA | FH31: NA | FI31: 0.024 | FJ31: 0.1205 | FK31: 0.059 | FL31: NA | FM31: NA | FN31: NA | FO31: 0.103 | FP31: 0.1202 | FQ31: 0.0632 | FR31: NA | FS31: NA | FT31: NA | FU31: 0.094 | FV31: 0.121 | FW31: 0.0691 | FX31: NA | FY31: NA | FZ31: NA | GA31: 0.076 | GB31: 0.1216 | GC31: 0.0573 | GD31: NA | GE31: NA | GF31: NA | GG31: 0.059 | GH31: 0.1215 | GI31: 0.0556 | GJ31: NA | GK31: NA | GL31: NA | GM31: 0.049 | GN31: 0.1227 | GO31: 0.0791 | GP31: NA | GQ31: NA | GR31: NA | GS31: 0.046 | GT31: 0.1241 | GU31: 0.0918 | GV31: NA | GW31: NA | GX31: NA | GY31: 0.049 | GZ31: 0.1267 | HA31: 0.0906 | HB31: NA | HC31: NA | HD31: NA | HE31: 0.054 | HF31: 0.1309 | HG31: 0.0919 | HH31: NA | HI31: NA | HJ31: NA | HK31: 0.055 | HL31: 0.1331 | HM31: 0.0788 | HN31: NA | HO31: NA | HP31: NA | HQ31: 0.06 | HR31: 0.1398 | HS31: 0.0678 | HT31: NA | HU31: NA | HV31: NA | HW31: 0.056 | HX31: 0.1463 | HY31: 0.0663 | HZ31: NA | IA31: NA | IB31: NA | IC31: 0.049 | ID31: 0.1628 | IE31: 0.057 | IF31: NA | IG31: NA | IH31: NA | II31: 0.046 | IJ31: 0.1685 | IK31: 0.0622 | IL31: NA | IM31: NA | IN31: NA | IO31: 0.04 | IP31: 0.1691 | IQ31: 0.0356 | IR31: NA | IS31: NA | IT31: NA | IU31: 0.047 | IV31: 0.1689 | IW31: 0.0299 | IX31: NA | IY31: NA | IZ31: NA | JA31: 0.049 | JB31: 0.1577 | JC31: 0.0362 | JD31: NA | JE31: NA | JF31: NA | JG31: 0.05 | JH31: 0.1528 | JI31: 0.0382 | JJ31: NA | JK31: NA | JL31: NA | JM31: 0.049 | JN31: 0.1507 | JO31: 0.0458 | JP31: NA | JQ31: NA | JR31: NA | JS31: 0.05 | JT31: 0.1481 | JU31: 0.0449 | JV31: NA | JW31: NA | JX31: NA
A32: 28 | B32: Housing Finance Company of Kenya | C32: 0.052 | D32: 0.1691 | E32: 0.0627 | F32: 0.084252013 | G32: 0.5153541 | H32: 0.016411098 | I32: 0.06 | J32: 0.1636 | K32: 0.0739 | L32: 0.086113915 | M32: 0.51457593 | N32: 0.017842612 | O32: 0.05 | P32: 0.1599 | Q32: 0.0602 | R32: 0.080500573 | S32: 0.47985511 | T32: 0.016227001 | U32: 0.057 | V32: 0.1546 | W32: 0.0631 | X32: 0.067802017 | Y32: 0.53619651 | Z32: 0.014548541 | AA32: 0.056 | AB32: 0.1606 | AC32: 0.0703 | AD32: 0.06902453 | AE32: 0.51864468 | AF32: 0.015217499 | AG32: 0.061 | AH32: 0.1682 | AI32: 0.0597 | AJ32: 0.064007575 | AK32: 0.47195818 | AL32: 0.02102257 | AM32: 0.05 | AN32: 0.183 | AO32: 0.0801 | AP32: 0.06171046 | AQ32: 0.49664041 | AR32: 0.020491497 | AS32: 0.038 | AT32: 0.1787 | AU32: 0.0645 | AV32: 0.068037362 | AW32: 0.48625349 | AX32: 0.017872835 | AY32: 0.038 | AZ32: 0.1818 | BA32: 0.058 | BB32: 0.079249645 | BC32: 0.56053253 | BD32: 0.018155959 | BE32: 0.044 | BF32: 0.1386 | BG32: 0.0634 | BH32: 0.080121159 | BI32: 0.49856955 | BJ32: 0.016490711 | BK32: 0.042 | BL32: 0.1366 | BM32: 0.0635 | BN32: 0.086776954 | BO32: 0.5039836 | BP32: 0.014628049 | BQ32: 0.054 | BR32: 0.1361 | BS32: 0.1028 | BT32: 0.10886871 | BU32: 0.62594082 | BV32: 0.005570844 | BW32: 0.033 | BX32: 0.1366 | BY32: 0.0921 | BZ32: 0.11360981 | CA32: 0.65111806 | CB32: 0.0049312899 | CC32: 0.032 | CD32: 0.1369 | CE32: 0.0706 | CF32: 0.11559915 | CG32: 0.70571108 | CH32: 0.0034448144 | CI32: 0.038 | CJ32: 0.1364 | CK32: 0.045 | CL32: 0.12283142 | CM32: 0.71001496 | CN32: 0.0027839172 | CO32: 0.052 | CP32: 0.1349 | CQ32: 0.0418 | CR32: 0.12695845 | CS32: 0.75772424 | CT32: 0.0034849829 | CU32: 0.061 | CV32: 0.1322 | CW32: 0.0428 | CX32: 0.13404351 | CY32: 0.77449703 | CZ32: 0.0018888553 | DA32: 0.053 | DB32: 0.1266 | DC32: 0.057 | DD32: 0.14059412 | DE32: 0.87483395 | DF32: -0.0020280174 | DG32: 0.056 | DH32: 0.1251 | DI32: 0.0571 | DJ32: 0.19536961 | DK32: 1.0070784 | DL32: -0.0071944565 | DM32: 0.048 | DN32: 0.1251 | DO32: 0.0435 | DP32: 0.19205858 | DQ32: 0.81511469 | DR32: -0.0032796085 | DS32: 0.06 | DT32: 0.1247 | DU32: 0.057 | DV32: 0.19485712 | DW32: 0.79982729 | DX32: -0.0026766565 | DY32: 0.05 | DZ32: 0.1247 | EA32: 0.0383 | EB32: 0.19300113 | EC32: 0.76174788 | ED32: -0.00048746156 | EE32: 0.051 | EF32: 0.1224 | EG32: 0.0582 | EH32: 0.1853257 | EI32: 0.88167445 | EJ32: 0.00011374798 | EK32: 0.046 | EL32: 0.1209 | EM32: 0.0584 | EN32: 0.18171437 | EO32: 0.78188196 | EP32: 0.0011719321 | EQ32: -0.041 | ER32: 0.1189 | ES32: 0.0459 | ET32: 0.1760847 | EU32: 0.96979091 | EV32: -0.0084044563 | EW32: -0.036 | EX32: 0.1175 | EY32: 0.042 | EZ32: 0.16851169 | FA32: 1.0492549 | FB32: -0.013841662 | FC32: -0.003 | FD32: 0.1202 | FE32: 0.0562 | FF32: 0.16433821 | FG32: 1.2311707 | FH32: -0.017240349 | FI32: 0.024 | FJ32: 0.1205 | FK32: 0.059 | FL32: 0.16554116 | FM32: 0.9326756 | FN32: -0.010891214 | FO32: 0.103 | FP32: 0.1202 | FQ32: 0.0632 | FR32: 0.15109563 | FS32: 1.0436421 | FT32: -0.0099968382 | FU32: 0.094 | FV32: 0.121 | FW32: 0.0691 | FX32: 0.14644075 | FY32: 1.0572199 | FZ32: -0.0096413023 | GA32: 0.076 | GB32: 0.1216 | GC32: 0.0573 | GD32: 0.14020174 | GE32: 1.1295273 | GF32: -0.0072180566 | GG32: 0.059 | GH32: 0.1215 | GI32: 0.0556 | GJ32: 0.16554116 | GK32: 0.98994318 | GL32: -0.011042168 | GM32: 0.049 | GN32: 0.1227 | GO32: 0.0791 | GP32: 0.13377954 | GQ32: 0.92212945 | GR32: 0.0017582694 | GS32: 0.046 | GT32: 0.1241 | GU32: 0.0918 | GV32: 0.13561663 | GW32: 0.93294673 | GX32: 0.001437066 | GY32: 0.049 | GZ32: 0.1267 | HA32: 0.0906 | HB32: 0.13390726 | HC32: 0.89924964 | HD32: 0.0033229913 | HE32: 0.054 | HF32: 0.1309 | HG32: 0.0919 | HH32: 0.13547654 | HI32: 0.81346711 | HJ32: 0.0032440715 | HK32: 0.055 | HL32: 0.1331 | HM32: 0.0788 | HN32: 0.16261287 | HO32: 0.83900633 | HP32: 0.003254864 | HQ32: 0.06 | HR32: 0.1398 | HS32: 0.0678 | HT32: 0.16096236 | HU32: 0.85481302 | HV32: 0.0023346002 | HW32: 0.056 | HX32: 0.1463 | HY32: 0.0663 | HZ32: 0.16594593 | IA32: 0.85763391 | IB32: 0.0032742523 | IC32: 0.049 | ID32: 0.1628 | IE32: 0.057 | IF32: 0.16950827 | IG32: 0.81527619 | IH32: 0.0030844268 | II32: 0.046 | IJ32: 0.1685 | IK32: 0.0622 | IL32: 0.17155478 | IM32: 0.84016751 | IN32: 0.0031821331 | IO32: 0.04 | IP32: 0.1691 | IQ32: 0.0356 | IR32: 0.17101222 | IS32: 0.85403695 | IT32: 0.0066078468 | IU32: 0.047 | IV32: 0.1689 | IW32: 0.0299 | IX32: 0.17960842 | IY32: 0.83286396 | IZ32: 0.0044386446 | JA32: 0.049 | JB32: 0.1577 | JC32: 0.0362 | JD32: 0.1780701 | JE32: 0.87865145 | JF32: 0.014013382 | JG32: 0.05 | JH32: 0.1528 | JI32: 0.0382 | JJ32: 0.16884179 | JK32: 0.69659207 | JL32: 0.013765737 | JM32: 0.049 | JN32: 0.1507 | JO32: 0.0458 | JP32: 0.16871237 | JQ32: 0.69382124 | JR32: 0.014221151 | JS32: 0.05 | JT32: 0.1481 | JU32: 0.0449 | JV32: 0.16127417 | JW32: 0.69977534 | JX32: 0.01375796
A33: 29 | B33: I&M Bank | C33: 0.052 | D33: 0.1691 | E33: 0.0627 | F33: 0.0097223693 | G33: 0.31366373 | H33: 0.035050157 | I33: 0.06 | J33: 0.1636 | K33: 0.0739 | L33: 0.010325735 | M33: 0.31910777 | N33: 0.038919262 | O33: 0.05 | P33: 0.1599 | Q33: 0.0602 | R33: 0.015424784 | S33: 0.2835653 | T33: 0.045383973 | U33: 0.057 | V33: 0.1546 | W33: 0.0631 | X33: 0.01921964 | Y33: 0.29270904 | Z33: 0.047081087 | AA33: 0.056 | AB33: 0.1606 | AC33: 0.0703 | AD33: 0.017834978 | AE33: 0.31090613 | AF33: 0.039504698 | AG33: 0.061 | AH33: 0.1682 | AI33: 0.0597 | AJ33: 0.028045606 | AK33: 0.31962805 | AL33: 0.038212108 | AM33: 0.05 | AN33: 0.183 | AO33: 0.0801 | AP33: 0.038441845 | AQ33: 0.32300218 | AR33: 0.040836163 | AS33: 0.038 | AT33: 0.1787 | AU33: 0.0645 | AV33: 0.041212798 | AW33: 0.28575477 | AX33: 0.042300577 | AY33: 0.038 | AZ33: 0.1818 | BA33: 0.058 | BB33: 0.040153179 | BC33: 0.28608002 | BD33: 0.043458831 | BE33: 0.044 | BF33: 0.1386 | BG33: 0.0634 | BH33: 0.039359838 | BI33: 0.31248926 | BJ33: 0.0412095 | BK33: 0.042 | BL33: 0.1366 | BM33: 0.0635 | BN33: 0.053717809 | BO33: 0.29704746 | BP33: 0.040662514 | BQ33: 0.054 | BR33: 0.1361 | BS33: 0.1028 | BT33: 0.050218922 | BU33: 0.3851795 | BV33: 0.03193146 | BW33: 0.033 | BX33: 0.1366 | BY33: 0.0921 | BZ33: 0.05126571 | CA33: 0.36164424 | CB33: 0.031817931 | CC33: 0.032 | CD33: 0.1369 | CE33: 0.0706 | CF33: 0.054218039 | CG33: 0.34742085 | CH33: 0.028598662 | CI33: 0.038 | CJ33: 0.1364 | CK33: 0.045 | CL33: 0.11348331 | CM33: 0.3137772 | CN33: 0.031531085 | CO33: 0.052 | CP33: 0.1349 | CQ33: 0.0418 | CR33: 0.1237618 | CS33: 0.36181579 | CT33: 0.029312488 | CU33: 0.061 | CV33: 0.1322 | CW33: 0.0428 | CX33: 0.1131996 | CY33: 0.35298871 | CZ33: 0.026994912 | DA33: 0.053 | DB33: 0.1266 | DC33: 0.057 | DD33: 0.10449161 | DE33: 0.34523369 | DF33: 0.040622505 | DG33: 0.056 | DH33: 0.1251 | DI33: 0.0571 | DJ33: 0.10743215 | DK33: 0.32010917 | DL33: 0.030688194 | DM33: 0.048 | DN33: 0.1251 | DO33: 0.0435 | DP33: 0.10028027 | DQ33: 0.36182303 | DR33: 0.030290822 | DS33: 0.06 | DT33: 0.1247 | DU33: 0.057 | DV33: 0.097148121 | DW33: 0.34050497 | DX33: 0.028320181 | DY33: 0.05 | DZ33: 0.1247 | EA33: 0.0383 | EB33: 0.088804554 | EC33: 0.34373088 | ED33: 0.028816929 | EE33: 0.051 | EF33: 0.1224 | EG33: 0.0582 | EH33: 0.097779117 | EI33: 0.33577547 | EJ33: 0.036154855 | EK33: 0.046 | EL33: 0.1209 | EM33: 0.0584 | EN33: 0.099951424 | EO33: 0.3781416 | EP33: 0.023785484 | EQ33: -0.041 | ER33: 0.1189 | ES33: 0.0459 | ET33: 0.095924739 | EU33: 0.38727809 | EV33: 0.025498654 | EW33: -0.036 | EX33: 0.1175 | EY33: 0.042 | EZ33: 0.096399022 | FA33: 0.39106516 | FB33: 0.023135384 | FC33: -0.003 | FD33: 0.1202 | FE33: 0.0562 | FF33: 0.096975308 | FG33: 0.35822012 | FH33: 0.031318122 | FI33: 0.024 | FJ33: 0.1205 | FK33: 0.059 | FL33: 0.10529877 | FM33: 0.41485091 | FN33: 0.021023282 | FO33: 0.103 | FP33: 0.1202 | FQ33: 0.0632 | FR33: 0.10027437 | FS33: 0.42256364 | FT33: 0.021874368 | FU33: 0.094 | FV33: 0.121 | FW33: 0.0691 | FX33: 0.096842836 | FY33: 0.41528934 | FZ33: 0.020546656 | GA33: 0.076 | GB33: 0.1216 | GC33: 0.0573 | GD33: 0.088858436 | GE33: 0.37992031 | GF33: 0.024109616 | GG33: 0.059 | GH33: 0.1215 | GI33: 0.0556 | GJ33: 0.089580475 | GK33: 0.37295571 | GL33: 0.022987173 | GM33: 0.049 | GN33: 0.1227 | GO33: 0.0791 | GP33: 0.084035666 | GQ33: 0.38660021 | GR33: 0.024664011 | GS33: 0.046 | GT33: 0.1241 | GU33: 0.0918 | GV33: 0.081774723 | GW33: 0.37001012 | GX33: 0.024575775 | GY33: 0.049 | GZ33: 0.1267 | HA33: 0.0906 | HB33: 0.081120696 | HC33: 0.36194914 | HD33: 0.03132345 | HE33: 0.054 | HF33: 0.1309 | HG33: 0.0919 | HH33: 0.082120718 | HI33: 0.36494978 | HJ33: 0.025258482 | HK33: 0.055 | HL33: 0.1331 | HM33: 0.0788 | HN33: 0.10985983 | HO33: 0.40343079 | HP33: 0.021574931 | HQ33: 0.06 | HR33: 0.1398 | HS33: 0.0678 | HT33: 0.10089918 | HU33: 0.41060315 | HV33: 0.021413698 | HW33: 0.056 | HX33: 0.1463 | HY33: 0.0663 | HZ33: 0.094096071 | IA33: 0.40052 | IB33: 0.026946842 | IC33: 0.049 | ID33: 0.1628 | IE33: 0.057 | IF33: 0.098443758 | IG33: 0.39113812 | IH33: 0.026585401 | II33: 0.046 | IJ33: 0.1685 | IK33: 0.0622 | IL33: 0.1049327 | IM33: 0.42473398 | IN33: 0.02162336 | IO33: 0.04 | IP33: 0.1691 | IQ33: 0.0356 | IR33: 0.10767751 | IS33: 0.4195242 | IT33: 0.022643573 | IU33: 0.047 | IV33: 0.1689 | IW33: 0.0299 | IX33: 0.11131548 | IY33: 0.4096962 | IZ33: 0.027781884 | JA33: 0.049 | JB33: 0.1577 | JC33: 0.0362 | JD33: 0.10816352 | JE33: 0.40071537 | JF33: 0.028179693 | JG33: 0.05 | JH33: 0.1528 | JI33: 0.0382 | JJ33: 0.11057782 | JK33: 0.3911189 | JL33: 0.027932263 | JM33: 0.049 | JN33: 0.1507 | JO33: 0.0458 | JP33: 0.10749023 | JQ33: 0.3972168 | JR33: 0.027255745 | JS33: 0.05 | JT33: 0.1481 | JU33: 0.0449 | JV33: 0.10382901 | JW33: 0.39481787 | JX33: 0.033568448
A34: 30 | B34: Imperial Bank | C34: 0.052 | D34: 0.1691 | E34: 0.0627 | F34: 0.043688024 | G34: 0.49179173 | H34: 0.036411392 | I34: 0.06 | J34: 0.1636 | K34: 0.0739 | L34: 0.049533384 | M34: 0.49874394 | N34: 0.036661951 | O34: 0.05 | P34: 0.1599 | Q34: 0.0602 | R34: 0.056246458 | S34: 0.47643315 | T34: 0.041453316 | U34: 0.057 | V34: 0.1546 | W34: 0.0631 | X34: 0.053977997 | Y34: 0.45652427 | Z34: 0.038274393 | AA34: 0.056 | AB34: 0.1606 | AC34: 0.0703 | AD34: 0.054312088 | AE34: 0.46012141 | AF34: 0.033835786 | AG34: 0.061 | AH34: 0.1682 | AI34: 0.0597 | AJ34: NA | AK34: NA | AL34: NA | AM34: 0.05 | AN34: 0.183 | AO34: 0.0801 | AP34: NA | AQ34: NA | AR34: NA | AS34: 0.038 | AT34: 0.1787 | AU34: 0.0645 | AV34: NA | AW34: NA | AX34: NA | AY34: 0.038 | AZ34: 0.1818 | BA34: 0.058 | BB34: NA | BC34: NA | BD34: NA | BE34: 0.044 | BF34: 0.1386 | BG34: 0.0634 | BH34: NA | BI34: NA | BJ34: NA | BK34: 0.042 | BL34: 0.1366 | BM34: 0.0635 | BN34: NA | BO34: NA | BP34: NA | BQ34: 0.054 | BR34: 0.1361 | BS34: 0.1028 | BT34: NA | BU34: NA | BV34: NA | BW34: 0.033 | BX34: 0.1366 | BY34: 0.0921 | BZ34: NA | CA34: NA | CB34: NA | CC34: 0.032 | CD34: 0.1369 | CE34: 0.0706 | CF34: NA | CG34: NA | CH34: NA | CI34: 0.038 | CJ34: 0.1364 | CK34: 0.045 | CL34: NA | CM34: NA | CN34: NA | CO34: 0.052 | CP34: 0.1349 | CQ34: 0.0418 | CR34: NA | CS34: NA | CT34: NA | CU34: 0.061 | CV34: 0.1322 | CW34: 0.0428 | CX34: NA | CY34: NA | CZ34: NA | DA34: 0.053 | DB34: 0.1266 | DC34: 0.057 | DD34: NA | DE34: NA | DF34: NA | DG34: 0.056 | DH34: 0.1251 | DI34: 0.0571 | DJ34: NA | DK34: NA | DL34: NA | DM34: 0.048 | DN34: 0.1251 | DO34: 0.0435 | DP34: NA | DQ34: NA | DR34: NA | DS34: 0.06 | DT34: 0.1247 | DU34: 0.057 | DV34: NA | DW34: NA | DX34: NA | DY34: 0.05 | DZ34: 0.1247 | EA34: 0.0383 | EB34: NA | EC34: NA | ED34: NA | EE34: 0.051 | EF34: 0.1224 | EG34: 0.0582 | EH34: NA | EI34: NA | EJ34: NA | EK34: 0.046 | EL34: 0.1209 | EM34: 0.0584 | EN34: NA | EO34: NA | EP34: NA | EQ34: -0.041 | ER34: 0.1189 | ES34: 0.0459 | ET34: NA | EU34: NA | EV34: NA | EW34: -0.036 | EX34: 0.1175 | EY34: 0.042 | EZ34: NA | FA34: NA | FB34: NA | FC34: -0.003 | FD34: 0.1202 | FE34: 0.0562 | FF34: NA | FG34: NA | FH34: NA | FI34: 0.024 | FJ34: 0.1205 | FK34: 0.059 | FL34: NA | FM34: NA | FN34: NA | FO34: 0.103 | FP34: 0.1202 | FQ34: 0.0632 | FR34: NA | FS34: NA | FT34: NA | FU34: 0.094 | FV34: 0.121 | FW34: 0.0691 | FX34: NA | FY34: NA | FZ34: NA | GA34: 0.076 | GB34: 0.1216 | GC34: 0.0573 | GD34: NA | GE34: NA | GF34: NA | GG34: 0.059 | GH34: 0.1215 | GI34: 0.0556 | GJ34: NA | GK34: NA | GL34: NA | GM34: 0.049 | GN34: 0.1227 | GO34: 0.0791 | GP34: NA | GQ34: NA | GR34: NA | GS34: 0.046 | GT34: 0.1241 | GU34: 0.0918 | GV34: NA | GW34: NA | GX34: NA | GY34: 0.049 | GZ34: 0.1267 | HA34: 0.0906 | HB34: NA | HC34: NA | HD34: NA | HE34: 0.054 | HF34: 0.1309 | HG34: 0.0919 | HH34: NA | HI34: NA | HJ34: NA | HK34: 0.055 | HL34: 0.1331 | HM34: 0.0788 | HN34: NA | HO34: NA | HP34: NA | HQ34: 0.06 | HR34: 0.1398 | HS34: 0.0678 | HT34: NA | HU34: NA | HV34: NA | HW34: 0.056 | HX34: 0.1463 | HY34: 0.0663 | HZ34: NA | IA34: NA | IB34: NA | IC34: 0.049 | ID34: 0.1628 | IE34: 0.057 | IF34: NA | IG34: NA | IH34: NA | II34: 0.046 | IJ34: 0.1685 | IK34: 0.0622 | IL34: NA | IM34: NA | IN34: NA | IO34: 0.04 | IP34: 0.1691 | IQ34: 0.0356 | IR34: NA | IS34: NA | IT34: NA | IU34: 0.047 | IV34: 0.1689 | IW34: 0.0299 | IX34: NA | IY34: NA | IZ34: NA | JA34: 0.049 | JB34: 0.1577 | JC34: 0.0362 | JD34: NA | JE34: NA | JF34: NA | JG34: 0.05 | JH34: 0.1528 | JI34: 0.0382 | JJ34: NA | JK34: NA | JL34: NA | JM34: 0.049 | JN34: 0.1507 | JO34: 0.0458 | JP34: NA | JQ34: NA | JR34: NA | JS34: 0.05 | JT34: 0.1481 | JU34: 0.0449 | JV34: NA | JW34: NA | JX34: NA
A35: 31 | B35: Kingdom Bank | C35: 0.052 | D35: 0.1691 | E35: 0.0627 | F35: 0.07647263 | G35: 0.81640319 | H35: 0.010177172 | I35: 0.06 | J35: 0.1636 | K35: 0.0739 | L35: 0.0921021 | M35: 0.81643698 | N35: 0.010791202 | O35: 0.05 | P35: 0.1599 | Q35: 0.0602 | R35: 0.076591812 | S35: 0.77019429 | T35: 0.0019560602 | U35: 0.057 | V35: 0.1546 | W35: 0.0631 | X35: 0.067189424 | Y35: 0.81998582 | Z35: 0.0075966188 | AA35: 0.056 | AB35: 0.1606 | AC35: 0.0703 | AD35: 0.074246096 | AE35: 0.82002085 | AF35: 0.0062428391 | AG35: 0.061 | AH35: 0.1682 | AI35: 0.0597 | AJ35: 0.036742028 | AK35: 0.82015537 | AL35: 0.0054799744 | AM35: 0.05 | AN35: 0.183 | AO35: 0.0801 | AP35: 0.049202358 | AQ35: 0.8463158 | AR35: 0.0011864438 | AS35: 0.038 | AT35: 0.1787 | AU35: 0.0645 | AV35: 0.051026249 | AW35: 0.95681856 | AX35: 0.00060076348 | AY35: 0.038 | AZ35: 0.1818 | BA35: 0.058 | BB35: 0.055757025 | BC35: 0.96425454 | BD35: -0.0017214662 | BE35: 0.044 | BF35: 0.1386 | BG35: 0.0634 | BH35: 0.0989548 | BI35: 0.94267867 | BJ35: -0.0022270718 | BK35: 0.042 | BL35: 0.1366 | BM35: 0.0635 | BN35: 0.14673776 | BO35: 1.1378632 | BP35: -0.010299701 | BQ35: 0.054 | BR35: 0.1361 | BS35: 0.1028 | BT35: 0.13099176 | BU35: 1.438793 | BV35: -0.025950693 | BW35: 0.033 | BX35: 0.1366 | BY35: 0.0921 | BZ35: 0.12702637 | CA35: 1.5382831 | CB35: -0.027403845 | CC35: 0.032 | CD35: 0.1369 | CE35: 0.0706 | CF35: 0.12603474 | CG35: 1.6257233 | CH35: -0.031914159 | CI35: 0.038 | CJ35: 0.1364 | CK35: 0.045 | CL35: 0.11746272 | CM35: 2.1002497 | CN35: -0.034482321 | CO35: 0.052 | CP35: 0.1349 | CQ35: 0.0418 | CR35: 0.11919435 | CS35: 1.1643412 | CT35: -0.018744083 | CU35: 0.061 | CV35: 0.1322 | CW35: 0.0428 | CX35: NA | CY35: NA | CZ35: 0 | DA35: 0.053 | DB35: 0.1266 | DC35: 0.057 | DD35: NA | DE35: NA | DF35: 0 | DG35: 0.056 | DH35: 0.1251 | DI35: 0.0571 | DJ35: NA | DK35: NA | DL35: 0 | DM35: 0.048 | DN35: 0.1251 | DO35: 0.0435 | DP35: NA | DQ35: NA | DR35: NA | DS35: 0.06 | DT35: 0.1247 | DU35: 0.057 | DV35: NA | DW35: NA | DX35: NA | DY35: 0.05 | DZ35: 0.1247 | EA35: 0.0383 | EB35: NA | EC35: NA | ED35: NA | EE35: 0.051 | EF35: 0.1224 | EG35: 0.0582 | EH35: NA | EI35: NA | EJ35: NA | EK35: 0.046 | EL35: 0.1209 | EM35: 0.0584 | EN35: NA | EO35: NA | EP35: NA | EQ35: -0.041 | ER35: 0.1189 | ES35: 0.0459 | ET35: NA | EU35: NA | EV35: NA | EW35: -0.036 | EX35: 0.1175 | EY35: 0.042 | EZ35: NA | FA35: NA | FB35: NA | FC35: -0.003 | FD35: 0.1202 | FE35: 0.0562 | FF35: 0.49718795 | FG35: 0.88983783 | FH35: -0.018236852 | FI35: 0.024 | FJ35: 0.1205 | FK35: 0.059 | FL35: 0.52766743 | FM35: 0.44045335 | FN35: 0.023812 | FO35: 0.103 | FP35: 0.1202 | FQ35: 0.0632 | FR35: 0.50654142 | FS35: 0.63560126 | FT35: 0.025543574 | FU35: 0.094 | FV35: 0.121 | FW35: 0.0691 | FX35: 0.5279327 | FY35: 0.66998252 | FZ35: 0.026239025 | GA35: 0.076 | GB35: 0.1216 | GC35: 0.0573 | GD35: 0.49352454 | GE35: 0.7115768 | GF35: 0.023311941 | GG35: 0.059 | GH35: 0.1215 | GI35: 0.0556 | GJ35: NA | GK35: 0.67090325 | GL35: 0.025026366 | GM35: 0.049 | GN35: 0.1227 | GO35: 0.0791 | GP35: 0.48184445 | GQ35: 0.58291674 | GR35: 0.025485644 | GS35: 0.046 | GT35: 0.1241 | GU35: 0.0918 | GV35: 0.43397773 | GW35: 0.7567723 | GX35: 0.025039825 | GY35: 0.049 | GZ35: 0.1267 | HA35: 0.0906 | HB35: 0.35592344 | HC35: 0.074456841 | HD35: 0.028038015 | HE35: 0.054 | HF35: 0.1309 | HG35: 0.0919 | HH35: 0.31821043 | HI35: 0.6599978 | HJ35: 0.0297735 | HK35: 0.055 | HL35: 0.1331 | HM35: 0.0788 | HN35: 0.29516431 | HO35: 0.63147408 | HP35: 0.029594 | HQ35: 0.06 | HR35: 0.1398 | HS35: 0.0678 | HT35: 0.2760273 | HU35: 0.61419933 | HV35: 0.029698308 | HW35: 0.056 | HX35: 0.1463 | HY35: 0.0663 | HZ35: 0.21378268 | IA35: 0.57530346 | IB35: 0.018356859 | IC35: 0.049 | ID35: 0.1628 | IE35: 0.057 | IF35: 0.21978496 | IG35: 0.55914713 | IH35: 0.036678506 | II35: 0.046 | IJ35: 0.1685 | IK35: 0.0622 | IL35: 0.21965279 | IM35: 0.46911262 | IN35: 0.023966177 | IO35: 0.04 | IP35: 0.1691 | IQ35: 0.0356 | IR35: 0.2000475 | IS35: 0.54128788 | IT35: 0.021148935 | IU35: 0.047 | IV35: 0.1689 | IW35: 0.0299 | IX35: 0.15138027 | IY35: 0.51674184 | IZ35: 0.01409374 | JA35: 0.049 | JB35: 0.1577 | JC35: 0.0362 | JD35: 0.15547757 | JE35: 0.58953287 | JF35: 0.013377897 | JG35: 0.05 | JH35: 0.1528 | JI35: 0.0382 | JJ35: 0.14535327 | JK35: 0.61871538 | JL35: 0.014516546 | JM35: 0.049 | JN35: 0.1507 | JO35: 0.0458 | JP35: 0.13225877 | JQ35: 0.60029655 | JR35: 0.015655149 | JS35: 0.05 | JT35: 0.1481 | JU35: 0.0449 | JV35: 0.11388509 | JW35: 0.63631058 | JX35: 0.018941605
A36: 32 | B36: Kenya Commercial Bank | C36: 0.052 | D36: 0.1691 | E36: 0.0627 | F36: 0.072991182 | G36: 0.46601795 | H36: 0.040984821 | I36: 0.06 | J36: 0.1636 | K36: 0.0739 | L36: 0.062702979 | M36: 0.46494319 | N36: 0.044045592 | O36: 0.05 | P36: 0.1599 | Q36: 0.0602 | R36: 0.044388612 | S36: 0.46438526 | T36: 0.045350248 | U36: 0.057 | V36: 0.1546 | W36: 0.0631 | X36: 0.053449229 | Y36: 0.23056687 | Z36: 0.043279501 | AA36: 0.056 | AB36: 0.1606 | AC36: 0.0703 | AD36: 0.054589361 | AE36: 0.4588254 | AF36: 0.04096774 | AG36: 0.061 | AH36: 0.1682 | AI36: 0.0597 | AJ36: 0.048346967 | AK36: 0.46528379 | AL36: 0.038604786 | AM36: 0.05 | AN36: 0.183 | AO36: 0.0801 | AP36: 0.050139052 | AQ36: 0.4734089 | AR36: 0.039065236 | AS36: 0.038 | AT36: 0.1787 | AU36: 0.0645 | AV36: 0.067257671 | AW36: 0.45152842 | AX36: 0.035899531 | AY36: 0.038 | AZ36: 0.1818 | BA36: 0.058 | BB36: 0.070648366 | BC36: 0.44320238 | BD36: 0.041779828 | BE36: 0.044 | BF36: 0.1386 | BG36: 0.0634 | BH36: 0.063231032 | BI36: 0.43462857 | BJ36: 0.042745834 | BK36: 0.042 | BL36: 0.1366 | BM36: 0.0635 | BN36: 0.063814148 | BO36: 0.44588005 | BP36: 0.040676558 | BQ36: 0.054 | BR36: 0.1361 | BS36: 0.1028 | BT36: 0.065376755 | BU36: 0.47098041 | BV36: 0.035022112 | BW36: 0.033 | BX36: 0.1366 | BY36: 0.0921 | BZ36: 0.066224978 | CA36: 0.47051865 | CB36: 0.036890903 | CC36: 0.032 | CD36: 0.1369 | CE36: 0.0706 | CF36: 0.069315205 | CG36: 0.47279791 | CH36: 0.036587393 | CI36: 0.038 | CJ36: 0.1364 | CK36: 0.045 | CL36: 0.07045843 | CM36: 0.4680353 | CN36: 0.036279132 | CO36: 0.052 | CP36: 0.1349 | CQ36: 0.0418 | CR36: 0.086035324 | CS36: 0.45933332 | CT36: 0.038614495 | CU36: 0.061 | CV36: 0.1322 | CW36: 0.0428 | CX36: 0.073700106 | CY36: 0.45365337 | CZ36: 0.03912556 | DA36: 0.053 | DB36: 0.1266 | DC36: 0.057 | DD36: 0.065437278 | DE36: 0.45106036 | DF36: 0.055345406 | DG36: 0.056 | DH36: 0.1251 | DI36: 0.0571 | DJ36: 0.059128415 | DK36: 0.45091327 | DL36: 0.038069642 | DM36: 0.048 | DN36: 0.1251 | DO36: 0.0435 | DP36: 0.069381456 | DQ36: 0.44768188 | DR36: 0.035747886 | DS36: 0.06 | DT36: 0.1247 | DU36: 0.057 | DV36: 0.067741339 | DW36: 0.42652535 | DX36: 0.03707713 | DY36: 0.05 | DZ36: 0.1247 | EA36: 0.0383 | EB36: 0.072265157 | EC36: 0.41834285 | ED36: 0.037106906 | EE36: 0.051 | EF36: 0.1224 | EG36: 0.0582 | EH36: 0.06431487 | EI36: 0.42120262 | EJ36: 0.035039306 | EK36: 0.046 | EL36: 0.1209 | EM36: 0.0584 | EN36: 0.066556422 | EO36: 0.4277105 | EP36: 0.031126844 | EQ36: -0.041 | ER36: 0.1189 | ES36: 0.0459 | ET36: 0.087708857 | EU36: 0.39689387 | EV36: 0.020065532 | EW36: -0.036 | EX36: 0.1175 | EY36: 0.042 | EZ36: 0.10718892 | FA36: 0.38535588 | FB36: 0.018584693 | FC36: -0.003 | FD36: 0.1202 | FE36: 0.0562 | FF36: 0.1079551 | FG36: 0.38049187 | FH36: 0.025956205 | FI36: 0.024 | FJ36: 0.1205 | FK36: 0.059 | FL36: 0.10834537 | FM36: 0.41709678 | FN36: 0.029864257 | FO36: 0.103 | FP36: 0.1202 | FQ36: 0.0632 | FR36: 0.10399692 | FS36: 0.3796781 | FT36: 0.034773267 | FU36: 0.094 | FV36: 0.121 | FW36: 0.0691 | FX36: 0.10347359 | FY36: 0.37658601 | FZ36: 0.036568476 | GA36: 0.076 | GB36: 0.1216 | GC36: 0.0573 | GD36: 0.1376713 | GE36: 0.38884011 | GF36: 0.036517637 | GG36: 0.059 | GH36: 0.1215 | GI36: 0.0556 | GJ36: 0.14084207 | GK36: 0.37800377 | GL36: 0.039267153 | GM36: 0.049 | GN36: 0.1227 | GO36: 0.0791 | GP36: 0.18928103 | GQ36: 0.38952159 | GR36: 0.038541582 | GS36: 0.046 | GT36: 0.1241 | GU36: 0.0918 | GV36: 0.16316885 | GW36: 0.37543856 | GX36: 0.039700532 | GY36: 0.049 | GZ36: 0.1267 | HA36: 0.0906 | HB36: 0.16169565 | HC36: 0.38036584 | HD36: 0.038644036 | HE36: 0.054 | HF36: 0.1309 | HG36: 0.0919 | HH36: 0.16228095 | HI36: 0.43933453 | HJ36: 0.026230881 | HK36: 0.055 | HL36: 0.1331 | HM36: 0.0788 | HN36: 0.15988797 | HO36: 0.39693791 | HP36: 0.025885155 | HQ36: 0.06 | HR36: 0.1398 | HS36: 0.0678 | HT36: 0.1528739 | HU36: 0.38700892 | HV36: 0.026890516 | HW36: 0.056 | HX36: 0.1463 | HY36: 0.0663 | HZ36: 0.16542348 | IA36: 0.40555621 | IB36: 0.021203968 | IC36: 0.049 | ID36: 0.1628 | IE36: 0.057 | IF36: 0.16912803 | IG36: 0.37140356 | IH36: 0.032454681 | II36: 0.046 | IJ36: 0.1685 | IK36: 0.0622 | IL36: 0.16891404 | IM36: 0.38608663 | IN36: 0.031187136 | IO36: 0.04 | IP36: 0.1691 | IQ36: 0.0356 | IR36: 0.16450602 | IS36: 0.38742953 | IT36: 0.03078363 | IU36: 0.047 | IV36: 0.1689 | IW36: 0.0299 | IX36: 0.16983738 | IY36: 0.36938963 | IZ36: 0.033316346 | JA36: 0.049 | JB36: 0.1577 | JC36: 0.0362 | JD36: 0.16917154 | JE36: 0.40513553 | JF36: 0.033959046 | JG36: 0.05 | JH36: 0.1528 | JI36: 0.0382 | JJ36: 0.17228397 | JK36: 0.40232138 | JL36: 0.034802003 | JM36: 0.049 | JN36: 0.1507 | JO36: 0.0458 | JP36: 0.16370131 | JQ36: 0.39742079 | JR36: 0.033599159 | JS36: 0.05 | JT36: 0.1481 | JU36: 0.0449 | JV36: 0.15185474 | JW36: 0.34812804 | JX36: 0.034945639
A37: 33 | B37: Sidian Bank | C37: 0.052 | D37: 0.1691 | E37: 0.0627 | F37: 0.065559752 | G37: 0.56225957 | H37: 0.035491009 | I37: 0.06 | J37: 0.1636 | K37: 0.0739 | L37: 0.070845751 | M37: 0.59711674 | N37: 0.0320034 | O37: 0.05 | P37: 0.1599 | Q37: 0.0602 | R37: 0.062508208 | S37: 0.59082458 | T37: 0.035453667 | U37: 0.057 | V37: 0.1546 | W37: 0.0631 | X37: 0.095322513 | Y37: 0.61989254 | Z37: 0.031938105 | AA37: 0.056 | AB37: 0.1606 | AC37: 0.0703 | AD37: 0.10533819 | AE37: 0.62044767 | AF37: 0.027716216 | AG37: 0.061 | AH37: 0.1682 | AI37: 0.0597 | AJ37: 0.10662819 | AK37: 0.66641129 | AL37: 0.022277468 | AM37: 0.05 | AN37: 0.183 | AO37: 0.0801 | AP37: 0.10495355 | AQ37: 0.67945661 | AR37: 0.021333129 | AS37: 0.038 | AT37: 0.1787 | AU37: 0.0645 | AV37: 0.11328695 | AW37: 0.67028422 | AX37: 0.021175805 | AY37: 0.038 | AZ37: 0.1818 | BA37: 0.058 | BB37: 0.13252099 | BC37: 0.71408159 | BD37: 0.016079072 | BE37: 0.044 | BF37: 0.1386 | BG37: 0.0634 | BH37: 0.1315468 | BI37: 0.72423221 | BJ37: 0.014479982 | BK37: 0.042 | BL37: 0.1366 | BM37: 0.0635 | BN37: 0.13662059 | BO37: 0.85085452 | BP37: 0.0014030294 | BQ37: 0.054 | BR37: 0.1361 | BS37: 0.1028 | BT37: 0.13487083 | BU37: 0.98869841 | BV37: -0.010598294 | BW37: 0.033 | BX37: 0.1366 | BY37: 0.0921 | BZ37: 0.15395712 | CA37: 0.99302331 | CB37: -0.012261117 | CC37: 0.032 | CD37: 0.1369 | CE37: 0.0706 | CF37: 0.13837496 | CG37: 1.0365291 | CH37: -0.018629053 | CI37: 0.038 | CJ37: 0.1364 | CK37: 0.045 | CL37: 0.17090685 | CM37: 1.0990883 | CN37: -0.020997455 | CO37: 0.052 | CP37: 0.1349 | CQ37: 0.0418 | CR37: 0.17229052 | CS37: 1.078432 | CT37: -0.016215664 | CU37: 0.061 | CV37: 0.1322 | CW37: 0.0428 | CX37: 0.18186693 | CY37: 1.0126455 | CZ37: -0.012438846 | DA37: 0.053 | DB37: 0.1266 | DC37: 0.057 | DD37: 0.17031494 | DE37: 0.97680918 | DF37: -0.015267508 | DG37: 0.056 | DH37: 0.1251 | DI37: 0.0571 | DJ37: 0.1690995 | DK37: 0.89619215 | DL37: -0.017718523 | DM37: 0.048 | DN37: 0.1251 | DO37: 0.0435 | DP37: 0.1564741 | DQ37: 0.83738021 | DR37: 0.0036506732 | DS37: 0.06 | DT37: 0.1247 | DU37: 0.057 | DV37: 0.15781537 | DW37: 0.83117664 | DX37: 0.0026795013 | DY37: 0.05 | DZ37: 0.1247 | EA37: 0.0383 | EB37: 0.16100736 | EC37: 0.79743775 | ED37: 0.0036239797 | EE37: 0.051 | EF37: 0.1224 | EG37: 0.0582 | EH37: 0.16446918 | EI37: 0.79947887 | EJ37: 0.0034535962 | EK37: 0.046 | EL37: 0.1209 | EM37: 0.0584 | EN37: 0.15934237 | EO37: 0.88200064 | EP37: -0.0023569638 | EQ37: -0.041 | ER37: 0.1189 | ES37: 0.0459 | ET37: 0.14122558 | EU37: 0.9828715 | EV37: -0.0067125573 | EW37: -0.036 | EX37: 0.1175 | EY37: 0.042 | EZ37: 0.10263877 | FA37: 0.60018554 | FB37: 0.00084450926 | FC37: -0.003 | FD37: 0.1202 | FE37: 0.0562 | FF37: 0.060405819 | FG37: 0.86774803 | FH37: 0.0020817931 | FI37: 0.024 | FJ37: 0.1205 | FK37: 0.059 | FL37: 0.093231881 | FM37: 0.73261912 | FN37: 0.012254447 | FO37: 0.103 | FP37: 0.1202 | FQ37: 0.0632 | FR37: 0.093832309 | FS37: 0.69257827 | FT37: 0.01466031 | FU37: 0.094 | FV37: 0.121 | FW37: 0.0691 | FX37: 0.092326962 | FY37: 0.68308305 | FZ37: 0.012611903 | GA37: 0.076 | GB37: 0.1216 | GC37: 0.0573 | GD37: 0.09985811 | GE37: 0.62408578 | GF37: 0.012965226 | GG37: 0.059 | GH37: 0.1215 | GI37: 0.0556 | GJ37: 0.098042538 | GK37: 0.69134272 | GL37: 0.0097380663 | GM37: 0.049 | GN37: 0.1227 | GO37: 0.0791 | GP37: 0.10245238 | GQ37: 0.68752798 | GR37: 0.010679997 | GS37: 0.046 | GT37: 0.1241 | GU37: 0.0918 | GV37: 0.11008529 | GW37: 0.6911929 | GX37: 0.011056975 | GY37: 0.049 | GZ37: 0.1267 | HA37: 0.0906 | HB37: 0.097289718 | HC37: 0.64999692 | HD37: 0.0093437916 | HE37: 0.054 | HF37: 0.1309 | HG37: 0.0919 | HH37: 0.10761527 | HI37: 0.70645905 | HJ37: 0.0094695638 | HK37: 0.055 | HL37: 0.1331 | HM37: 0.0788 | HN37: 0.11422016 | HO37: 0.7188609 | HP37: 0.0083827118 | HQ37: 0.06 | HR37: 0.1398 | HS37: 0.0678 | HT37: 0.12688396 | HU37: 0.72800089 | HV37: 0.0064317522 | HW37: 0.056 | HX37: 0.1463 | HY37: 0.0663 | HZ37: 0.14512885 | IA37: 0.68748608 | IB37: -0.010031072 | IC37: 0.049 | ID37: 0.1628 | IE37: 0.057 | IF37: 0.15344488 | IG37: 0.65441853 | IH37: 0.012131728 | II37: 0.046 | IJ37: 0.1685 | IK37: 0.0622 | IL37: 0.16503019 | IM37: 0.72274113 | IN37: 0.00765605 | IO37: 0.04 | IP37: 0.1691 | IQ37: 0.0356 | IR37: 0.17284694 | IS37: 0.74011005 | IT37: 0.0052988589 | IU37: 0.047 | IV37: 0.1689 | IW37: 0.0299 | IX37: 0.21151418 | IY37: 0.61905325 | IZ37: 0.0052181041 | JA37: 0.049 | JB37: 0.1577 | JC37: 0.0362 | JD37: 0.21968266 | JE37: 0.45456481 | JF37: 0.032827885 | JG37: 0.05 | JH37: 0.1528 | JI37: 0.0382 | JJ37: 0.19922141 | JK37: 0.46076594 | JL37: 0.027675934 | JM37: 0.049 | JN37: 0.1507 | JO37: 0.0458 | JP37: 0.21688299 | JQ37: 0.45705962 | JR37: 0.023846431 | JS37: 0.05 | JT37: 0.1481 | JU37: 0.0449 | JV37: 0.19598837 | JW37: 0.43388537 | JX37: 0.0228228
A38: 34 | B38: Middle East Bank | C38: 0.052 | D38: 0.1691 | E38: 0.0627 | F38: 0.1366047 | G38: 1.0425937 | H38: -0.0035261679 | I38: 0.06 | J38: 0.1636 | K38: 0.0739 | L38: 0.15919139 | M38: 0.69119408 | N38: 0.0064415167 | O38: 0.05 | P38: 0.1599 | Q38: 0.0602 | R38: 0.22448253 | S38: 0.71405112 | T38: 0.011728705 | U38: 0.057 | V38: 0.1546 | W38: 0.0631 | X38: 0.21965933 | Y38: 1.4464432 | Z38: -0.014745299 | AA38: 0.056 | AB38: 0.1606 | AC38: 0.0703 | AD38: 0.21063109 | AE38: 1.3035441 | AF38: -0.011570695 | AG38: 0.061 | AH38: 0.1682 | AI38: 0.0597 | AJ38: 0.19510981 | AK38: 1.076021 | AL38: -0.0067958305 | AM38: 0.05 | AN38: 0.183 | AO38: 0.0801 | AP38: 0.20994245 | AQ38: 0.76976113 | AR38: 0.005998715 | AS38: 0.038 | AT38: 0.1787 | AU38: 0.0645 | AV38: 0.20801827 | AW38: 1.2216038 | AX38: -0.0078309705 | AY38: 0.038 | AZ38: 0.1818 | BA38: 0.058 | BB38: 0.20966344 | BC38: 1.1137261 | BD38: -0.0073899798 | BE38: 0.044 | BF38: 0.1386 | BG38: 0.0634 | BH38: 0.18779571 | BI38: 1.1188609 | BJ38: -0.0079385787 | BK38: 0.042 | BL38: 0.1366 | BM38: 0.0635 | BN38: 0.20393692 | BO38: 1.1081485 | BP38: -0.01215004 | BQ38: 0.054 | BR38: 0.1361 | BS38: 0.1028 | BT38: 0.20488483 | BU38: 0.71877466 | BV38: 0.016600764 | BW38: 0.033 | BX38: 0.1366 | BY38: 0.0921 | BZ38: 0.20991574 | CA38: 0.86538132 | CB38: -0.005245746 | CC38: 0.032 | CD38: 0.1369 | CE38: 0.0706 | CF38: 0.25419222 | CG38: 1.08282 | CH38: -0.011266447 | CI38: 0.038 | CJ38: 0.1364 | CK38: 0.045 | CL38: 0.29825095 | CM38: 1.0492989 | CN38: -0.0048651039 | CO38: 0.052 | CP38: 0.1349 | CQ38: 0.0418 | CR38: 0.31716556 | CS38: 2.0824429 | CT38: -0.038473109 | CU38: 0.061 | CV38: 0.1322 | CW38: 0.0428 | CX38: 0.30555858 | CY38: 1.371684 | CZ38: -0.018999623 | DA38: 0.053 | DB38: 0.1266 | DC38: 0.057 | DD38: 0.30363962 | DE38: 1.4653489 | DF38: -0.025631068 | DG38: 0.056 | DH38: 0.1251 | DI38: 0.0571 | DJ38: 0.2766565 | DK38: 1.0161558 | DL38: 0.00049819212 | DM38: 0.048 | DN38: 0.1251 | DO38: 0.0435 | DP38: 0.26096958 | DQ38: 0.60400853 | DR38: 0.026806812 | DS38: 0.06 | DT38: 0.1247 | DU38: 0.057 | DV38: 0.20647182 | DW38: 0.60087091 | DX38: 0.022643957 | DY38: 0.05 | DZ38: 0.1247 | EA38: 0.0383 | EB38: 0.20115015 | EC38: 0.67614391 | ED38: 0.015229346 | EE38: 0.051 | EF38: 0.1224 | EG38: 0.0582 | EH38: 0.12078077 | EI38: 0.68853505 | EJ38: 0.00052273976 | EK38: 0.046 | EL38: 0.1209 | EM38: 0.0584 | EN38: 0.10729747 | EO38: 0.66975356 | EP38: 0.012748963 | EQ38: -0.041 | ER38: 0.1189 | ES38: 0.0459 | ET38: 0.097018885 | EU38: 0.72675956 | EV38: 0.0076263662 | EW38: -0.036 | EX38: 0.1175 | EY38: 0.042 | EZ38: 0.093352956 | FA38: 0.71989714 | FB38: 0.0076418502 | FC38: -0.003 | FD38: 0.1202 | FE38: 0.0562 | FF38: 0.091589134 | FG38: 0.72238172 | FH38: 0.012909254 | FI38: 0.024 | FJ38: 0.1205 | FK38: 0.059 | FL38: 0.085910848 | FM38: 0.73740449 | FN38: 0.011173214 | FO38: 0.103 | FP38: 0.1202 | FQ38: 0.0632 | FR38: 0.083360402 | FS38: 0.71721545 | FT38: 0.010307548 | FU38: 0.094 | FV38: 0.121 | FW38: 0.0691 | FX38: 0.082971616 | FY38: 0.72285655 | FZ38: 0.010045926 | GA38: 0.076 | GB38: 0.1216 | GC38: 0.0573 | GD38: 0.076892256 | GE38: 0.72873067 | GF38: 0.011100271 | GG38: 0.059 | GH38: 0.1215 | GI38: 0.0556 | GJ38: 0.059441445 | GK38: 0.64497905 | GL38: 0.013825312 | GM38: 0.049 | GN38: 0.1227 | GO38: 0.0791 | GP38: 0.059688264 | GQ38: 0.65786056 | GR38: 0.014776883 | GS38: 0.046 | GT38: 0.1241 | GU38: 0.0918 | GV38: 0.056528189 | GW38: 0.72103091 | GX38: 0.016170776 | GY38: 0.049 | GZ38: 0.1267 | HA38: 0.0906 | HB38: 0.058365294 | HC38: 0.49259147 | HD38: 0.033402152 | HE38: 0.054 | HF38: 0.1309 | HG38: 0.0919 | HH38: 0.059681996 | HI38: 0.56029176 | HJ38: 0.024051599 | HK38: 0.055 | HL38: 0.1331 | HM38: 0.0788 | HN38: 0.051083498 | HO38: 0.55632132 | HP38: 0.022802525 | HQ38: 0.06 | HR38: 0.1398 | HS38: 0.0678 | HT38: 0.064418656 | HU38: 0.5533549 | HV38: 0.022187332 | HW38: 0.056 | HX38: 0.1463 | HY38: 0.0663 | HZ38: 0.16154836 | IA38: 0.57663834 | IB38: 0.022344452 | IC38: 0.049 | ID38: 0.1628 | IE38: 0.057 | IF38: 0.17265646 | IG38: 0.32457455 | IH38: 0.012770303 | II38: 0.046 | IJ38: 0.1685 | IK38: 0.0622 | IL38: 0.17624757 | IM38: 0.67021612 | IN38: 0.01320738 | IO38: 0.04 | IP38: 0.1691 | IQ38: 0.0356 | IR38: 0.17976316 | IS38: 0.68698715 | IT38: 0.012009305 | IU38: 0.047 | IV38: 0.1689 | IW38: 0.0299 | IX38: 0.26598026 | IY38: 0.59125109 | IZ38: 0.012293896 | JA38: 0.049 | JB38: 0.1577 | JC38: 0.0362 | JD38: 0.2804061 | JE38: 0.8978737 | JF38: 0.0073205226 | JG38: 0.05 | JH38: 0.1528 | JI38: 0.0382 | JJ38: 0.28453321 | JK38: 0.80224608 | JL38: 0.012111939 | JM38: 0.049 | JN38: 0.1507 | JO38: 0.0458 | JP38: 0.25615247 | JQ38: 0.83105965 | JR38: 0.0083741582 | JS38: 0.05 | JT38: 0.1481 | JU38: 0.0449 | JV38: 0.22219076 | JW38: 0.79806845 | JX38: 0.01601735
A39: 35 | B39: National Bank of kenya | C39: 0.052 | D39: 0.1691 | E39: 0.0627 | F39: 0.097033253 | G39: 0.71354516 | H39: 0.015529008 | I39: 0.06 | J39: 0.1636 | K39: 0.0739 | L39: 0.083595739 | M39: 0.72468718 | N39: 0.014235133 | O39: 0.05 | P39: 0.1599 | Q39: 0.0602 | R39: 0.096961973 | S39: 0.70826648 | T39: 0.0074359745 | U39: 0.057 | V39: 0.1546 | W39: 0.0631 | X39: 0.087521374 | Y39: 0.67635313 | Z39: 0.015965142 | AA39: 0.056 | AB39: 0.1606 | AC39: 0.0703 | AD39: 0.083218612 | AE39: 0.54426213 | AF39: 0.027618573 | AG39: 0.061 | AH39: 0.1682 | AI39: 0.0597 | AJ39: 0.0766502 | AK39: 0.72719523 | AL39: 0.024646012 | AM39: 0.05 | AN39: 0.183 | AO39: 0.0801 | AP39: 0.12812115 | AQ39: 0.78501198 | AR39: -0.009536544 | AS39: 0.038 | AT39: 0.1787 | AU39: 0.0645 | AV39: 0.18530459 | AW39: 0.92963638 | AX39: 0.010786657 | AY39: 0.038 | AZ39: 0.1818 | BA39: 0.058 | BB39: 0.27713202 | BC39: 0.64353378 | BD39: 0.0051156343 | BE39: 0.044 | BF39: 0.1386 | BG39: 0.0634 | BH39: 0.33570507 | BI39: 0.68422173 | BJ39: 0.0057686876 | BK39: 0.042 | BL39: 0.1366 | BM39: 0.0635 | BN39: 0.31087615 | BO39: 0.73894749 | BP39: 0.001226749 | BQ39: 0.054 | BR39: 0.1361 | BS39: 0.1028 | BT39: 0.30594553 | BU39: 0.91532919 | BV39: 0.00097502919 | BW39: 0.033 | BX39: 0.1366 | BY39: 0.0921 | BZ39: 0.31408079 | CA39: 0.8882719 | CB39: 0.0025789484 | CC39: 0.032 | CD39: 0.1369 | CE39: 0.0706 | CF39: 0.31021527 | CG39: 0.89644898 | CH39: 0.0011188981 | CI39: 0.038 | CJ39: 0.1364 | CK39: 0.045 | CL39: 0.31319983 | CM39: 1.0571685 | CN39: 0.0033768955 | CO39: 0.052 | CP39: 0.1349 | CQ39: 0.0418 | CR39: 0.32834734 | CS39: 0.93486124 | CT39: -0.0052162854 | CU39: 0.061 | CV39: 0.1322 | CW39: 0.0428 | CX39: 0.35212324 | CY39: 0.99007377 | CZ39: -0.0027774129 | DA39: 0.053 | DB39: 0.1266 | DC39: 0.057 | DD39: 0.355981 | DE39: 0.94276967 | DF39: 0.0067265662 | DG39: 0.056 | DH39: 0.1251 | DI39: 0.0571 | DJ39: 0.36100647 | DK39: 0.90487309 | DL39: 0.0013873751 | DM39: 0.048 | DN39: 0.1251 | DO39: 0.0435 | DP39: 0.36986508 | DQ39: 0.79223219 | DR39: 0.0024068439 | DS39: 0.06 | DT39: 0.1247 | DU39: 0.057 | DV39: 0.36739455 | DW39: 0.94443775 | DX39: 0.0018737251 | DY39: 0.05 | DZ39: 0.1247 | EA39: 0.0383 | EB39: 0.36619287 | EC39: 0.90103 | ED39: 0.0045149214 | EE39: 0.051 | EF39: 0.1224 | EG39: 0.0582 | EH39: 0.31037033 | EI39: 0.86058733 | EJ39: -0.002966842 | EK39: 0.046 | EL39: 0.1209 | EM39: 0.0584 | EN39: 0.29653908 | EO39: 0.77480453 | EP39: 0.005488273 | EQ39: -0.041 | ER39: 0.1189 | ES39: 0.0459 | ET39: 0.31649115 | EU39: 0.86048244 | EV39: -0.0065954087 | EW39: -0.036 | EX39: 0.1175 | EY39: 0.042 | EZ39: 0.30472162 | FA39: 0.8265194 | FB39: 0.00096984594 | FC39: -0.003 | FD39: 0.1202 | FE39: 0.0562 | FF39: 0.28508652 | FG39: 0.80886344 | FH39: 0.0014711666 | FI39: 0.024 | FJ39: 0.1205 | FK39: 0.059 | FL39: 0.27273945 | FM39: 0.79222949 | FN39: 0.0089692298 | FO39: 0.103 | FP39: 0.1202 | FQ39: 0.0632 | FR39: 0.27497338 | FS39: 0.7435809 | FT39: 0.015525889 | FU39: 0.094 | FV39: 0.121 | FW39: 0.0691 | FX39: 0.26220512 | FY39: 0.76001368 | FZ39: 0.010411309 | GA39: 0.076 | GB39: 0.1216 | GC39: 0.0573 | GD39: 0.24833523 | GE39: 0.76254034 | GF39: 0.0073702705 | GG39: 0.059 | GH39: 0.1215 | GI39: 0.0556 | GJ39: 0.25562933 | GK39: 0.73733383 | GL39: 0.0093885634 | GM39: 0.049 | GN39: 0.1227 | GO39: 0.0791 | GP39: 0.25678285 | GQ39: 0.7349606 | GR39: 0.0092699305 | GS39: 0.046 | GT39: 0.1241 | GU39: 0.0918 | GV39: 0.20723484 | GW39: 0.76674853 | GX39: 0.0075123991 | GY39: 0.049 | GZ39: 0.1267 | HA39: 0.0906 | HB39: 0.18408247 | HC39: 0.74909695 | HD39: 0.0049757878 | HE39: 0.054 | HF39: 0.1309 | HG39: 0.0919 | HH39: 0.19623041 | HI39: 0.80531361 | HJ39: 0.0027486905 | HK39: 0.055 | HL39: 0.1331 | HM39: 0.0788 | HN39: 0.21202418 | HO39: 1.526101 | HP39: -0.052224811 | HQ39: 0.06 | HR39: 0.1398 | HS39: 0.0678 | HT39: 0.20026524 | HU39: 1.2782086 | HV39: -0.027691899 | HW39: 0.056 | HX39: 0.1463 | HY39: 0.0663 | HZ39: 0.22037207 | IA39: 1.0457908 | IB39: -0.021995268 | IC39: 0.049 | ID39: 0.1628 | IE39: 0.057 | IF39: 0.21346403 | IG39: 0.69737393 | IH39: 0.011173237 | II39: 0.046 | IJ39: 0.1685 | IK39: 0.0622 | IL39: 0.23271815 | IM39: 0.025247802 | IN39: 0.010578532 | IO39: 0.04 | IP39: 0.1691 | IQ39: 0.0356 | IR39: 0.25898002 | IS39: 0.71344939 | IT39: 0.010243069 | IU39: 0.047 | IV39: 0.1689 | IW39: 0.0299 | IX39: 0.26718928 | IY39: 0.73289539 | IZ39: 0.0064198365 | JA39: 0.049 | JB39: 0.1577 | JC39: 0.0362 | JD39: 0.28694204 | JE39: 0.70827888 | JF39: 0.0062905329 | JG39: 0.05 | JH39: 0.1528 | JI39: 0.0382 | JJ39: 0.2470439 | JK39: 0.70120125 | JL39: 0.014030951 | JM39: 0.049 | JN39: 0.1507 | JO39: 0.0458 | JP39: 0.22319075 | JQ39: 0.71467024 | JR39: 0.014178971 | JS39: 0.05 | JT39: 0.1481 | JU39: 0.0449 | JV39: 0.20512196 | JW39: 0.66804015 | JX39: 0.01537879
A40: 36 | B40: NIC Bank | C40: 0.052 | D40: 0.1691 | E40: 0.0627 | F40: 0.040431567 | G40: 0.38576915 | H40: 0.031651917 | I40: 0.06 | J40: 0.1636 | K40: 0.0739 | L40: 0.032030414 | M40: 0.3775934 | N40: 0.032660604 | O40: 0.05 | P40: 0.1599 | Q40: 0.0602 | R40: 0.033215453 | S40: 0.37887795 | T40: 0.032152786 | U40: 0.057 | V40: 0.1546 | W40: 0.0631 | X40: 0.052788479 | Y40: 0.383794 | Z40: 0.028638068 | AA40: 0.056 | AB40: 0.1606 | AC40: 0.0703 | AD40: 0.053161681 | AE40: 0.3751009 | AF40: 0.03104221 | AG40: 0.061 | AH40: 0.1682 | AI40: 0.0597 | AJ40: 0.048865734 | AK40: 0.37181664 | AL40: 0.033175687 | AM40: 0.05 | AN40: 0.183 | AO40: 0.0801 | AP40: 0.10134786 | AQ40: 0.36421535 | AR40: 0.029888226 | AS40: 0.038 | AT40: 0.1787 | AU40: 0.0645 | AV40: 0.098165152 | AW40: 0.29565293 | AX40: 0.023195707 | AY40: 0.038 | AZ40: 0.1818 | BA40: 0.058 | BB40: 0.096834005 | BC40: 0.30918068 | BD40: 0.026892164 | BE40: 0.044 | BF40: 0.1386 | BG40: 0.0634 | BH40: 0.10828505 | BI40: 0.31916045 | BJ40: 0.027100978 | BK40: 0.042 | BL40: 0.1366 | BM40: 0.0635 | BN40: 0.1005049 | BO40: 0.34318043 | BP40: 0.026001397 | BQ40: 0.054 | BR40: 0.1361 | BS40: 0.1028 | BT40: 0.096852188 | BU40: 0.34573212 | BV40: 0.022823612 | BW40: 0.033 | BX40: 0.1366 | BY40: 0.0921 | BZ40: 0.097892119 | CA40: 0.36406735 | CB40: 0.023184099 | CC40: 0.032 | CD40: 0.1369 | CE40: 0.0706 | CF40: 0.098529657 | CG40: 0.36749578 | CH40: 0.025441035 | CI40: 0.038 | CJ40: 0.1364 | CK40: 0.045 | CL40: 0.096890426 | CM40: 0.3734059 | CN40: 0.023387998 | CO40: 0.052 | CP40: 0.1349 | CQ40: 0.0418 | CR40: 0.11259453 | CS40: 0.40849865 | CT40: 0.019928339 | CU40: 0.061 | CV40: 0.1322 | CW40: 0.0428 | CX40: 0.1148535 | CY40: 0.40722396 | CZ40: 0.021413481 | DA40: 0.053 | DB40: 0.1266 | DC40: 0.057 | DD40: 0.11549134 | DE40: 0.41134533 | DF40: 0.030646948 | DG40: 0.056 | DH40: 0.1251 | DI40: 0.0571 | DJ40: 0.11012577 | DK40: 0.41435675 | DL40: 0.02272534 | DM40: 0.048 | DN40: 0.1251 | DO40: 0.0435 | DP40: 0.11086363 | DQ40: 0.42481378 | DR40: 0.021154469 | DS40: 0.06 | DT40: 0.1247 | DU40: 0.057 | DV40: 0.10894579 | DW40: 0.4183541 | DX40: 0.020544923 | DY40: 0.05 | DZ40: 0.1247 | EA40: 0.0383 | EB40: 0.11032082 | EC40: 0.41916641 | ED40: 0.022466752 | EE40: 0.051 | EF40: 0.1224 | EG40: 0.0582 | EH40: NA | EI40: NA | EJ40: NA | EK40: 0.046 | EL40: 0.1209 | EM40: 0.0584 | EN40: NA | EO40: NA | EP40: NA | EQ40: -0.041 | ER40: 0.1189 | ES40: 0.0459 | ET40: NA | EU40: NA | EV40: NA | EW40: -0.036 | EX40: 0.1175 | EY40: 0.042 | EZ40: NA | FA40: NA | FB40: NA | FC40: -0.003 | FD40: 0.1202 | FE40: 0.0562 | FF40: NA | FG40: NA | FH40: NA | FI40: 0.024 | FJ40: 0.1205 | FK40: 0.059 | FL40: NA | FM40: NA | FN40: NA | FO40: 0.103 | FP40: 0.1202 | FQ40: 0.0632 | FR40: NA | FS40: NA | FT40: NA | FU40: 0.094 | FV40: 0.121 | FW40: 0.0691 | FX40: NA | FY40: NA | FZ40: NA | GA40: 0.076 | GB40: 0.1216 | GC40: 0.0573 | GD40: NA | GE40: NA | GF40: NA | GG40: 0.059 | GH40: 0.1215 | GI40: 0.0556 | GJ40: NA | GK40: NA | GL40: NA | GM40: 0.049 | GN40: 0.1227 | GO40: 0.0791 | GP40: NA | GQ40: NA | GR40: NA | GS40: 0.046 | GT40: 0.1241 | GU40: 0.0918 | GV40: NA | GW40: NA | GX40: NA | GY40: 0.049 | GZ40: 0.1267 | HA40: 0.0906 | HB40: NA | HC40: NA | HD40: NA | HE40: 0.054 | HF40: 0.1309 | HG40: 0.0919 | HH40: NA | HI40: NA | HJ40: NA | HK40: 0.055 | HL40: 0.1331 | HM40: 0.0788 | HN40: NA | HO40: NA | HP40: NA | HQ40: 0.06 | HR40: 0.1398 | HS40: 0.0678 | HT40: NA | HU40: NA | HV40: NA | HW40: 0.056 | HX40: 0.1463 | HY40: 0.0663 | HZ40: NA | IA40: NA | IB40: NA | IC40: 0.049 | ID40: 0.1628 | IE40: 0.057 | IF40: NA | IG40: NA | IH40: NA | II40: 0.046 | IJ40: 0.1685 | IK40: 0.0622 | IL40: NA | IM40: NA | IN40: NA | IO40: 0.04 | IP40: 0.1691 | IQ40: 0.0356 | IR40: NA | IS40: NA | IT40: NA | IU40: 0.047 | IV40: 0.1689 | IW40: 0.0299 | IX40: NA | IY40: NA | IZ40: NA | JA40: 0.049 | JB40: 0.1577 | JC40: 0.0362 | JD40: NA | JE40: NA | JF40: NA | JG40: 0.05 | JH40: 0.1528 | JI40: 0.0382 | JJ40: NA | JK40: NA | JL40: NA | JM40: 0.049 | JN40: 0.1507 | JO40: 0.0458 | JP40: NA | JQ40: NA | JR40: NA | JS40: 0.05 | JT40: 0.1481 | JU40: 0.0449 | JV40: NA | JW40: NA | JX40: NA
A41: 37 | B41: M-Oriental Bank Limited | C41: 0.052 | D41: 0.1691 | E41: 0.0627 | F41: 0.082985472 | G41: 0.70848342 | H41: 0.013140977 | I41: 0.06 | J41: 0.1636 | K41: 0.0739 | L41: 0.083595434 | M41: 0.67887035 | N41: 0.014431257 | O41: 0.05 | P41: 0.1599 | Q41: 0.0602 | R41: 0.089623468 | S41: 0.67047427 | T41: 0.0096806771 | U41: 0.057 | V41: 0.1546 | W41: 0.0631 | X41: 0.086972267 | Y41: 0.77576134 | Z41: 0.0075844811 | AA41: 0.056 | AB41: 0.1606 | AC41: 0.0703 | AD41: 0.087786623 | AE41: 0.78223756 | AF41: 0.0080886708 | AG41: 0.061 | AH41: 0.1682 | AI41: 0.0597 | AJ41: 0.10694913 | AK41: 0.73957141 | AL41: 0.0096663161 | AM41: 0.05 | AN41: 0.183 | AO41: 0.0801 | AP41: 0.12217001 | AQ41: 0.74274906 | AR41: 0.0052467108 | AS41: 0.038 | AT41: 0.1787 | AU41: 0.0645 | AV41: 0.11466044 | AW41: 0.78592787 | AX41: 0.010045718 | AY41: 0.038 | AZ41: 0.1818 | BA41: 0.058 | BB41: 0.096520751 | BC41: 0.73608339 | BD41: 0.0068385117 | BE41: 0.044 | BF41: 0.1386 | BG41: 0.0634 | BH41: 0.10421542 | BI41: 0.73227297 | BJ41: 0.0047008434 | BK41: 0.042 | BL41: 0.1366 | BM41: 0.0635 | BN41: 0.18639312 | BO41: 0.60322805 | BP41: 0.003658222 | BQ41: 0.054 | BR41: 0.1361 | BS41: 0.1028 | BT41: 0.099872023 | BU41: 0.71832334 | BV41: 0.00986606 | BW41: 0.033 | BX41: 0.1366 | BY41: 0.0921 | BZ41: 0.09472038 | CA41: 0.70468532 | CB41: 0.011141523 | CC41: 0.032 | CD41: 0.1369 | CE41: 0.0706 | CF41: 0.087417594 | CG41: 0.69188434 | CH41: 0.011636455 | CI41: 0.038 | CJ41: 0.1364 | CK41: 0.045 | CL41: 0.092240379 | CM41: 0.63832499 | CN41: 0.0094170926 | CO41: 0.052 | CP41: 0.1349 | CQ41: 0.0418 | CR41: 0.08776997 | CS41: 0.70015236 | CT41: 0.0075356269 | CU41: 0.061 | CV41: 0.1322 | CW41: 0.0428 | CX41: 0.087622262 | CY41: 0.75114068 | CZ41: 0.0059408372 | DA41: 0.053 | DB41: 0.1266 | DC41: 0.057 | DD41: 0.088752534 | DE41: 0.73680622 | DF41: 0.0096409798 | DG41: 0.056 | DH41: 0.1251 | DI41: 0.0571 | DJ41: 0.085913743 | DK41: 0.63784726 | DL41: 0.0078179213 | DM41: 0.048 | DN41: 0.1251 | DO41: 0.0435 | DP41: 0.13446692 | DQ41: 0.82317541 | DR41: 0.0032608505 | DS41: 0.06 | DT41: 0.1247 | DU41: 0.057 | DV41: 0.13863052 | DW41: 0.7826046 | DX41: 0.0050009078 | DY41: 0.05 | DZ41: 0.1247 | EA41: 0.0383 | EB41: 0.13688448 | EC41: 0.78058175 | ED41: 0.0051202612 | EE41: 0.051 | EF41: 0.1224 | EG41: 0.0582 | EH41: 0.16187231 | EI41: 0.69093458 | EJ41: -0.0019161203 | EK41: 0.046 | EL41: 0.1209 | EM41: 0.0584 | EN41: 0.16002547 | EO41: 0.84237065 | EP41: 0.0018633545 | EQ41: -0.041 | ER41: 0.1189 | ES41: 0.0459 | ET41: 0.16353229 | EU41: 0.82777558 | EV41: 0.0022909221 | EW41: -0.036 | EX41: 0.1175 | EY41: 0.042 | EZ41: 0.17077977 | FA41: 0.77634833 | FB41: 0.0036424384 | FC41: -0.003 | FD41: 0.1202 | FE41: 0.0562 | FF41: 0.19541171 | FG41: 0.53184001 | FH41: 0.0021778738 | FI41: 0.024 | FJ41: 0.1205 | FK41: 0.059 | FL41: 0.19984135 | FM41: 0.79281549 | FN41: 0.0016743845 | FO41: 0.103 | FP41: 0.1202 | FQ41: 0.0632 | FR41: 0.20916058 | FS41: 0.78934846 | FT41: 0.0022778552 | FU41: 0.094 | FV41: 0.121 | FW41: 0.0691 | FX41: 0.20983861 | FY41: 0.73114147 | FZ41: 0.0015981419 | GA41: 0.076 | GB41: 0.1216 | GC41: 0.0573 | GD41: 0.22049549 | GE41: 0.52547903 | GF41: 0.003523719 | GG41: 0.059 | GH41: 0.1215 | GI41: 0.0556 | GJ41: 0.20819278 | GK41: 0.74808633 | GL41: 0.0052146291 | GM41: 0.049 | GN41: 0.1227 | GO41: 0.0791 | GP41: 0.17868846 | GQ41: 0.46766492 | GR41: 0.010435114 | GS41: 0.046 | GT41: 0.1241 | GU41: 0.0918 | GV41: 0.16960338 | GW41: 0.51130107 | GX41: 0.0099483047 | GY41: 0.049 | GZ41: 0.1267 | HA41: 0.0906 | HB41: 0.17607164 | HC41: 0.4070866 | HD41: 0.0095893331 | HE41: 0.054 | HF41: 0.1309 | HG41: 0.0919 | HH41: 0.16940213 | HI41: 0.62959968 | HJ41: 0.0094310746 | HK41: 0.055 | HL41: 0.1331 | HM41: 0.0788 | HN41: 0.17502363 | HO41: 0.59854569 | HP41: 0.011177012 | HQ41: 0.06 | HR41: 0.1398 | HS41: 0.0678 | HT41: 0.26511801 | HU41: 0.60467789 | HV41: 0.010579478 | HW41: 0.056 | HX41: 0.1463 | HY41: 0.0663 | HZ41: 0.21245218 | IA41: 0.50265566 | IB41: 0.01008192 | IC41: 0.049 | ID41: 0.1628 | IE41: 0.057 | IF41: 0.21026756 | IG41: 0.6411405 | IH41: 0.007493249 | II41: 0.046 | IJ41: 0.1685 | IK41: 0.0622 | IL41: 0.21001623 | IM41: 0.57528135 | IN41: 0.011604942 | IO41: 0.04 | IP41: 0.1691 | IQ41: 0.0356 | IR41: 0.22394319 | IS41: 0.56631867 | IT41: 0.0133309 | IU41: 0.047 | IV41: 0.1689 | IW41: 0.0299 | IX41: 0.22764286 | IY41: 0.50125265 | IZ41: 0.011428501 | JA41: 0.049 | JB41: 0.1577 | JC41: 0.0362 | JD41: 0.23521982 | JE41: 0.64473299 | JF41: 0.012339761 | JG41: 0.05 | JH41: 0.1528 | JI41: 0.0382 | JJ41: 0.21536361 | JK41: 0.63572353 | JL41: 0.013247162 | JM41: 0.049 | JN41: 0.1507 | JO41: 0.0458 | JP41: 0.21266225 | JQ41: 0.62790801 | JR41: 0.014000335 | JS41: 0.05 | JT41: 0.1481 | JU41: 0.0449 | JV41: 0.25933548 | JW41: 0.56298209 | JX41: 0.014903685
A42: 38 | B42: Paramount Universal Bank | C42: 0.052 | D42: 0.1691 | E42: 0.0627 | F42: 0.092310074 | G42: 0.63399339 | H42: 0.017260972 | I42: 0.06 | J42: 0.1636 | K42: 0.0739 | L42: 0.074218505 | M42: 0.58754689 | N42: 0.021175711 | O42: 0.05 | P42: 0.1599 | Q42: 0.0602 | R42: 0.061970757 | S42: 0.66083818 | T42: 0.013434283 | U42: 0.057 | V42: 0.1546 | W42: 0.0631 | X42: 0.047136908 | Y42: 0.68748917 | Z42: 0.014923703 | AA42: 0.056 | AB42: 0.1606 | AC42: 0.0703 | AD42: 0.0407858 | AE42: 0.59879964 | AF42: 0.018021134 | AG42: 0.061 | AH42: 0.1682 | AI42: 0.0597 | AJ42: 0.050377112 | AK42: 0.57298553 | AL42: 0.019376338 | AM42: 0.05 | AN42: 0.183 | AO42: 0.0801 | AP42: 0.049362207 | AQ42: 0.64623998 | AR42: 0.015101752 | AS42: 0.038 | AT42: 0.1787 | AU42: 0.0645 | AV42: 0.10854303 | AW42: 0.66710019 | AX42: 0.015249105 | AY42: 0.038 | AZ42: 0.1818 | BA42: 0.058 | BB42: 0.10752642 | BC42: 0.72834844 | BD42: 0.013921571 | BE42: 0.044 | BF42: 0.1386 | BG42: 0.0634 | BH42: 0.10316446 | BI42: 0.9819409 | BJ42: 0.010462659 | BK42: 0.042 | BL42: 0.1366 | BM42: 0.0635 | BN42: 0.076434165 | BO42: 7.6857077 | BP42: 0.010654029 | BQ42: 0.054 | BR42: 0.1361 | BS42: 0.1028 | BT42: 0.091900488 | BU42: 0.65733482 | BV42: 0.0063162291 | BW42: 0.033 | BX42: 0.1366 | BY42: 0.0921 | BZ42: 0.076780656 | CA42: 0.69153888 | CB42: 0.0091431075 | CC42: 0.032 | CD42: 0.1369 | CE42: 0.0706 | CF42: 0.079352858 | CG42: 0.71097108 | CH42: 0.010033311 | CI42: 0.038 | CJ42: 0.1364 | CK42: 0.045 | CL42: 0.095522138 | CM42: 0.69373651 | CN42: 0.01234889 | CO42: 0.052 | CP42: 0.1349 | CQ42: 0.0418 | CR42: 0.10219004 | CS42: 0.77181641 | CT42: 0.010427138 | CU42: 0.061 | CV42: 0.1322 | CW42: 0.0428 | CX42: 0.10099744 | CY42: 0.80620557 | CZ42: 0.0099256649 | DA42: 0.053 | DB42: 0.1266 | DC42: 0.057 | DD42: 0.10144103 | DE42: 0.77431373 | DF42: 0.0093777982 | DG42: 0.056 | DH42: 0.1251 | DI42: 0.0571 | DJ42: 0.11648263 | DK42: 0.71958397 | DL42: 0.024270951 | DM42: 0.048 | DN42: 0.1251 | DO42: 0.0435 | DP42: 0.11233999 | DQ42: 0.79171672 | DR42: 0.0093761377 | DS42: 0.06 | DT42: 0.1247 | DU42: 0.057 | DV42: 0.10799044 | DW42: 0.80688245 | DX42: 0.0083610995 | DY42: 0.05 | DZ42: 0.1247 | EA42: 0.0383 | EB42: 0.10263804 | EC42: 0.81729794 | ED42: 0.008419291 | EE42: 0.051 | EF42: 0.1224 | EG42: 0.0582 | EH42: 0.10805166 | EI42: 0.78982012 | EJ42: 0.0089469607 | EK42: 0.046 | EL42: 0.1209 | EM42: 0.0584 | EN42: 0.10260625 | EO42: 0.73395115 | EP42: 0.010383943 | EQ42: -0.041 | ER42: 0.1189 | ES42: 0.0459 | ET42: 0.10317386 | EU42: 0.70952424 | EV42: 0.010037605 | EW42: -0.036 | EX42: 0.1175 | EY42: 0.042 | EZ42: 0.10904036 | FA42: 0.66886265 | FB42: 0.0080021065 | FC42: -0.003 | FD42: 0.1202 | FE42: 0.0562 | FF42: 0.10151735 | FG42: 0.63048112 | FH42: 0.012369847 | FI42: 0.024 | FJ42: 0.1205 | FK42: 0.059 | FL42: 0.10172129 | FM42: 0.64341686 | FN42: 0.010383604 | FO42: 0.103 | FP42: 0.1202 | FQ42: 0.0632 | FR42: 0.079556582 | FS42: 0.62717958 | FT42: 0.010601759 | FU42: 0.094 | FV42: 0.121 | FW42: 0.0691 | FX42: 0.09479302 | FY42: 0.61004837 | FZ42: 0.010157444 | GA42: 0.076 | GB42: 0.1216 | GC42: 0.0573 | GD42: 0.097356509 | GE42: 0.60977133 | GF42: 0.012521403 | GG42: 0.059 | GH42: 0.1215 | GI42: 0.0556 | GJ42: 0.096490064 | GK42: 0.57441614 | GL42: 0.01294124 | GM42: 0.049 | GN42: 0.1227 | GO42: 0.0791 | GP42: 0.098234895 | GQ42: 0.5776176 | GR42: 0.013941831 | GS42: 0.046 | GT42: 0.1241 | GU42: 0.0918 | GV42: 0.095306664 | GW42: 0.55658947 | GX42: 0.015206669 | GY42: 0.049 | GZ42: 0.1267 | HA42: 0.0906 | HB42: 0.092060307 | HC42: 0.55457529 | HD42: 0.017276593 | HE42: 0.054 | HF42: 0.1309 | HG42: 0.0919 | HH42: 0.091469901 | HI42: 0.45393176 | HJ42: 0.017515931 | HK42: 0.055 | HL42: 0.1331 | HM42: 0.0788 | HN42: 0.086724718 | HO42: 0.43196515 | HP42: 0.020095249 | HQ42: 0.06 | HR42: 0.1398 | HS42: 0.0678 | HT42: 0.080305799 | HU42: 0.49289586 | HV42: 0.018103673 | HW42: 0.056 | HX42: 0.1463 | HY42: 0.0663 | HZ42: 0.070436153 | IA42: 0.50472837 | IB42: 0.019932599 | IC42: 0.049 | ID42: 0.1628 | IE42: 0.057 | IF42: 0.071834204 | IG42: 0.60584975 | IH42: 0.018847636 | II42: 0.046 | IJ42: 0.1685 | IK42: 0.0622 | IL42: 0.071159857 | IM42: 0.61139955 | IN42: 0.019516133 | IO42: 0.04 | IP42: 0.1691 | IQ42: 0.0356 | IR42: 0.070718266 | IS42: 0.58454175 | IT42: 0.019750929 | IU42: 0.047 | IV42: 0.1689 | IW42: 0.0299 | IX42: 0.11354103 | IY42: 0.59153185 | IZ42: 0.021563044 | JA42: 0.049 | JB42: 0.1577 | JC42: 0.0362 | JD42: 0.11794578 | JE42: 0.55238122 | JF42: 0.022739331 | JG42: 0.05 | JH42: 0.1528 | JI42: 0.0382 | JJ42: 0.12616866 | JK42: 0.4998548 | JL42: 0.01945301 | JM42: 0.049 | JN42: 0.1507 | JO42: 0.0458 | JP42: 0.12534259 | JQ42: 0.3274585 | JR42: 0.019319945 | JS42: 0.05 | JT42: 0.1481 | JU42: 0.0449 | JV42: 0.17363615 | JW42: 0.32122897 | JX42: 0.022368345
A43: 39 | B43: Prime Bank | C43: 0.052 | D43: 0.1691 | E43: 0.0627 | F43: 0.017221312 | G43: 0.39032304 | H43: 0.032444606 | I43: 0.06 | J43: 0.1636 | K43: 0.0739 | L43: 0.01477536 | M43: 0.48219494 | N43: 0.034096625 | O43: 0.05 | P43: 0.1599 | Q43: 0.0602 | R43: 0.013210163 | S43: 0.3920813 | T43: 0.033263899 | U43: 0.057 | V43: 0.1546 | W43: 0.0631 | X43: 0.012746154 | Y43: 0.40225411 | Z43: 0.033465669 | AA43: 0.056 | AB43: 0.1606 | AC43: 0.0703 | AD43: 0.01380115 | AE43: 0.3877389 | AF43: 0.031801925 | AG43: 0.061 | AH43: 0.1682 | AI43: 0.0597 | AJ43: 0.01496941 | AK43: 0.37406821 | AL43: 0.034046884 | AM43: 0.05 | AN43: 0.183 | AO43: 0.0801 | AP43: 0.016712708 | AQ43: 0.39155107 | AR43: 0.033742597 | AS43: 0.038 | AT43: 0.1787 | AU43: 0.0645 | AV43: 0.016266905 | AW43: 0.47802415 | AX43: 0.026720042 | AY43: 0.038 | AZ43: 0.1818 | BA43: 0.058 | BB43: 0.028019539 | BC43: 0.42340964 | BD43: 0.028192278 | BE43: 0.044 | BF43: 0.1386 | BG43: 0.0634 | BH43: 0.028022686 | BI43: 0.4264003 | BJ43: 0.027892735 | BK43: 0.042 | BL43: 0.1366 | BM43: 0.0635 | BN43: 0.034904403 | BO43: 0.43982444 | BP43: 0.029213184 | BQ43: 0.054 | BR43: 0.1361 | BS43: 0.1028 | BT43: 0.028196787 | BU43: 0.48596398 | BV43: 0.025376384 | BW43: 0.033 | BX43: 0.1366 | BY43: 0.0921 | BZ43: 0.029156793 | CA43: 0.47693643 | CB43: 0.026265278 | CC43: 0.032 | CD43: 0.1369 | CE43: 0.0706 | CF43: 0.032365207 | CG43: 0.47148373 | CH43: 0.026155037 | CI43: 0.038 | CJ43: 0.1364 | CK43: 0.045 | CL43: 0.046550668 | CM43: 0.50030725 | CN43: 0.025985209 | CO43: 0.052 | CP43: 0.1349 | CQ43: 0.0418 | CR43: 0.056034889 | CS43: 0.49520783 | CT43: 0.024638169 | CU43: 0.061 | CV43: 0.1322 | CW43: 0.0428 | CX43: 0.060243913 | CY43: 0.49496313 | CZ43: 0.02255939 | DA43: 0.053 | DB43: 0.1266 | DC43: 0.057 | DD43: 0.067684162 | DE43: 0.48375239 | DF43: 0.026224188 | DG43: 0.056 | DH43: 0.1251 | DI43: 0.0571 | DJ43: 0.057359255 | DK43: 0.51047805 | DL43: 0.023104479 | DM43: 0.048 | DN43: 0.1251 | DO43: 0.0435 | DP43: 0.066063394 | DQ43: 0.47708369 | DR43: 0.023735675 | DS43: 0.06 | DT43: 0.1247 | DU43: 0.057 | DV43: 0.083398484 | DW43: 0.47017488 | DX43: 0.023479207 | DY43: 0.05 | DZ43: 0.1247 | EA43: 0.0383 | EB43: 0.096894075 | EC43: 0.45961421 | ED43: 0.023409497 | EE43: 0.051 | EF43: 0.1224 | EG43: 0.0582 | EH43: 0.092584492 | EI43: 0.48629354 | EJ43: 0.023573145 | EK43: 0.046 | EL43: 0.1209 | EM43: 0.0584 | EN43: 0.104286 | EO43: 0.46222798 | EP43: 0.023087449 | EQ43: -0.041 | ER43: 0.1189 | ES43: 0.0459 | ET43: 0.096888859 | EU43: 0.48350724 | EV43: 0.02139593 | EW43: -0.036 | EX43: 0.1175 | EY43: 0.042 | EZ43: 0.094967382 | FA43: 0.47058169 | FB43: 0.021382486 | FC43: -0.003 | FD43: 0.1202 | FE43: 0.0562 | FF43: 0.098977154 | FG43: 0.47714817 | FH43: 0.019017269 | FI43: 0.024 | FJ43: 0.1205 | FK43: 0.059 | FL43: 0.095420248 | FM43: 0.47530977 | FN43: 0.022621059 | FO43: 0.103 | FP43: 0.1202 | FQ43: 0.0632 | FR43: 0.11051855 | FS43: 0.47404513 | FT43: 0.022963455 | FU43: 0.094 | FV43: 0.121 | FW43: 0.0691 | FX43: 0.11181285 | FY43: 0.43877383 | FZ43: 0.024692947 | GA43: 0.076 | GB43: 0.1216 | GC43: 0.0573 | GD43: 0.10281702 | GE43: 0.43197427 | GF43: 0.025169285 | GG43: 0.059 | GH43: 0.1215 | GI43: 0.0556 | GJ43: 0.10223443 | GK43: 0.45665643 | GL43: 0.024065803 | GM43: 0.049 | GN43: 0.1227 | GO43: 0.0791 | GP43: 0.099102205 | GQ43: 0.43688949 | GR43: 0.025803862 | GS43: 0.046 | GT43: 0.1241 | GU43: 0.0918 | GV43: 0.089242252 | GW43: 0.42196131 | GX43: 0.027019753 | GY43: 0.049 | GZ43: 0.1267 | HA43: 0.0906 | HB43: 0.10921465 | HC43: 0.058400651 | HD43: 0.026536864 | HE43: 0.054 | HF43: 0.1309 | HG43: 0.0919 | HH43: 0.097680099 | HI43: 0.12070895 | HJ43: 0.028226871 | HK43: 0.055 | HL43: 0.1331 | HM43: 0.0788 | HN43: 0.095287305 | HO43: 0.45194024 | HP43: 0.028212031 | HQ43: 0.06 | HR43: 0.1398 | HS43: 0.0678 | HT43: 0.088259825 | HU43: 0.43982299 | HV43: 0.028055548 | HW43: 0.056 | HX43: 0.1463 | HY43: 0.0663 | HZ43: 0.084856925 | IA43: 0.44908376 | IB43: 0.027634081 | IC43: 0.049 | ID43: 0.1628 | IE43: 0.057 | IF43: 0.081590409 | IG43: 0.43225434 | IH43: 0.028083685 | II43: 0.046 | IJ43: 0.1685 | IK43: 0.0622 | IL43: 0.08378695 | IM43: 0.44859445 | IN43: 0.026682309 | IO43: 0.04 | IP43: 0.1691 | IQ43: 0.0356 | IR43: 0.086073693 | IS43: 0.44858229 | IT43: 0.025848258 | IU43: 0.047 | IV43: 0.1689 | IW43: 0.0299 | IX43: 0.081151701 | IY43: 0.47309927 | IZ43: 0.023818977 | JA43: 0.049 | JB43: 0.1577 | JC43: 0.0362 | JD43: 0.082292582 | JE43: 0.45806975 | JF43: 0.026727813 | JG43: 0.05 | JH43: 0.1528 | JI43: 0.0382 | JJ43: 0.069624996 | JK43: 0.44545612 | JL43: 0.026199053 | JM43: 0.049 | JN43: 0.1507 | JO43: 0.0458 | JP43: 0.068443821 | JQ43: 0.42322715 | JR43: 0.026487395 | JS43: 0.05 | JT43: 0.1481 | JU43: 0.0449 | JV43: 0.073484414 | JW43: 0.48621263 | JX43: 0.022608867
